Workbook
Name _______bot1: #REF!
Name _______bot3: #REF!
Name _______bot4: #REF!
Name _______bot5: #REF!
Name _______bot6: #REF!
Name _______top1: #REF!
Name _______top2: #REF!
Name _______top3: #REF!
Name _______top4: #REF!
Name _______top5: #REF!
Name _______top6: #REF!
Name ______bot2: #REF!
Name _____bot1: #REF!
Name _____bot3: #REF!
Name _____bot4: #REF!
Name _____bot5: #REF!
Name _____bot6: #REF!
Name _____top1: #REF!
Name _____top2: #REF!
Name _____top3: #REF!
Name _____top4: #REF!
Name _____top5: #REF!
Name _____top6: #REF!
Name ____bot1: #REF!
Name ____bot2: #REF!
Name ____bot3: #REF!
Name ____bot4: #REF!
Name ____bot5: #REF!
Name ____bot6: #REF!
Name ____top1: #REF!
Name ____top2: #REF!
Name ____top3: #REF!
Name ____top4: #REF!
Name ____top5: #REF!
Name ____top6: #REF!
Name ___bot1: #REF!
Name ___bot2: #REF!
Name ___bot3: #REF!
Name ___bot4: #REF!
Name ___bot5: #REF!
Name ___bot6: #REF!
Name ___top1: #REF!
Name ___top2: #REF!
Name ___top3: #REF!
Name ___top4: #REF!
Name ___top5: #REF!
Name ___top6: #REF!
Name __bot1: #REF!
Name __bot2: #REF!
Name __bot3: #REF!
Name __bot4: #REF!
Name __bot5: #REF!
Name __bot6: #REF!
Name __top1: #REF!
Name __top2: #REF!
Name __top3: #REF!
Name __top4: #REF!
Name __top5: #REF!
Name __top6: #REF!
Name _bot1: #REF!

Sheet How to update
B2: How to update
B3: 1. | C3: Navigate to the tabs included in the 'Data Links' tab at the bottom of this spreadsheet
B4: 2. | C4: Starting with the first link, download the data and open the downloaded spreadsheet
B5: 3. | C5: In the downloaded spreadsheet, find the tab that contains the same data as the tab in this spreadsheet that you are trying to update and copy all of the data and only the data
B6: 4. | C6: Line the first month of the copied data up with the first month in the tab you are hoping to update and paste the new data on top of it, overwriting the old data (i.e. July 2014 should be pasted on top of July 2014)
B7: 5. | C7: Repeat for all tabs until the spreadsheet is completely updated
B8: 6. | C8: Do a quick comparison with the ONS published stats to make sure all the formulas are pulling through correctly
B9: 7. | C9: To update the dashboard, ensure the yellow date box in the top left hand corner of the dashboard tab is set to the correct value

Sheet Data links
B2: Tab | C2: Data link (August - Make sure to download most recent month!!!)
B3: 1. Payrolled employees | C3: https://www.ons.gov.uk/employmentandlabourmarket/peopleinwork/earningsandworkinghours/datasets/realtimeinformationstatisticsreferencetableseasonallyadjusted
B4: 23. Employees Industry
B5: 2, 5, 10, 11, 13, 15, 18, 20, 21 | C5: A01: Summary of labour market statistics - Office for National Statistics
B6: 1 UK (Claimant count) | C6: CLA01: Claimant Count - Office for National Statistics
B7: Real Average Weekly Earnings (using CPI) | C7: X09: Real average weekly earnings using consumer price inflation (seasonally adjusted) - Office for National Statistics
B8: Redundancies | C8: HR1: Potential redundancies - Office for National Statistics
B9: Labour market flows | C9: X02: Labour Force Survey flows estimates

Sheet Dashboard
B1: Aug-Oct | L1: Dropdowns: | M1: Month | N1: Offset Count | O1: Year
A2: Year | B2: 2025 | M2: Nov-Jan | N2: 13 | O2: 2022
A3: Offset factor | B3: =((VLOOKUP(B1,$M$2:$N$13, 2, FALSE)-0)+((Dashboard!B2-2024)*12)) | M3: Dec-Feb | N3: =N2+1 | O3: 2023
M4: Jan-Mar | N4: =N3+1 | O4: 2024
B5: {{LFS_PERIOD}} | D5: Current | E5: Change on quarter | F5: Change on the year | G5: Change since Covid-20 | I5: Good or Bad' formatting? | K5: For data showing percentage point change | M5: Feb-Apr | N5: =N4+1 | O5: 2025
B6: Employment (000s) 16+ | D6: {{EMP16_CUR}} | E6: {{EMP16_DQ}} | F6: {{EMP16_DY}} | G6: {{EMP16_DC}} | I6: Minus = Bad | M6: Mar-May | N6: =N5+1 | O6: 2026
B7: Employment rate (16-64) | D7: {{EMP_RT_CUR}} | E7: {{EMP_RT_DQ}} | F7: {{EMP_RT_DY}} | G7: {{EMP_RT_DC}} | I7: Minus = Bad | K7: Add 'pp' in brief | M7: Apr-Jun | N7: =N6+1 | O7: 2027
B8: Unemployment, 16+ (000s) | D8: {{UNEMP16_CUR}} | E8: {{UNEMP16_DQ}} | F8: {{UNEMP16_DY}} | G8: {{UNEMP16_DC}} | I8: Minus = Good | M8: May-Jul | N8: =N7+1 | O8: 2028
B9: Unemployment rate, 16+ | D9: {{UNEMP_RT_CUR}} | E9: {{UNEMP_RT_DQ}} | F9: {{UNEMP_RT_DY}} | G9: {{UNEMP_RT_DC}} | I9: Minus = Good | K9: Add 'pp' in brief | M9: Jun-Aug | N9: =N8+1 | O9: 2029
B10: Economic inactivity (000s) (16-64) | D10: {{INACT_CUR}} | E10: {{INACT_DQ}} | F10: {{INACT_DY}} | G10: {{INACT_DC}} | I10: Minus = Good | M10: Jul-Sep | N10: =N9+1 | O10: 2030
B11: Economic inactivity rate (16-64) | D11: {{INACT_RT_CUR}} | E11: {{INACT_RT_DQ}} | F11: {{INACT_RT_DY}} | G11: {{INACT_RT_DC}} | I11: Minus = Good | K11: Add 'pp' in brief | M11: Aug-Oct | N11: =N10+1
B12: 50-64s inactivity (000s) | D12: {{INACT5064_CUR}} | E12: {{INACT5064_DQ}} | F12: {{INACT5064_DY}} | G12: {{INACT5064_DC}} | I12: Minus = Good | M12: Sep-Nov | N12: =N11+1
B13: 50-64s inactivity rate | D13: {{INACT5064_RT_CUR}} | E13: {{INACT5064_RT_DQ}} | F13: {{INACT5064_RT_DY}} | G13: {{INACT5064_RT_DC}} | I13: Minus = Good | K13: Add 'pp' in brief | M13: Oct-Dec | N13: =N12+1
B14: Provisional December 2024 HMRC Payroll employees (000s) | D14: {{PAYROLL_CUR}} | E14: {{PAYROLL_DQ}} | F14: {{PAYROLL_DY}} | G14: {{PAYROLL_DC}} | I14: Minus = Bad
A15: *note: covid period is different (Jan-Mar) due to reporting periods | B15: Provisional Nov 2024-Jan 2025 Vacancies (000s) | D15: {{VAC_CUR}} | E15: {{VAC_DQ}} | F15: {{VAC_DY}} | G15: {{VAC_DC}} | I15: Do not format
B16: Wage growth in cash terms (total pay, including bonuses, yearly % change) | C16: Change in annual earnings | D16: {{WAGES_CUR}} | E16: {{WAGES_DQ}} | F16: {{WAGES_DY}} | G16: {{WAGES_DC}} | I16: Minus = Bad
B17: Wage growth adjusted for inflation (total pay, including bonuses, yearly % change) | D17: {{WAGES_CPI_CUR}} | E17: {{WAGES_CPI_DQ}} | F17: {{WAGES_CPI_DY}} | G17: {{WAGES_CPI_DC}} | I17: Minus = Bad

Sheet 1. Payrolled employees (UK)
B1: Current | C1: Change on month (singular) | D1: Change on quarter | E1: Change year on year | F1: Change since Covid-19 | G1: Change since 2024 election | H1: Change since coming into office | I1: Change since start of the year | J1: Max
A2: Number | B2: {{PAYROLL_CUR}} | C2: {=INDEX($B$11:$B$1048576,COUNTA($B$11:$B$1048576))-INDEX($B$11:$B$1048576,COUNTA($B$11:$B$1048576)-1)} | D2: {{PAYROLL_DQ}} | E2: {{PAYROLL_DY}} | F2: {{PAYROLL_DC}} | G2: {{PAYROLL_DE}} | H2: {=INDEX($B$11:$B$1048576,COUNTA($B$11:$B$1048576))-$B$130} | I2: {=INDEX(B$11:B$1048576,COUNTA(B$11:B$1048576))-_xlfn.XLOOKUP("January " & TEXT(TODAY(),"yyyy"),A$11:A$1048576,B$11:B$1048576)} | J2: =MAX($B$11:$B$1048576)
A3: % | C3: {=INDEX($B$11:$B$1048576,COUNTA($B$11:$B$1048576))/INDEX($B$11:$B$1048576,COUNTA($B$11:$B$1048576)-1)-1} | D3: =AVERAGE(OFFSET(INDEX($B$11:$B$1048576,COUNTA($B$11:$B$1048576)),-2,0,3,1))/AVERAGE(OFFSET(INDEX($B$11:$B$1048576,COUNTA($B$11:$B$1048576)),-5,0,3,1))-1 | E3: =AVERAGE(OFFSET(INDEX($B$11:$B$1048576,COUNTA($B$11:$B$1048576)),-2,0,3,1))/AVERAGE(OFFSET(INDEX($B$11:$B$1048576,COUNTA($B$11:$B$1048576)),-14,0,3,1))-1 | F3: {=INDEX($B$11:$B$1048576,COUNTA($B$11:$B$1048576))/AVERAGE($B$76:$B$78)-1} | G3: =AVERAGE(OFFSET(INDEX($B$11:$B$1048576,COUNTA($B$11:$B$1048576)),-2,0,3,1))/AVERAGE($B$128:$B$130)-1 | H3: {=INDEX($B$11:$B$1048576,COUNTA($B$11:$B$1048576))/$B$130-1} | I3: {=INDEX(B$11:B$1048576,COUNTA(B$11:B$1048576))/_xlfn.XLOOKUP("January " & TEXT(TODAY(),"yyyy"),A$11:A$1048576,B$11:B$1048576)-1}
A5: 1. Payrolled employee counts from PAYE RTI
A6: UK, all industries, seasonally adjusted
A8: Units | B8: Payrolled employees
A10: Date | B10: Payrolled employees | C10: Change on previous month

Sheet 23. Employees Industry
A1: Yearly change | B1: Agriculture, forestry and fishing | C1: Mining and quarrying | D1: Manufacturing | E1: Energy production and supply | F1: Water supply, sewerage and waste | G1: Construction | H1: Wholesale and retail; repair of motor vehicles | I1: Transportation and storage | J1: Accommodation and food service activities | K1: Information and communication | L1: Finance and insurance | M1: Real estate | N1: Professional, scientific and technical | O1: Administrative and support services | P1: Public administration and defence; social security | Q1: Education | R1: Health and social work | S1: Arts, entertainment and recreation | T1: Other service activities | U1: Households and Extraterritorial | V1: UK
A2: Number | B2: {=INDEX(B$12:B$1048576,COUNTA(B$12:B$1048576))-INDEX(B$12:B$1048576,COUNTA(B$12:B$1048576)-12)} | C2: {=INDEX(C$12:C$1048576,COUNTA(C$12:C$1048576))-INDEX(C$12:C$1048576,COUNTA(C$12:C$1048576)-12)} | D2: {=INDEX(D$12:D$1048576,COUNTA(D$12:D$1048576))-INDEX(D$12:D$1048576,COUNTA(D$12:D$1048576)-12)} | E2: {=INDEX(E$12:E$1048576,COUNTA(E$12:E$1048576))-INDEX(E$12:E$1048576,COUNTA(E$12:E$1048576)-12)} | F2: {=INDEX(F$12:F$1048576,COUNTA(F$12:F$1048576))-INDEX(F$12:F$1048576,COUNTA(F$12:F$1048576)-12)} | G2: {=INDEX(G$12:G$1048576,COUNTA(G$12:G$1048576))-INDEX(G$12:G$1048576,COUNTA(G$12:G$1048576)-12)} | H2: {=INDEX(H$12:H$1048576,COUNTA(H$12:H$1048576))-INDEX(H$12:H$1048576,COUNTA(H$12:H$1048576)-12)} | I2: {=INDEX(I$12:I$1048576,COUNTA(I$12:I$1048576))-INDEX(I$12:I$1048576,COUNTA(I$12:I$1048576)-12)} | ... V2: {=INDEX(V$12:V$1048576,COUNTA(V$12:V$1048576))-INDEX(V$12:V$1048576,COUNTA(V$12:V$1048576)-12)}
A3: % | B3: {=INDEX(B$12:B$1048576,COUNTA(B$12:B$1048576))/INDEX(B$12:B$1048576,COUNTA(B$12:B$1048576)-12)-1} | C3: {=INDEX(C$12:C$1048576,COUNTA(C$12:C$1048576))/INDEX(C$12:C$1048576,COUNTA(C$12:C$1048576)-12)-1} | D3: {=INDEX(D$12:D$1048576,COUNTA(D$12:D$1048576))/INDEX(D$12:D$1048576,COUNTA(D$12:D$1048576)-12)-1} | E3: {=INDEX(E$12:E$1048576,COUNTA(E$12:E$1048576))/INDEX(E$12:E$1048576,COUNTA(E$12:E$1048576)-12)-1} | F3: {=INDEX(F$12:F$1048576,COUNTA(F$12:F$1048576))/INDEX(F$12:F$1048576,COUNTA(F$12:F$1048576)-12)-1} | G3: {=INDEX(G$12:G$1048576,COUNTA(G$12:G$1048576))/INDEX(G$12:G$1048576,COUNTA(G$12:G$1048576)-12)-1} | H3: {=INDEX(H$12:H$1048576,COUNTA(H$12:H$1048576))/INDEX(H$12:H$1048576,COUNTA(H$12:H$1048576)-12)-1} | I3: {=INDEX(I$12:I$1048576,COUNTA(I$12:I$1048576))/INDEX(I$12:I$1048576,COUNTA(I$12:I$1048576)-12)-1} | ... V3: {=INDEX(V$12:V$1048576,COUNTA(V$12:V$1048576))/INDEX(V$12:V$1048576,COUNTA(V$12:V$1048576)-12)-1}
A4: Rank | B4: =RANK(B2,$B$2:$U$2) | C4: =RANK(C2,$B$2:$U$2) | D4: =RANK(D2,$B$2:$U$2) | E4: =RANK(E2,$B$2:$U$2) | F4: =RANK(F2,$B$2:$U$2) | G4: =RANK(G2,$B$2:$U$2) | H4: =RANK(H2,$B$2:$U$2) | I4: =RANK(I2,$B$2:$U$2) | ... U4: =RANK(U2,$B$2:$U$2)
A5: 23. Payrolled employees from PAYE RTI
A6: UK, seasonally adjusted
A7: Earnings and employment from Pay As You Earn Real Time Information, seasonally adjusted - Office for National Statistics
A8: Units | B8: Payrolled employees
B10: A | C10: B | D10: C | E10: D | F10: E | G10: F | H10: G | I10: H | J10: I | K10: J | L10: K | M10: L | N10: M | O10: N | P10: O | Q10: P | R10: Q | S10: R | T10: S | U10: T-U
A11: Date | B11: Agriculture, forestry and fishing | C11: Mining and quarrying | D11: Manufacturing | E11: Energy production and supply | F11: Water supply, sewerage and waste | G11: Construction | H11: Wholesale and retail; repair of motor vehicles | I11: Transportation and storage | J11: Accommodation and food service activities | K11: Information and communication | L11: Finance and insurance | M11: Real estate | N11: Professional, scientific and technical | O11: Administrative and support services | P11: Public administration and defence; social security | Q11: Education | R11: Health and social work | S11: Arts, entertainment and recreation | T11: Other service activities | U11: Households and Extraterritorial | V11: UK
A12: July 2014 | B12: 177905 | C12: 58307 | D12: 2336087 | E12: 92943 | F12: 155653 | G12: 1081408 | H12: 4255533 | I12: 1164523 | J12: 1758770 | K12: 1060896 | L12: 1054685 | M12: 401247 | N12: 1934869 | O12: 2230040 | P12: 1588018 | Q12: 2879249 | R12: 3429105 | S12: 520128 | T12: 486204 | U12: 96542 | V12: 26762113
A13: August 2014 | B13: 178179 | C13: 58487 | D13: 2340535 | E13: 92980 | F13: 155943 | G13: 1087984 | H13: 4264797 | I13: 1165997 | J13: 1767010 | K13: 1066653 | L13: 1055820 | M13: 401904 | N13: 1943596 | O13: 2250253 | P13: 1584818 | Q13: 2881488 | R13: 3435643 | S13: 521066 | T13: 487131 | U13: 96940 | V13: 26837223

Sheet 2
B2: Aged 16 and over | J2: Aged 16-64 | R2: Aged 16-17 | Z2: Aged 18-24 | AH2: Aged 25-34 | AP2: Aged 35-49 | AX2: Aged 50-64 | BF2: Age 65+
B3: Employment | D3: Unemployment | F3: Activity | H3: Inactivity | J3: Employment | L3: Unemployment | N3: Activity | P3: Inactivity | R3: Employment | T3: Unemployment | V3: Activity | X3: Inactivity | Z3: Employment | AB3: Unemployment | AD3: Activity | AF3: Inactivity | AH3: Employment | AJ3: Unemployment | AL3: Activity | AN3: Inactivity | AP3: Employment | AR3: Unemployment | AT3: Activity | AV3: Inactivity | AX3: Employment | AZ3: Unemployment | BB3: Activity | BD3: Inactivity | BF3: Employment | BH3: Unemployment | BJ3: Activity | BL3: Inactivity
B4: level | C4: rate (%) | D4: level | E4: rate (%) | F4: level | G4: rate (%) | H4: level | I4: rate (%) | J4: level | K4: rate (%) | L4: level | M4: rate (%) | N4: level | O4: rate (%) | P4: level | Q4: rate (%) | R4: level | S4: rate (%) | T4: level | U4: rate (%) | V4: level | W4: rate (%) | X4: level | Y4: rate (%) | Z4: level | AA4: rate (%) | AB4: level | AC4: rate (%) | AD4: level | AE4: rate (%) | AF4: level | AG4: rate (%) | AH4: level | AI4: rate (%) | AJ4: level | AK4: rate (%) | AL4: level | AM4: rate (%) | AN4: level | AO4: rate (%) | AP4: level | AQ4: rate (%) | AR4: level | AS4: rate (%) | AT4: level | AU4: rate (%) | AV4: level | AW4: rate (%) | AX4: level | AY4: rate (%) | AZ4: level | BA4: rate (%) | BB4: level | BC4: rate (%) | BD4: level | BE4: rate (%) | BF4: level | BG4: rate (%) | BH4: level | BI4: rate (%) | BJ4: level | BK4: rate (%) | BL4: level | BM4: rate (%)
A5: Current | B5: {{EMP16_CUR}} | C5: {{EMP_RT_CUR}} | D5: {{UNEMP16_CUR}} | E5: {{UNEMP_RT_CUR}} | F5: {=INDEX(F$18:F$1048576,COUNTA(F$18:F$1048576))} | G5: {=INDEX(G$18:G$1048576,COUNTA(G$18:G$1048576))} | H5: {{INACT_CUR}} | I5: {{INACT_RT_CUR}} | J5: {=INDEX(J$18:J$1048576,COUNTA(J$18:J$1048576))} | K5: {=INDEX(K$18:K$1048576,COUNTA(K$18:K$1048576))} | L5: {=INDEX(L$18:L$1048576,COUNTA(L$18:L$1048576))} | M5: {=INDEX(M$18:M$1048576,COUNTA(M$18:M$1048576))} | N5: {=INDEX(N$18:N$1048576,COUNTA(N$18:N$1048576))} | O5: {=INDEX(O$18:O$1048576,COUNTA(O$18:O$1048576))} | P5: {=INDEX(P$18:P$1048576,COUNTA(P$18:P$1048576))} | Q5: {=INDEX(Q$18:Q$1048576,COUNTA(Q$18:Q$1048576))} | ... BM5: {=INDEX(BM$18:BM$1048576,COUNTA(BM$18:BM$1048576))}
A6: Quarterly change | B6: {{EMP16_DQ}} | C6: {{EMP_RT_DQ}} | D6: {{UNEMP16_DQ}} | E6: {{UNEMP_RT_DQ}} | F6: {=INDEX(F$18:F$1048576,COUNTA(F$18:F$1048576))-INDEX(F$18:F$1048576,COUNTA(F$18:F$1048576)-3)} | G6: {=INDEX(G$18:G$1048576,COUNTA(G$18:G$1048576))-INDEX(G$18:G$1048576,COUNTA(G$18:G$1048576)-3)} | H6: {{INACT_DQ}} | I6: {{INACT_RT_DQ}} | J6: {=INDEX(J$18:J$1048576,COUNTA(J$18:J$1048576))-INDEX(J$18:J$1048576,COUNTA(J$18:J$1048576)-3)} | K6: {=INDEX(K$18:K$1048576,COUNTA(K$18:K$1048576))-INDEX(K$18:K$1048576,COUNTA(K$18:K$1048576)-3)} | L6: {=INDEX(L$18:L$1048576,COUNTA(L$18:L$1048576))-INDEX(L$18:L$1048576,COUNTA(L$18:L$1048576)-3)} | M6: {=INDEX(M$18:M$1048576,COUNTA(M$18:M$1048576))-INDEX(M$18:M$1048576,COUNTA(M$18:M$1048576)-3)} | N6: {=INDEX(N$18:N$1048576,COUNTA(N$18:N$1048576))-INDEX(N$18:N$1048576,COUNTA(N$18:N$1048576)-3)} | O6: {=INDEX(O$18:O$1048576,COUNTA(O$18:O$1048576))-INDEX(O$18:O$1048576,COUNTA(O$18:O$1048576)-3)} | P6: {=INDEX(P$18:P$1048576,COUNTA(P$18:P$1048576))-INDEX(P$18:P$1048576,COUNTA(P$18:P$1048576)-3)} | Q6: {=INDEX(Q$18:Q$1048576,COUNTA(Q$18:Q$1048576))-INDEX(Q$18:Q$1048576,COUNTA(Q$18:Q$1048576)-3)} | ... BM6: {=INDEX(BM$18:BM$1048576,COUNTA(BM$18:BM$1048576))-INDEX(BM$18:BM$1048576,COUNTA(BM$18:BM$1048576)-3)}
A7: Change year on year | B7: {{EMP16_DY}} | C7: {{EMP_RT_DY}} | D7: {{UNEMP16_DY}} | E7: {{UNEMP_RT_DY}} | F7: {=INDEX(F$18:F$1048576,COUNTA(F$18:F$1048576))-INDEX(F$18:F$1048576,COUNTA(F$18:F$1048576)-12)} | G7: {=INDEX(G$18:G$1048576,COUNTA(G$18:G$1048576))-INDEX(G$18:G$1048576,COUNTA(G$18:G$1048576)-12)} | H7: {{INACT_DY}} | I7: {{INACT_RT_DY}} | J7: {=INDEX(J$18:J$1048576,COUNTA(J$18:J$1048576))-INDEX(J$18:J$1048576,COUNTA(J$18:J$1048576)-12)} | K7: {=INDEX(K$18:K$1048576,COUNTA(K$18:K$1048576))-INDEX(K$18:K$1048576,COUNTA(K$18:K$1048576)-12)} | L7: {=INDEX(L$18:L$1048576,COUNTA(L$18:L$1048576))-INDEX(L$18:L$1048576,COUNTA(L$18:L$1048576)-12)} | M7: {=INDEX(M$18:M$1048576,COUNTA(M$18:M$1048576))-INDEX(M$18:M$1048576,COUNTA(M$18:M$1048576)-12)} | N7: {=INDEX(N$18:N$1048576,COUNTA(N$18:N$1048576))-INDEX(N$18:N$1048576,COUNTA(N$18:N$1048576)-12)} | O7: {=INDEX(O$18:O$1048576,COUNTA(O$18:O$1048576))-INDEX(O$18:O$1048576,COUNTA(O$18:O$1048576)-12)} | P7: {=INDEX(P$18:P$1048576,COUNTA(P$18:P$1048576))-INDEX(P$18:P$1048576,COUNTA(P$18:P$1048576)-12)} | Q7: {=INDEX(Q$18:Q$1048576,COUNTA(Q$18:Q$1048576))-INDEX(Q$18:Q$1048576,COUNTA(Q$18:Q$1048576)-12)} | ... BM7: {=INDEX(BM$18:BM$1048576,COUNTA(BM$18:BM$1048576))-INDEX(BM$18:BM$1048576,COUNTA(BM$18:BM$1048576)-12)}
A8: Change since Covid (Dec 19-feb 20) | B8: {{EMP16_DC}} | C8: {{EMP_RT_DC}} | D8: {{UNEMP16_DC}} | E8: {{UNEMP_RT_DC}} | F8: {=INDEX(F$18:F$1048576,COUNTA(F$18:F$1048576))-F$351} | G8: {=INDEX(G$18:G$1048576,COUNTA(G$18:G$1048576))-G$351} | H8: {{INACT_DC}} | I8: {{INACT_RT_DC}} | J8: {=INDEX(J$18:J$1048576,COUNTA(J$18:J$1048576))-J$351} | K8: {=INDEX(K$18:K$1048576,COUNTA(K$18:K$1048576))-K$351} | L8: {=INDEX(L$18:L$1048576,COUNTA(L$18:L$1048576))-L$351} | M8: {=INDEX(M$18:M$1048576,COUNTA(M$18:M$1048576))-M$351} | N8: {=INDEX(N$18:N$1048576,COUNTA(N$18:N$1048576))-N$351} | O8: {=INDEX(O$18:O$1048576,COUNTA(O$18:O$1048576))-O$351} | P8: {=INDEX(P$18:P$1048576,COUNTA(P$18:P$1048576))-P$351} | Q8: {=INDEX(Q$18:Q$1048576,COUNTA(Q$18:Q$1048576))-Q$351} | ... BM8: {=INDEX(BM$18:BM$1048576,COUNTA(BM$18:BM$1048576))-BM$351}
A9: change since 2010 election | B9: {=INDEX(B$18:B$1048576,COUNTA(B$18:B$1048576))-B$233} | C9: {=INDEX(C$18:C$1048576,COUNTA(C$18:C$1048576))-C$233} | D9: {=INDEX(D$18:D$1048576,COUNTA(D$18:D$1048576))-D$233} | E9: {=INDEX(E$18:E$1048576,COUNTA(E$18:E$1048576))-E$233} | F9: {=INDEX(F$18:F$1048576,COUNTA(F$18:F$1048576))-F$233} | G9: {=INDEX(G$18:G$1048576,COUNTA(G$18:G$1048576))-G$233} | H9: {=INDEX(H$18:H$1048576,COUNTA(H$18:H$1048576))-H$233} | I9: {=INDEX(I$18:I$1048576,COUNTA(I$18:I$1048576))-I$233} | ... BM9: {=INDEX(BM$18:BM$1048576,COUNTA(BM$18:BM$1048576))-BM$233}
A10: change since 2024 election | B10: {{EMP16_DE}} | C10: {{EMP_RT_DE}} | D10: {{UNEMP16_DE}} | E10: {{UNEMP_RT_DE}} | F10: {=INDEX(F$18:F$1048576,COUNTA(F$18:F$1048576))-F$403} | G10: {=INDEX(G$18:G$1048576,COUNTA(G$18:G$1048576))-G$403} | H10: {{INACT_DE}} | I10: {{INACT_RT_DE}} | J10: {=INDEX(J$18:J$1048576,COUNTA(J$18:J$1048576))-J$403} | K10: {=INDEX(K$18:K$1048576,COUNTA(K$18:K$1048576))-K$403} | L10: {=INDEX(L$18:L$1048576,COUNTA(L$18:L$1048576))-L$403} | M10: {=INDEX(M$18:M$1048576,COUNTA(M$18:M$1048576))-M$403} | N10: {=INDEX(N$18:N$1048576,COUNTA(N$18:N$1048576))-N$403} | O10: {=INDEX(O$18:O$1048576,COUNTA(O$18:O$1048576))-O$403} | P10: {=INDEX(P$18:P$1048576,COUNTA(P$18:P$1048576))-P$403} | Q10: {=INDEX(Q$18:Q$1048576,COUNTA(Q$18:Q$1048576))-Q$403} | ... BM10: {=INDEX(BM$18:BM$1048576,COUNTA(BM$18:BM$1048576))-BM$403}
A11: Table 2: Labour market activity by age group (seasonally adjusted) | J11: =J418-J402
A12: Date of publication: | B12: 45335 | G12: Date of next publication: | J12: 45363 | M12: Source: Labour Force Survey
A13: Inquiries: Email: | B13: labour.market@ons.gov.uk | G13: Tel: 01633 455400 | J13: =K414-K417
A14: United Kingdom (thousands) seasonally adjusted
B15: Aged 16 and over | J15: Aged 16-64 | R15: Aged 16-17 | Z15: Aged 18-24 | AH15: Aged 25-34 | AP15: Aged 35-49 | AX15: Aged 50-64 | BF15: Age 65+
B16: Employment | D16: Unemployment | F16: Activity | H16: Inactivity | J16: Employment | L16: Unemployment | N16: Activity | P16: Inactivity | R16: Employment | T16: Unemployment | V16: Activity | X16: Inactivity | Z16: Employment | AB16: Unemployment | AD16: Activity | AF16: Inactivity | AH16: Employment | AJ16: Unemployment | AL16: Activity | AN16: Inactivity | AP16: Employment | AR16: Unemployment | AT16: Activity | AV16: Inactivity | AX16: Employment | AZ16: Unemployment | BB16: Activity | BD16: Inactivity | BF16: Employment | BH16: Unemployment | BJ16: Activity | BL16: Inactivity
B17: level | C17: rate (%) | D17: level | E17: rate (%) | F17: level | G17: rate (%) | H17: level | I17: rate (%) | J17: level | K17: rate (%) | L17: level | M17: rate (%) | N17: level | O17: rate (%) | P17: level | Q17: rate (%) | R17: level | S17: rate (%) | T17: level | U17: rate (%) | V17: level | W17: rate (%) | X17: level | Y17: rate (%) | Z17: level | AA17: rate (%) | AB17: level | AC17: rate (%) | AD17: level | AE17: rate (%) | AF17: level | AG17: rate (%) | AH17: level | AI17: rate (%) | AJ17: level | AK17: rate (%) | AL17: level | AM17: rate (%) | AN17: level | AO17: rate (%) | AP17: level | AQ17: rate (%) | AR17: level | AS17: rate (%) | AT17: level | AU17: rate (%) | AV17: level | AW17: rate (%) | AX17: level | AY17: rate (%) | AZ17: level | BA17: rate (%) | BB17: level | BC17: rate (%) | BD17: level | BE17: rate (%) | BF17: level | BG17: rate (%) | BH17: level | BI17: rate (%) | BJ17: level | BK17: rate (%) | BL17: level | BM17: rate (%)

Sheet 5
B2: Workforce jobs | C2: Employee jobs | D2: Self-employment jobs | E2: HM Forces | F2: Government- supported trainees
A3: Current | B3: {=INDEX(B$16:B$1048576,COUNTA(B$16:B$1048576))} | C3: {=INDEX(C$16:C$1048576,COUNTA(C$16:C$1048576))} | D3: {=INDEX(D$16:D$1048576,COUNTA(D$16:D$1048576))} | E3: {=INDEX(E$16:E$1048576,COUNTA(E$16:E$1048576))} | F3: {=INDEX(F$16:F$1048576,COUNTA(F$16:F$1048576))}
A4: Quarterly change | B4: {=INDEX(B$16:B$1048576,COUNTA(B$16:B$1048576))-INDEX(B$16:B$1048576,COUNTA(B$16:B$1048576)-1)} | C4: {=INDEX(C$16:C$1048576,COUNTA(C$16:C$1048576))-INDEX(C$16:C$1048576,COUNTA(C$16:C$1048576)-1)} | D4: {=INDEX(D$16:D$1048576,COUNTA(D$16:D$1048576))-INDEX(D$16:D$1048576,COUNTA(D$16:D$1048576)-1)} | E4: {=INDEX(E$16:E$1048576,COUNTA(E$16:E$1048576))-INDEX(E$16:E$1048576,COUNTA(E$16:E$1048576)-1)} | F4: {=INDEX(F$16:F$1048576,COUNTA(F$16:F$1048576))-INDEX(F$16:F$1048576,COUNTA(F$16:F$1048576)-1)}
A5: Max | B5: =MAX(B$16:B$1048576) | C5: =MAX(C$16:C$1048576) | D5: =MAX(D$16:D$1048576) | E5: =MAX(E$16:E$1048576) | F5: =MAX(F$16:F$1048576)
A6: Jobs created since new gov | B6: {=INDEX(B$16:B$1048576,COUNTA(B$16:B$1048576))-B$276} | C6: {=INDEX(C$16:C$1048576,COUNTA(C$16:C$1048576))-C$276} | D6: {=INDEX(D$16:D$1048576,COUNTA(D$16:D$1048576))-D$276} | E6: {=INDEX(E$16:E$1048576,COUNTA(E$16:E$1048576))-E$276} | F6: {=INDEX(F$16:F$1048576,COUNTA(F$16:F$1048576))-F$276}
A8: Table 5: Workforce jobs (seasonally adjusted)1
A9: Date of publication: | C9: 45916 | E9: Date of next publication: | F9: 46007
A10: Inquiries: Email: | C10: workforce.jobs@ons.gov.uk | E10: Telephone: | F10: 01633 455400
F11: Sources: Employer surveys, Labour Force Survey and administrative sources
A12: United Kingdom (thousands) seasonally adjusted
B13: Workforce jobs1 | C13: Employee jobs1 | D13: Self-employment jobs2 | E13: HM Forces | F13: Government- supported trainees2 3
B14: 1 | C14: 2 | D14: 3 | E14: 4 | F14: 5
B15: DYDC | C15: BCAJ | D15: DYZN | E15: LOJX | F15: LOJU

Sheet 10
B1: People | D1: Men | F1: Women
B2: Level1 | C2: Rate per thousand2 | D2: Level1 | E2: Rate per thousand2 | F2: Level1 | G2: Rate per thousand2
A3: Current | B3: {=INDEX(B$18:B$1048576,COUNTA(B$18:B$1048576))} | C3: {=INDEX(C$18:C$1048576,COUNTA(C$18:C$1048576))} | D3: {=INDEX(D$18:D$1048576,COUNTA(D$18:D$1048576))} | E3: {=INDEX(E$18:E$1048576,COUNTA(E$18:E$1048576))} | F3: {=INDEX(F$18:F$1048576,COUNTA(F$18:F$1048576))} | G3: {=INDEX(G$18:G$1048576,COUNTA(G$18:G$1048576))}
A4: Quarterly change | B4: {=INDEX(B$18:B$1048576,COUNTA(B$18:B$1048576))-INDEX(B$18:B$1048576,COUNTA(B$18:B$1048576)-3)} | C4: {=INDEX(C$18:C$1048576,COUNTA(C$18:C$1048576))-INDEX(C$18:C$1048576,COUNTA(C$18:C$1048576)-3)} | D4: {=INDEX(D$18:D$1048576,COUNTA(D$18:D$1048576))-INDEX(D$18:D$1048576,COUNTA(D$18:D$1048576)-3)} | E4: {=INDEX(E$18:E$1048576,COUNTA(E$18:E$1048576))-INDEX(E$18:E$1048576,COUNTA(E$18:E$1048576)-3)} | F4: {=INDEX(F$18:F$1048576,COUNTA(F$18:F$1048576))-INDEX(F$18:F$1048576,COUNTA(F$18:F$1048576)-3)} | G4: {=INDEX(G$18:G$1048576,COUNTA(G$18:G$1048576))-INDEX(G$18:G$1048576,COUNTA(G$18:G$1048576)-3)}
A5: year on year change | B5: {=INDEX(B$18:B$1048576,COUNTA(B$18:B$1048576))-INDEX(B$18:B$1048576,COUNTA(B$18:B$1048576)-12)} | C5: {=INDEX(C$18:C$1048576,COUNTA(C$18:C$1048576))-INDEX(C$18:C$1048576,COUNTA(C$18:C$1048576)-12)} | D5: {=INDEX(D$18:D$1048576,COUNTA(D$18:D$1048576))-INDEX(D$18:D$1048576,COUNTA(D$18:D$1048576)-12)} | E5: {=INDEX(E$18:E$1048576,COUNTA(E$18:E$1048576))-INDEX(E$18:E$1048576,COUNTA(E$18:E$1048576)-12)} | F5: {=INDEX(F$18:F$1048576,COUNTA(F$18:F$1048576))-INDEX(F$18:F$1048576,COUNTA(F$18:F$1048576)-12)} | G5: {=INDEX(G$18:G$1048576,COUNTA(G$18:G$1048576))-INDEX(G$18:G$1048576,COUNTA(G$18:G$1048576)-12)}
A6: Since pandemic | B6: {=INDEX(B$18:B$1048576,COUNTA(B$18:B$1048576))-B$351} | C6: {=INDEX(C$18:C$1048576,COUNTA(C$18:C$1048576))-C$351} | D6: {=INDEX(D$18:D$1048576,COUNTA(D$18:D$1048576))-D$351} | E6: {=INDEX(E$18:E$1048576,COUNTA(E$18:E$1048576))-E$351} | F6: {=INDEX(F$18:F$1048576,COUNTA(F$18:F$1048576))-F$351} | G6: {=INDEX(G$18:G$1048576,COUNTA(G$18:G$1048576))-G$351}
A7: Since 2010 election | B7: {=INDEX(B$18:B$1048576,COUNTA(B$18:B$1048576))-B$233} | C7: {=INDEX(C$18:C$1048576,COUNTA(C$18:C$1048576))-C$233} | D7: {=INDEX(D$18:D$1048576,COUNTA(D$18:D$1048576))-D$233} | E7: {=INDEX(E$18:E$1048576,COUNTA(E$18:E$1048576))-E$233} | F7: {=INDEX(F$18:F$1048576,COUNTA(F$18:F$1048576))-F$233} | G7: {=INDEX(G$18:G$1048576,COUNTA(G$18:G$1048576))-G$233}
A9: Table 10: Redundancies levels1 and rates2 for those aged 16 and over

Sheet 11
C1: Economic inactivity by reason (thousands) | M1: Percentage of economically inactive (%) | W1: Economic inactivity by wants a job (thousands) | AD1: Percentage of economically inactive by wants a job (%) | AK1: Economic inactivity by does not want a job (thousands) | AR1: Percentage of economically inactive by does not want a job (%)
B2: Total economically inactive aged 16-64 (thousands)4 | C2: Student | D2: Looking after family / home | E2: Temp sick | F2: Long-term sick | G2: Discouraged workers1 | H2: Retired | I2: Other2 | J2: Does not want job (thousands) | K2: Wants a job (thousands) | L2: Total economically inactive aged 16-64 | M2: Student | N2: Looking after family / home | O2: Temp sick | P2: Long-term sick | Q2: Discouraged workers1 | R2: Retired | S2: Other2 | T2: Does not want job (%age of economically inactive) | U2: Wants a job (%age of economically inactive) | V2: Total economically inactive wants a job aged 16-64 (thousands) | W2: Student | X2: Looking after family / home | Y2: Temp sick | Z2: Long-term sick | AA2: Discouraged workers1 | AB2: Other2 | AC2: Total wants a job aged 16-64 | AD2: Student | AE2: Looking after family / home | AF2: Temp sick | AG2: Long-term sick | AH2: Discouraged workers1 | AI2: Other2 | AJ2: Total economically inactive does not want a job aged 16-64 (thousands) | AK2: Student | AL2: Looking after family / home | AM2: Temp sick | AN2: Long-term sick | AO2: Retired | AP2: Other2 | AQ2: Total does not want a job aged 16-64 | AR2: Student | AS2: Looking after family / home | AT2: Temp sick | AU2: Long-term sick | AV2: Retired | AW2: Other2
A3: Current | B3: {=INDEX(B$18:B$1048576,COUNTA(B$18:B$1048576))} | C3: {=INDEX(C$30:C$1048576,COUNTA(C$30:C$1048576))} | D3: {=INDEX(D$30:D$1048576,COUNTA(D$30:D$1048576))} | E3: {=INDEX(E$30:E$1048576,COUNTA(E$30:E$1048576))} | F3: {=INDEX(F$30:F$1048576,COUNTA(F$30:F$1048576))} | G3: {=INDEX(G$30:G$1048576,COUNTA(G$30:G$1048576))} | H3: {=INDEX(H$30:H$1048576,COUNTA(H$30:H$1048576))} | I3: {=INDEX(I$30:I$1048576,COUNTA(I$30:I$1048576))} | J3: {=INDEX(J$30:J$1048576,COUNTA(J$30:J$1048576))} | K3: {=INDEX(K$30:K$1048576,COUNTA(K$30:K$1048576))} | L3: {=INDEX(L$18:L$1048576,COUNTA(L$18:L$1048576))} | M3: {=INDEX(M$30:M$1048576,COUNTA(M$30:M$1048576))} | N3: {=INDEX(N$30:N$1048576,COUNTA(N$30:N$1048576))} | O3: {=INDEX(O$30:O$1048576,COUNTA(O$30:O$1048576))} | P3: {=INDEX(P$30:P$1048576,COUNTA(P$30:P$1048576))} | Q3: {=INDEX(Q$30:Q$1048576,COUNTA(Q$30:Q$1048576))} | R3: {=INDEX(R$30:R$1048576,COUNTA(R$30:R$1048576))} | S3: {=INDEX(S$30:S$1048576,COUNTA(S$30:S$1048576))} | T3: {=INDEX(T$30:T$1048576,COUNTA(T$30:T$1048576))} | U3: {=INDEX(U$30:U$1048576,COUNTA(U$30:U$1048576))} | V3: {=INDEX(V$18:V$1048576,COUNTA(V$18:V$1048576))} | W3: {=INDEX(W$18:W$1048576,COUNTA(W$18:W$1048576))} | X3: {=INDEX(X$18:X$1048576,COUNTA(X$18:X$1048576))} | Y3: {=INDEX(Y$18:Y$1048576,COUNTA(Y$18:Y$1048576))} | Z3: {=INDEX(Z$18:Z$1048576,COUNTA(Z$18:Z$1048576))} | AA3: {=INDEX(AA$18:AA$1048576,COUNTA(AA$18:AA$1048576))} | AB3: {=INDEX(AB$18:AB$1048576,COUNTA(AB$18:AB$1048576))} | AC3: {=INDEX(AC$18:AC$1048576,COUNTA(AC$18:AC$1048576))} | ... AW3: {=INDEX(AW$18:AW$1048576,COUNTA(AW$18:AW$1048576))}
A4: Quarterly change | B4: {=INDEX(B$18:B$1048576,COUNTA(B$18:B$1048576))-INDEX(B$18:B$1048576,COUNTA(B$18:B$1048576)-3)} | C4: {=INDEX(C$18:C$1048576,COUNTA(C$18:C$1048576))-INDEX(C$18:C$1048576,COUNTA(C$18:C$1048576)-3)} | D4: {=INDEX(D$18:D$1048576,COUNTA(D$18:D$1048576))-INDEX(D$18:D$1048576,COUNTA(D$18:D$1048576)-3)} | E4: {=INDEX(E$18:E$1048576,COUNTA(E$18:E$1048576))-INDEX(E$18:E$1048576,COUNTA(E$18:E$1048576)-3)} | F4: {=INDEX(F$18:F$1048576,COUNTA(F$18:F$1048576))-INDEX(F$18:F$1048576,COUNTA(F$18:F$1048576)-3)} | G4: {=INDEX(G$18:G$1048576,COUNTA(G$18:G$1048576))-INDEX(G$18:G$1048576,COUNTA(G$18:G$1048576)-3)} | H4: {=INDEX(H$18:H$1048576,COUNTA(H$18:H$1048576))-INDEX(H$18:H$1048576,COUNTA(H$18:H$1048576)-3)} | I4: {=INDEX(I$18:I$1048576,COUNTA(I$18:I$1048576))-INDEX(I$18:I$1048576,COUNTA(I$18:I$1048576)-3)} | ... AW4: {=INDEX(AW$18:AW$1048576,COUNTA(AW$18:AW$1048576))-INDEX(AW$18:AW$1048576,COUNTA(AW$18:AW$1048576)-3)}
A5: year on year change | B5: {=INDEX(B$18:B$1048576,COUNTA(B$18:B$1048576))-INDEX(B$18:B$1048576,COUNTA(B$18:B$1048576)-12)} | C5: {=INDEX(C$18:C$1048576,COUNTA(C$18:C$1048576))-INDEX(C$18:C$1048576,COUNTA(C$18:C$1048576)-12)} | D5: {=INDEX(D$18:D$1048576,COUNTA(D$18:D$1048576))-INDEX(D$18:D$1048576,COUNTA(D$18:D$1048576)-12)} | E5: {=INDEX(E$18:E$1048576,COUNTA(E$18:E$1048576))-INDEX(E$18:E$1048576,COUNTA(E$18:E$1048576)-12)} | F5: {=INDEX(F$18:F$1048576,COUNTA(F$18:F$1048576))-INDEX(F$18:F$1048576,COUNTA(F$18:F$1048576)-12)} | G5: {=INDEX(G$18:G$1048576,COUNTA(G$18:G$1048576))-INDEX(G$18:G$1048576,COUNTA(G$18:G$1048576)-12)} | H5: {=INDEX(H$18:H$1048576,COUNTA(H$18:H$1048576))-INDEX(H$18:H$1048576,COUNTA(H$18:H$1048576)-12)} | I5: {=INDEX(I$18:I$1048576,COUNTA(I$18:I$1048576))-INDEX(I$18:I$1048576,COUNTA(I$18:I$1048576)-12)} | ... AW5: {=INDEX(AW$18:AW$1048576,COUNTA(AW$18:AW$1048576))-INDEX(AW$18:AW$1048576,COUNTA(AW$18:AW$1048576)-12)}
A6: Since pandemic | B6: {=INDEX(B$18:B$1048576,COUNTA(B$18:B$1048576))-B$351} | C6: {=INDEX(C$18:C$1048576,COUNTA(C$18:C$1048576))-C$351} | D6: {=INDEX(D$18:D$1048576,COUNTA(D$18:D$1048576))-D$351} | E6: {=INDEX(E$18:E$1048576,COUNTA(E$18:E$1048576))-E$351} | F6: {=INDEX(F$18:F$1048576,COUNTA(F$18:F$1048576))-F$351} | G6: {=INDEX(G$18:G$1048576,COUNTA(G$18:G$1048576))-G$351} | H6: {=INDEX(H$18:H$1048576,COUNTA(H$18:H$1048576))-H$351} | I6: {=INDEX(I$18:I$1048576,COUNTA(I$18:I$1048576))-I$351} | ... AW6: {=INDEX(AW$18:AW$1048576,COUNTA(AW$18:AW$1048576))-AW$351}
A7: Since 2010 election | B7: {=INDEX(B$18:B$1048576,COUNTA(B$18:B$1048576))-B$233} | C7: {=INDEX(C$18:C$1048576,COUNTA(C$18:C$1048576))-C$233} | D7: {=INDEX(D$18:D$1048576,COUNTA(D$18:D$1048576))-D$233} | E7: {=INDEX(E$18:E$1048576,COUNTA(E$18:E$1048576))-E$233} | F7: {=INDEX(F$18:F$1048576,COUNTA(F$18:F$1048576))-F$233} | G7: {=INDEX(G$18:G$1048576,COUNTA(G$18:G$1048576))-G$233} | H7: {=INDEX(H$18:H$1048576,COUNTA(H$18:H$1048576))-H$233} | I7: {=INDEX(I$18:I$1048576,COUNTA(I$18:I$1048576))-I$233} | ... AW7: {=INDEX(AW$18:AW$1048576,COUNTA(AW$18:AW$1048576))-AW$233}
A9: Table 11: Economic inactivity for those aged from 16 to 64 (seasonally adjusted)

Sheet 13
B1: Whole Economy | E1: Private sector3 4 5 | H1: Public sector3 4 5 | K1: Services, SIC 2007 sections G-S | N1: Finance and business services, SIC 2007 sections K-N | Q1: Public sector excluding financial services 4 5 | T1: Manufacturing, SIC 2007 section C | W1: Construction, SIC 2007 section F | Z1: Wholesaling, retailing, hotels & restaurants, SIC 2007 sections G & I
B2: Weekly Earnings (£) | C2: % changes year on year | E2: Weekly Earnings (£) | F2: % changes year on year | H2: Weekly Earnings (£) | I2: % changes year on year | K2: Weekly Earnings (£) | L2: % changes year on year | N2: Weekly Earnings (£) | O2: % changes year on year | Q2: Weekly Earnings (£) | R2: % changes year on year | T2: Weekly Earnings (£) | U2: % changes year on year | W2: Weekly Earnings (£) | X2: % changes year on year | Z2: Weekly Earnings (£) | AA2: % changes year on year
C3: Single month | D3: 3 month average 2 | F3: Single month | G3: 3 month average 2 | I3: Single month | J3: 3 month average 2 | L3: Single month | M3: 3 month average 2 | O3: Single month | P3: 3 month average 2 | R3: Single month | S3: 3 month average 2 | U3: Single month | V3: 3 month average 2 | X3: Single month | Y3: 3 month average 2 | AA3: Single month | AB3: 3 month average 2
A4: Current (3mo avg) | B4: =(AVERAGE(OFFSET(INDEX(B$18:B$1048576,COUNTA(B$18:B$1048576)),-2,0,3,1))) | C4: {=INDEX(C$30:C$1048576,COUNTA(C$30:C$1048576))} | D4: {=INDEX(D$32:D$1048576,COUNTA(D$32:D$1048576))} | E4: =(AVERAGE(OFFSET(INDEX(E$18:E$1048576,COUNTA(E$18:E$1048576)),-2,0,3,1))) | F4: {=INDEX(F$30:F$1048576,COUNTA(F$30:F$1048576))} | G4: {=INDEX(G$32:G$1048576,COUNTA(G$32:G$1048576))} | H4: =(AVERAGE(OFFSET(INDEX(H$18:H$1048576,COUNTA(H$18:H$1048576)),-2,0,3,1))) | I4: {=INDEX(I$30:I$1048576,COUNTA(I$30:I$1048576))} | J4: {=INDEX(J$32:J$1048576,COUNTA(J$32:J$1048576))} | K4: =(AVERAGE(OFFSET(INDEX(K$18:K$1048576,COUNTA(K$18:K$1048576)),-2,0,3,1))) | L4: {=INDEX(L$30:L$1048576,COUNTA(L$30:L$1048576))} | M4: {=INDEX(M$32:M$1048576,COUNTA(M$32:M$1048576))} | N4: =(AVERAGE(OFFSET(INDEX(N$18:N$1048576,COUNTA(N$18:N$1048576)),-2,0,3,1))) | O4: {=INDEX(O$30:O$1048576,COUNTA(O$30:O$1048576))} | P4: {=INDEX(P$32:P$1048576,COUNTA(P$32:P$1048576))} | Q4: =(AVERAGE(OFFSET(INDEX(Q$18:Q$1048576,COUNTA(Q$18:Q$1048576)),-2,0,3,1))) | R4: {=INDEX(R$30:R$1048576,COUNTA(R$30:R$1048576))} | S4: {=INDEX(S$32:S$1048576,COUNTA(S$32:S$1048576))} | T4: =(AVERAGE(OFFSET(INDEX(T$18:T$1048576,COUNTA(T$18:T$1048576)),-2,0,3,1))) | U4: {=INDEX(U$30:U$1048576,COUNTA(U$30:U$1048576))} | V4: {=INDEX(V$32:V$1048576,COUNTA(V$32:V$1048576))} | W4: =(AVERAGE(OFFSET(INDEX(W$18:W$1048576,COUNTA(W$18:W$1048576)),-2,0,3,1))) | X4: {=INDEX(X$30:X$1048576,COUNTA(X$30:X$1048576))} | Y4: {=INDEX(Y$32:Y$1048576,COUNTA(Y$32:Y$1048576))} | Z4: =(AVERAGE(OFFSET(INDEX(Z$18:Z$1048576,COUNTA(Z$18:Z$1048576)),-2,0,3,1))) | AA4: {=INDEX(AA$30:AA$1048576,COUNTA(AA$30:AA$1048576))} | AB4: {=INDEX(AB$32:AB$1048576,COUNTA(AB$32:AB$1048576))}
A5: Change on quarter | B5: =(AVERAGE(OFFSET(INDEX(B$18:B$1048576,COUNTA(B$18:B$1048576)),-2,0,3,1))-AVERAGE(OFFSET(INDEX(B$18:B$1048576,COUNTA(B$18:B$1048576)),-5,0,3,1)))*52 | C5: {=INDEX(C$30:C$1048576,COUNTA(C$30:C$1048576))-INDEX(C$30:C$1048576,COUNTA(C$30:C$1048576)-3)} | D5: {=INDEX(D$32:D$1048576,COUNTA(D$32:D$1048576))-INDEX(D$32:D$1048576,COUNTA(D$32:D$1048576)-3)} | E5: =(AVERAGE(OFFSET(INDEX(E$18:E$1048576,COUNTA(E$18:E$1048576)),-2,0,3,1))-AVERAGE(OFFSET(INDEX(E$18:E$1048576,COUNTA(E$18:E$1048576)),-5,0,3,1)))*52 | F5: {=INDEX(F$30:F$1048576,COUNTA(F$30:F$1048576))-INDEX(F$30:F$1048576,COUNTA(F$30:F$1048576)-3)} | G5: {=INDEX(G$32:G$1048576,COUNTA(G$32:G$1048576))-INDEX(G$32:G$1048576,COUNTA(G$32:G$1048576)-3)} | H5: =(AVERAGE(OFFSET(INDEX(H$18:H$1048576,COUNTA(H$18:H$1048576)),-2,0,3,1))-AVERAGE(OFFSET(INDEX(H$18:H$1048576,COUNTA(H$18:H$1048576)),-5,0,3,1)))*52 | I5: {=INDEX(I$30:I$1048576,COUNTA(I$30:I$1048576))-INDEX(I$30:I$1048576,COUNTA(I$30:I$1048576)-3)} | J5: {=INDEX(J$32:J$1048576,COUNTA(J$32:J$1048576))-INDEX(J$32:J$1048576,COUNTA(J$32:J$1048576)-3)} | K5: =(AVERAGE(OFFSET(INDEX(K$18:K$1048576,COUNTA(K$18:K$1048576)),-2,0,3,1))-AVERAGE(OFFSET(INDEX(K$18:K$1048576,COUNTA(K$18:K$1048576)),-5,0,3,1)))*52 | L5: {=INDEX(L$30:L$1048576,COUNTA(L$30:L$1048576))-INDEX(L$30:L$1048576,COUNTA(L$30:L$1048576)-3)} | M5: {=INDEX(M$32:M$1048576,COUNTA(M$32:M$1048576))-INDEX(M$32:M$1048576,COUNTA(M$32:M$1048576)-3)} | N5: =(AVERAGE(OFFSET(INDEX(N$18:N$1048576,COUNTA(N$18:N$1048576)),-2,0,3,1))-AVERAGE(OFFSET(INDEX(N$18:N$1048576,COUNTA(N$18:N$1048576)),-5,0,3,1)))*52 | O5: {=INDEX(O$30:O$1048576,COUNTA(O$30:O$1048576))-INDEX(O$30:O$1048576,COUNTA(O$30:O$1048576)-3)} | P5: {=INDEX(P$32:P$1048576,COUNTA(P$32:P$1048576))-INDEX(P$32:P$1048576,COUNTA(P$32:P$1048576)-3)} | Q5: =(AVERAGE(OFFSET(INDEX(Q$18:Q$1048576,COUNTA(Q$18:Q$1048576)),-2,0,3,1))-AVERAGE(OFFSET(INDEX(Q$18:Q$1048576,COUNTA(Q$18:Q$1048576)),-5,0,3,1)))*52 | R5: {=INDEX(R$30:R$1048576,COUNTA(R$30:R$1048576))-INDEX(R$30:R$1048576,COUNTA(R$30:R$1048576)-3)} | S5: {=INDEX(S$32:S$1048576,COUNTA(S$32:S$1048576))-INDEX(S$32:S$1048576,COUNTA(S$32:S$1048576)-3)} | T5: =(AVERAGE(OFFSET(INDEX(T$18:T$1048576,COUNTA(T$18:T$1048576)),-2,0,3,1))-AVERAGE(OFFSET(INDEX(T$18:T$1048576,COUNTA(T$18:T$1048576)),-5,0,3,1)))*52 | U5: {=INDEX(U$30:U$1048576,COUNTA(U$30:U$1048576))-INDEX(U$30:U$1048576,COUNTA(U$30:U$1048576)-3)} | V5: {=INDEX(V$32:V$1048576,COUNTA(V$32:V$1048576))-INDEX(V$32:V$1048576,COUNTA(V$32:V$1048576)-3)} | W5: =(AVERAGE(OFFSET(INDEX(W$18:W$1048576,COUNTA(W$18:W$1048576)),-2,0,3,1))-AVERAGE(OFFSET(INDEX(W$18:W$1048576,COUNTA(W$18:W$1048576)),-5,0,3,1)))*52 | X5: {=INDEX(X$30:X$1048576,COUNTA(X$30:X$1048576))-INDEX(X$30:X$1048576,COUNTA(X$30:X$1048576)-3)} | Y5: {=INDEX(Y$32:Y$1048576,COUNTA(Y$32:Y$1048576))-INDEX(Y$32:Y$1048576,COUNTA(Y$32:Y$1048576)-3)} | Z5: =(AVERAGE(OFFSET(INDEX(Z$18:Z$1048576,COUNTA(Z$18:Z$1048576)),-2,0,3,1))-AVERAGE(OFFSET(INDEX(Z$18:Z$1048576,COUNTA(Z$18:Z$1048576)),-5,0,3,1)))*52 | AA5: {=INDEX(AA$30:AA$1048576,COUNTA(AA$30:AA$1048576))-INDEX(AA$30:AA$1048576,COUNTA(AA$30:AA$1048576)-3)} | AB5: {=INDEX(AB$32:AB$1048576,COUNTA(AB$32:AB$1048576))-INDEX(AB$32:AB$1048576,COUNTA(AB$32:AB$1048576)-3)}
A6: Change year on year | B6: =(AVERAGE(OFFSET(INDEX(B$18:B$1048576,COUNTA(B$18:B$1048576)),-2,0,3,1))-AVERAGE(OFFSET(INDEX(B$18:B$1048576,COUNTA(B$18:B$1048576)),-14,0,3,1)))*52 | C6: {=INDEX(C$30:C$1048576,COUNTA(C$30:C$1048576))-INDEX(C$30:C$1048576,COUNTA(C$30:C$1048576)-12)} | D6: {=INDEX(D$32:D$1048576,COUNTA(D$32:D$1048576))-INDEX(D$32:D$1048576,COUNTA(D$32:D$1048576)-12)} | E6: =(AVERAGE(OFFSET(INDEX(E$18:E$1048576,COUNTA(E$18:E$1048576)),-2,0,3,1))-AVERAGE(OFFSET(INDEX(E$18:E$1048576,COUNTA(E$18:E$1048576)),-14,0,3,1)))*52 | F6: {=INDEX(F$30:F$1048576,COUNTA(F$30:F$1048576))-INDEX(F$30:F$1048576,COUNTA(F$30:F$1048576)-12)} | G6: {=INDEX(G$32:G$1048576,COUNTA(G$32:G$1048576))-INDEX(G$32:G$1048576,COUNTA(G$32:G$1048576)-12)} | H6: =(AVERAGE(OFFSET(INDEX(H$18:H$1048576,COUNTA(H$18:H$1048576)),-2,0,3,1))-AVERAGE(OFFSET(INDEX(H$18:H$1048576,COUNTA(H$18:H$1048576)),-14,0,3,1)))*52 | I6: {=INDEX(I$30:I$1048576,COUNTA(I$30:I$1048576))-INDEX(I$30:I$1048576,COUNTA(I$30:I$1048576)-12)} | J6: {=INDEX(J$32:J$1048576,COUNTA(J$32:J$1048576))-INDEX(J$32:J$1048576,COUNTA(J$32:J$1048576)-12)} | K6: =(AVERAGE(OFFSET(INDEX(K$18:K$1048576,COUNTA(K$18:K$1048576)),-2,0,3,1))-AVERAGE(OFFSET(INDEX(K$18:K$1048576,COUNTA(K$18:K$1048576)),-14,0,3,1)))*52 | L6: {=INDEX(L$30:L$1048576,COUNTA(L$30:L$1048576))-INDEX(L$30:L$1048576,COUNTA(L$30:L$1048576)-12)} | M6: {=INDEX(M$32:M$1048576,COUNTA(M$32:M$1048576))-INDEX(M$32:M$1048576,COUNTA(M$32:M$1048576)-12)} | N6: =(AVERAGE(OFFSET(INDEX(N$18:N$1048576,COUNTA(N$18:N$1048576)),-2,0,3,1))-AVERAGE(OFFSET(INDEX(N$18:N$1048576,COUNTA(N$18:N$1048576)),-14,0,3,1)))*52 | O6: {=INDEX(O$30:O$1048576,COUNTA(O$30:O$1048576))-INDEX(O$30:O$1048576,COUNTA(O$30:O$1048576)-12)} | P6: {=INDEX(P$32:P$1048576,COUNTA(P$32:P$1048576))-INDEX(P$32:P$1048576,COUNTA(P$32:P$1048576)-12)} | Q6: =(AVERAGE(OFFSET(INDEX(Q$18:Q$1048576,COUNTA(Q$18:Q$1048576)),-2,0,3,1))-AVERAGE(OFFSET(INDEX(Q$18:Q$1048576,COUNTA(Q$18:Q$1048576)),-14,0,3,1)))*52 | R6: {=INDEX(R$30:R$1048576,COUNTA(R$30:R$1048576))-INDEX(R$30:R$1048576,COUNTA(R$30:R$1048576)-12)} | S6: {=INDEX(S$32:S$1048576,COUNTA(S$32:S$1048576))-INDEX(S$32:S$1048576,COUNTA(S$32:S$1048576)-12)} | T6: =(AVERAGE(OFFSET(INDEX(T$18:T$1048576,COUNTA(T$18:T$1048576)),-2,0,3,1))-AVERAGE(OFFSET(INDEX(T$18:T$1048576,COUNTA(T$18:T$1048576)),-14,0,3,1)))*52 | U6: {=INDEX(U$30:U$1048576,COUNTA(U$30:U$1048576))-INDEX(U$30:U$1048576,COUNTA(U$30:U$1048576)-12)} | V6: {=INDEX(V$32:V$1048576,COUNTA(V$32:V$1048576))-INDEX(V$32:V$1048576,COUNTA(V$32:V$1048576)-12)} | W6: =(AVERAGE(OFFSET(INDEX(W$18:W$1048576,COUNTA(W$18:W$1048576)),-2,0,3,1))-AVERAGE(OFFSET(INDEX(W$18:W$1048576,COUNTA(W$18:W$1048576)),-14,0,3,1)))*52 | X6: {=INDEX(X$30:X$1048576,COUNTA(X$30:X$1048576))-INDEX(X$30:X$1048576,COUNTA(X$30:X$1048576)-12)} | Y6: {=INDEX(Y$32:Y$1048576,COUNTA(Y$32:Y$1048576))-INDEX(Y$32:Y$1048576,COUNTA(Y$32:Y$1048576)-12)} | Z6: =(AVERAGE(OFFSET(INDEX(Z$18:Z$1048576,COUNTA(Z$18:Z$1048576)),-2,0,3,1))-AVERAGE(OFFSET(INDEX(Z$18:Z$1048576,COUNTA(Z$18:Z$1048576)),-14,0,3,1)))*52 | AA6: {=INDEX(AA$30:AA$1048576,COUNTA(AA$30:AA$1048576))-INDEX(AA$30:AA$1048576,COUNTA(AA$30:AA$1048576)-12)} | AB6: {=INDEX(AB$32:AB$1048576,COUNTA(AB$32:AB$1048576))-INDEX(AB$32:AB$1048576,COUNTA(AB$32:AB$1048576)-12)}
A7: Change since Covid-19 | B7: =(AVERAGE(OFFSET(INDEX(B$18:B$1048576,COUNTA(B$18:B$1048576)),-2,0,3,1))-AVERAGE($B$257:$B$259))*52 | C7: {=INDEX(C$30:C$1048576,COUNTA(C$30:C$1048576))-AVERAGE($C$257:$C$259)} | D7: {=INDEX(D$32:D$1048576,COUNTA(D$32:D$1048576))-AVERAGE($D$257:$D$259)} | E7: =(AVERAGE(OFFSET(INDEX(E$18:E$1048576,COUNTA(E$18:E$1048576)),-2,0,3,1))-AVERAGE($B$257:$B$259))*52 | F7: {=INDEX(F$30:F$1048576,COUNTA(F$30:F$1048576))-AVERAGE($C$257:$C$259)} | G7: {=INDEX(G$32:G$1048576,COUNTA(G$32:G$1048576))-AVERAGE($D$257:$D$259)} | H7: =(AVERAGE(OFFSET(INDEX(H$18:H$1048576,COUNTA(H$18:H$1048576)),-2,0,3,1))-AVERAGE($B$257:$B$259))*52 | I7: {=INDEX(I$30:I$1048576,COUNTA(I$30:I$1048576))-AVERAGE($C$257:$C$259)} | J7: {=INDEX(J$32:J$1048576,COUNTA(J$32:J$1048576))-AVERAGE($D$257:$D$259)} | K7: =(AVERAGE(OFFSET(INDEX(K$18:K$1048576,COUNTA(K$18:K$1048576)),-2,0,3,1))-AVERAGE($B$257:$B$259))*52 | L7: {=INDEX(L$30:L$1048576,COUNTA(L$30:L$1048576))-AVERAGE($C$257:$C$259)} | M7: {=INDEX(M$32:M$1048576,COUNTA(M$32:M$1048576))-AVERAGE($D$257:$D$259)} | N7: =(AVERAGE(OFFSET(INDEX(N$18:N$1048576,COUNTA(N$18:N$1048576)),-2,0,3,1))-AVERAGE($B$257:$B$259))*52 | O7: {=INDEX(O$30:O$1048576,COUNTA(O$30:O$1048576))-AVERAGE($C$257:$C$259)} | P7: {=INDEX(P$32:P$1048576,COUNTA(P$32:P$1048576))-AVERAGE($D$257:$D$259)} | Q7: =(AVERAGE(OFFSET(INDEX(Q$18:Q$1048576,COUNTA(Q$18:Q$1048576)),-2,0,3,1))-AVERAGE($B$257:$B$259))*52 | R7: {=INDEX(R$30:R$1048576,COUNTA(R$30:R$1048576))-AVERAGE($C$257:$C$259)} | S7: {=INDEX(S$32:S$1048576,COUNTA(S$32:S$1048576))-AVERAGE($D$257:$D$259)} | T7: =(AVERAGE(OFFSET(INDEX(T$18:T$1048576,COUNTA(T$18:T$1048576)),-2,0,3,1))-AVERAGE($B$257:$B$259))*52 | U7: {=INDEX(U$30:U$1048576,COUNTA(U$30:U$1048576))-AVERAGE($C$257:$C$259)} | V7: {=INDEX(V$32:V$1048576,COUNTA(V$32:V$1048576))-AVERAGE($D$257:$D$259)} | W7: =(AVERAGE(OFFSET(INDEX(W$18:W$1048576,COUNTA(W$18:W$1048576)),-2,0,3,1))-AVERAGE($B$257:$B$259))*52 | X7: {=INDEX(X$30:X$1048576,COUNTA(X$30:X$1048576))-AVERAGE($C$257:$C$259)} | Y7: {=INDEX(Y$32:Y$1048576,COUNTA(Y$32:Y$1048576))-AVERAGE($D$257:$D$259)} | Z7: =(AVERAGE(OFFSET(INDEX(Z$18:Z$1048576,COUNTA(Z$18:Z$1048576)),-2,0,3,1))-AVERAGE($B$257:$B$259))*52 | AA7: {=INDEX(AA$30:AA$1048576,COUNTA(AA$30:AA$1048576))-AVERAGE($C$257:$C$259)} | AB7: {=INDEX(AB$32:AB$1048576,COUNTA(AB$32:AB$1048576))-AVERAGE($D$257:$D$259)}
A9: Table 13: Average Weekly Earnings (nominal) - Total Pay (Great Britain, seasonally adjusted)1 | M9: Source: Monthly Wages & Salaries Survey
A10: Date of publication: | E10: 45643 | H10: Date of next publication: | L10: 45678
A11: Inquiries: Email: | C11: labour.market@ons.gov.uk | J11: Tel: 01633 455400
A12: Standard Industrial Classification (2007)
B13: Whole Economy | E13: Private sector3 4 5 | H13: Public sector3 4 5 | K13: Services, SIC 2007 sections G-S | N13: Finance and business services, SIC 2007 sections K-N | Q13: Public sector excluding financial services 4 5 | T13: Manufacturing, SIC 2007 section C | W13: Construction, SIC 2007 section F | Z13: Wholesaling, retailing, hotels & restaurants, SIC 2007 sections G & I
B14: Weekly Earnings (£) | C14: % changes year on year | E14: Weekly Earnings (£) | F14: % changes year on year | H14: Weekly Earnings (£) | I14: % changes year on year | K14: Weekly Earnings (£) | L14: % changes year on year | N14: Weekly Earnings (£) | O14: % changes year on year | Q14: Weekly Earnings (£) | R14: % changes year on year | T14: Weekly Earnings (£) | U14: % changes year on year | W14: Weekly Earnings (£) | X14: % changes year on year | Z14: Weekly Earnings (£) | AA14: % changes year on year
C15: Single month | D15: 3 month average 2 | F15: Single month | G15: 3 month average 2 | I15: Single month | J15: 3 month average 2 | L15: Single month | M15: 3 month average 2 | O15: Single month | P15: 3 month average 2 | R15: Single month | S15: 3 month average 2 | U15: Single month | V15: 3 month average 2 | X15: Single month | Y15: 3 month average 2 | AA15: Single month | AB15: 3 month average 2
B16: KAB9 | C16: KAC2 | D16: KAC3 | E16: KAC4 | F16: KAC5 | G16: KAC6 | H16: KAC7 | I16: KAC8 | J16: KAC9 | K16: K5BZ | L16: K5C2 | M16: K5C3 | N16: K5C4 | O16: K5C5 | P16: K5C6 | Q16: KAD8 | R16: KAD9 | S16: KAE2 | T16: K5CA | U16: K5CB | V16: K5CC | W16: K5CD | X16: K5CE | Y16: K5CF | Z16: K5CG | AA16: K5CH | AB16: K5CI

Sheet 15
B1: Whole Economy | E1: Private sector 3 4 5 | H1: Public sector 3 4 5 | K1: Services, SIC 2007 sections G-S | N1: Finance and business services, SIC 2007 sections K-N | Q1: Public sector excluding financial services 4 5 | T1: Manufacturing, SIC 2007 section C | W1: Construction, SIC 2007 section F | Z1: Wholesaling, retailing, hotels & restaurants, SIC 2007 sections G & I
B2: Weekly Earnings (£) | C2: % changes year on year | E2: Weekly Earnings (£) | F2: % changes year on year | H2: Weekly Earnings (£) | I2: % changes year on year | K2: Weekly Earnings (£) | L2: % changes year on year | N2: Weekly Earnings (£) | O2: % changes year on year | Q2: Weekly Earnings (£) | R2: % changes year on year | T2: Weekly Earnings (£) | U2: % changes year on year | W2: Weekly Earnings (£) | X2: % changes year on year | Z2: Weekly Earnings (£) | AA2: % changes year on year
C3: Single month | D3: 3 month average 2 | F3: Single month | G3: 3 month average 2 | I3: Single month | J3: 3 month average 2 | L3: Single month | M3: 3 month average 2 | O3: Single month | P3: 3 month average 2 | R3: Single month | S3: 3 month average 2 | U3: Single month | V3: 3 month average 2 | X3: Single month | Y3: 3 month average 2 | AA3: Single month | AB3: 3 month average 2
A4: Current | B4: {=INDEX(B$19:B$1048576,COUNTA(B$19:B$1048576))} | C4: {=INDEX(C$31:C$1048576,COUNTA(C$31:C$1048576))} | D4: {=INDEX(D$33:D$1048576,COUNTA(D$33:D$1048576))} | E4: {=INDEX(E$19:E$1048576,COUNTA(E$19:E$1048576))} | F4: {=INDEX(F$31:F$1048576,COUNTA(F$31:F$1048576))} | G4: {=INDEX(G$33:G$1048576,COUNTA(G$33:G$1048576))} | H4: {=INDEX(H$19:H$1048576,COUNTA(H$19:H$1048576))} | I4: {=INDEX(I$31:I$1048576,COUNTA(I$31:I$1048576))} | J4: {=INDEX(J$33:J$1048576,COUNTA(J$33:J$1048576))} | K4: {=INDEX(K$19:K$1048576,COUNTA(K$19:K$1048576))} | L4: {=INDEX(L$31:L$1048576,COUNTA(L$31:L$1048576))} | M4: {=INDEX(M$33:M$1048576,COUNTA(M$33:M$1048576))} | N4: {=INDEX(N$19:N$1048576,COUNTA(N$19:N$1048576))} | O4: {=INDEX(O$31:O$1048576,COUNTA(O$31:O$1048576))} | P4: {=INDEX(P$33:P$1048576,COUNTA(P$33:P$1048576))} | Q4: {=INDEX(Q$19:Q$1048576,COUNTA(Q$19:Q$1048576))} | R4: {=INDEX(R$31:R$1048576,COUNTA(R$31:R$1048576))} | S4: {=INDEX(S$33:S$1048576,COUNTA(S$33:S$1048576))} | T4: {=INDEX(T$19:T$1048576,COUNTA(T$19:T$1048576))} | U4: {=INDEX(U$31:U$1048576,COUNTA(U$31:U$1048576))} | V4: {=INDEX(V$33:V$1048576,COUNTA(V$33:V$1048576))} | W4: {=INDEX(W$19:W$1048576,COUNTA(W$19:W$1048576))} | X4: {=INDEX(X$31:X$1048576,COUNTA(X$31:X$1048576))} | Y4: {=INDEX(Y$33:Y$1048576,COUNTA(Y$33:Y$1048576))} | Z4: {=INDEX(Z$19:Z$1048576,COUNTA(Z$19:Z$1048576))} | AA4: {=INDEX(AA$31:AA$1048576,COUNTA(AA$31:AA$1048576))} | AB4: {=INDEX(AB$33:AB$1048576,COUNTA(AB$33:AB$1048576))}
A5: Quarterly change | B5: {=INDEX(B$19:B$1048576,COUNTA(B$19:B$1048576))-INDEX(B$19:B$1048576,COUNTA(B$19:B$1048576)-3)} | C5: {=INDEX(C$31:C$1048576,COUNTA(C$31:C$1048576))-INDEX(C$31:C$1048576,COUNTA(C$31:C$1048576)-3)} | D5: {=INDEX(D$33:D$1048576,COUNTA(D$33:D$1048576))-INDEX(D$33:D$1048576,COUNTA(D$33:D$1048576)-3)} | E5: {=INDEX(E$19:E$1048576,COUNTA(E$19:E$1048576))-INDEX(E$19:E$1048576,COUNTA(E$19:E$1048576)-3)} | F5: {=INDEX(F$31:F$1048576,COUNTA(F$31:F$1048576))-INDEX(F$31:F$1048576,COUNTA(F$31:F$1048576)-3)} | G5: {=INDEX(G$33:G$1048576,COUNTA(G$33:G$1048576))-INDEX(G$33:G$1048576,COUNTA(G$33:G$1048576)-3)} | H5: {=INDEX(H$19:H$1048576,COUNTA(H$19:H$1048576))-INDEX(H$19:H$1048576,COUNTA(H$19:H$1048576)-3)} | I5: {=INDEX(I$31:I$1048576,COUNTA(I$31:I$1048576))-INDEX(I$31:I$1048576,COUNTA(I$31:I$1048576)-3)} | J5: {=INDEX(J$33:J$1048576,COUNTA(J$33:J$1048576))-INDEX(J$33:J$1048576,COUNTA(J$33:J$1048576)-3)} | K5: {=INDEX(K$19:K$1048576,COUNTA(K$19:K$1048576))-INDEX(K$19:K$1048576,COUNTA(K$19:K$1048576)-3)} | L5: {=INDEX(L$31:L$1048576,COUNTA(L$31:L$1048576))-INDEX(L$31:L$1048576,COUNTA(L$31:L$1048576)-3)} | M5: {=INDEX(M$33:M$1048576,COUNTA(M$33:M$1048576))-INDEX(M$33:M$1048576,COUNTA(M$33:M$1048576)-3)} | N5: {=INDEX(N$19:N$1048576,COUNTA(N$19:N$1048576))-INDEX(N$19:N$1048576,COUNTA(N$19:N$1048576)-3)} | O5: {=INDEX(O$31:O$1048576,COUNTA(O$31:O$1048576))-INDEX(O$31:O$1048576,COUNTA(O$31:O$1048576)-3)} | P5: {=INDEX(P$33:P$1048576,COUNTA(P$33:P$1048576))-INDEX(P$33:P$1048576,COUNTA(P$33:P$1048576)-3)} | Q5: {=INDEX(Q$19:Q$1048576,COUNTA(Q$19:Q$1048576))-INDEX(Q$19:Q$1048576,COUNTA(Q$19:Q$1048576)-3)} | R5: {=INDEX(R$31:R$1048576,COUNTA(R$31:R$1048576))-INDEX(R$31:R$1048576,COUNTA(R$31:R$1048576)-3)} | S5: {=INDEX(S$33:S$1048576,COUNTA(S$33:S$1048576))-INDEX(S$33:S$1048576,COUNTA(S$33:S$1048576)-3)} | T5: {=INDEX(T$19:T$1048576,COUNTA(T$19:T$1048576))-INDEX(T$19:T$1048576,COUNTA(T$19:T$1048576)-3)} | U5: {=INDEX(U$31:U$1048576,COUNTA(U$31:U$1048576))-INDEX(U$31:U$1048576,COUNTA(U$31:U$1048576)-3)} | V5: {=INDEX(V$33:V$1048576,COUNTA(V$33:V$1048576))-INDEX(V$33:V$1048576,COUNTA(V$33:V$1048576)-3)} | W5: {=INDEX(W$19:W$1048576,COUNTA(W$19:W$1048576))-INDEX(W$19:W$1048576,COUNTA(W$19:W$1048576)-3)} | X5: {=INDEX(X$31:X$1048576,COUNTA(X$31:X$1048576))-INDEX(X$31:X$1048576,COUNTA(X$31:X$1048576)-3)} | Y5: {=INDEX(Y$33:Y$1048576,COUNTA(Y$33:Y$1048576))-INDEX(Y$33:Y$1048576,COUNTA(Y$33:Y$1048576)-3)} | Z5: {=INDEX(Z$19:Z$1048576,COUNTA(Z$19:Z$1048576))-INDEX(Z$19:Z$1048576,COUNTA(Z$19:Z$1048576)-3)} | AA5: {=INDEX(AA$31:AA$1048576,COUNTA(AA$31:AA$1048576))-INDEX(AA$31:AA$1048576,COUNTA(AA$31:AA$1048576)-3)} | AB5: {=INDEX(AB$33:AB$1048576,COUNTA(AB$33:AB$1048576))-INDEX(AB$33:AB$1048576,COUNTA(AB$33:AB$1048576)-3)}
A6: year on year change | B6: {=INDEX(B$19:B$1048576,COUNTA(B$19:B$1048576))-INDEX(B$19:B$1048576,COUNTA(B$19:B$1048576)-12)} | C6: {=INDEX(C$31:C$1048576,COUNTA(C$31:C$1048576))-INDEX(C$31:C$1048576,COUNTA(C$31:C$1048576)-12)} | D6: {=INDEX(D$33:D$1048576,COUNTA(D$33:D$1048576))-INDEX(D$33:D$1048576,COUNTA(D$33:D$1048576)-12)} | E6: {=INDEX(E$19:E$1048576,COUNTA(E$19:E$1048576))-INDEX(E$19:E$1048576,COUNTA(E$19:E$1048576)-12)} | F6: {=INDEX(F$31:F$1048576,COUNTA(F$31:F$1048576))-INDEX(F$31:F$1048576,COUNTA(F$31:F$1048576)-12)} | G6: {=INDEX(G$33:G$1048576,COUNTA(G$33:G$1048576))-INDEX(G$33:G$1048576,COUNTA(G$33:G$1048576)-12)} | H6: {=INDEX(H$19:H$1048576,COUNTA(H$19:H$1048576))-INDEX(H$19:H$1048576,COUNTA(H$19:H$1048576)-12)} | I6: {=INDEX(I$31:I$1048576,COUNTA(I$31:I$1048576))-INDEX(I$31:I$1048576,COUNTA(I$31:I$1048576)-12)} | J6: {=INDEX(J$33:J$1048576,COUNTA(J$33:J$1048576))-INDEX(J$33:J$1048576,COUNTA(J$33:J$1048576)-12)} | K6: {=INDEX(K$19:K$1048576,COUNTA(K$19:K$1048576))-INDEX(K$19:K$1048576,COUNTA(K$19:K$1048576)-12)} | L6: {=INDEX(L$31:L$1048576,COUNTA(L$31:L$1048576))-INDEX(L$31:L$1048576,COUNTA(L$31:L$1048576)-12)} | M6: {=INDEX(M$33:M$1048576,COUNTA(M$33:M$1048576))-INDEX(M$33:M$1048576,COUNTA(M$33:M$1048576)-12)} | N6: {=INDEX(N$19:N$1048576,COUNTA(N$19:N$1048576))-INDEX(N$19:N$1048576,COUNTA(N$19:N$1048576)-12)} | O6: {=INDEX(O$31:O$1048576,COUNTA(O$31:O$1048576))-INDEX(O$31:O$1048576,COUNTA(O$31:O$1048576)-12)} | P6: {=INDEX(P$33:P$1048576,COUNTA(P$33:P$1048576))-INDEX(P$33:P$1048576,COUNTA(P$33:P$1048576)-12)} | Q6: {=INDEX(Q$19:Q$1048576,COUNTA(Q$19:Q$1048576))-INDEX(Q$19:Q$1048576,COUNTA(Q$19:Q$1048576)-12)} | R6: {=INDEX(R$31:R$1048576,COUNTA(R$31:R$1048576))-INDEX(R$31:R$1048576,COUNTA(R$31:R$1048576)-12)} | S6: {=INDEX(S$33:S$1048576,COUNTA(S$33:S$1048576))-INDEX(S$33:S$1048576,COUNTA(S$33:S$1048576)-12)} | T6: {=INDEX(T$19:T$1048576,COUNTA(T$19:T$1048576))-INDEX(T$19:T$1048576,COUNTA(T$19:T$1048576)-12)} | U6: {=INDEX(U$31:U$1048576,COUNTA(U$31:U$1048576))-INDEX(U$31:U$1048576,COUNTA(U$31:U$1048576)-12)} | V6: {=INDEX(V$33:V$1048576,COUNTA(V$33:V$1048576))-INDEX(V$33:V$1048576,COUNTA(V$33:V$1048576)-12)} | W6: {=INDEX(W$19:W$1048576,COUNTA(W$19:W$1048576))-INDEX(W$19:W$1048576,COUNTA(W$19:W$1048576)-12)} | X6: {=INDEX(X$31:X$1048576,COUNTA(X$31:X$1048576))-INDEX(X$31:X$1048576,COUNTA(X$31:X$1048576)-12)} | Y6: {=INDEX(Y$33:Y$1048576,COUNTA(Y$33:Y$1048576))-INDEX(Y$33:Y$1048576,COUNTA(Y$33:Y$1048576)-12)} | Z6: {=INDEX(Z$19:Z$1048576,COUNTA(Z$19:Z$1048576))-INDEX(Z$19:Z$1048576,COUNTA(Z$19:Z$1048576)-12)} | AA6: {=INDEX(AA$31:AA$1048576,COUNTA(AA$31:AA$1048576))-INDEX(AA$31:AA$1048576,COUNTA(AA$31:AA$1048576)-12)} | AB6: {=INDEX(AB$33:AB$1048576,COUNTA(AB$33:AB$1048576))-INDEX(AB$33:AB$1048576,COUNTA(AB$33:AB$1048576)-12)}
A7: Since pandemic | B7: {=INDEX(B$19:B$1048576,COUNTA(B$19:B$1048576))-B$260} | C7: {=INDEX(C$31:C$1048576,COUNTA(C$31:C$1048576))-C$260} | D7: {=INDEX(D$31:D$1048576,COUNTA(D$31:D$1048576))-D$260} | E7: {=INDEX(E$19:E$1048576,COUNTA(E$19:E$1048576))-E$260} | F7: {=INDEX(F$31:F$1048576,COUNTA(F$31:F$1048576))-F$260} | G7: {=INDEX(G$31:G$1048576,COUNTA(G$31:G$1048576))-G$260} | H7: {=INDEX(H$19:H$1048576,COUNTA(H$19:H$1048576))-H$260} | I7: {=INDEX(I$31:I$1048576,COUNTA(I$31:I$1048576))-I$260} | J7: {=INDEX(J$31:J$1048576,COUNTA(J$31:J$1048576))-J$260} | K7: {=INDEX(K$19:K$1048576,COUNTA(K$19:K$1048576))-K$260} | L7: {=INDEX(L$31:L$1048576,COUNTA(L$31:L$1048576))-L$260} | M7: {=INDEX(M$31:M$1048576,COUNTA(M$31:M$1048576))-M$260} | N7: {=INDEX(N$19:N$1048576,COUNTA(N$19:N$1048576))-N$260} | O7: {=INDEX(O$31:O$1048576,COUNTA(O$31:O$1048576))-O$260} | P7: {=INDEX(P$31:P$1048576,COUNTA(P$31:P$1048576))-P$260} | Q7: {=INDEX(Q$19:Q$1048576,COUNTA(Q$19:Q$1048576))-Q$260} | R7: {=INDEX(R$31:R$1048576,COUNTA(R$31:R$1048576))-R$260} | S7: {=INDEX(S$31:S$1048576,COUNTA(S$31:S$1048576))-S$260} | T7: {=INDEX(T$19:T$1048576,COUNTA(T$19:T$1048576))-T$260} | U7: {=INDEX(U$31:U$1048576,COUNTA(U$31:U$1048576))-U$260} | V7: {=INDEX(V$31:V$1048576,COUNTA(V$31:V$1048576))-V$260} | W7: {=INDEX(W$19:W$1048576,COUNTA(W$19:W$1048576))-W$260} | X7: {=INDEX(X$31:X$1048576,COUNTA(X$31:X$1048576))-X$260} | Y7: {=INDEX(Y$31:Y$1048576,COUNTA(Y$31:Y$1048576))-Y$260} | Z7: {=INDEX(Z$19:Z$1048576,COUNTA(Z$19:Z$1048576))-Z$260} | AA7: {=INDEX(AA$31:AA$1048576,COUNTA(AA$31:AA$1048576))-AA$260} | AB7: {=INDEX(AB$31:AB$1048576,COUNTA(AB$31:AB$1048576))-AB$260}
A8: Since 2010 election | B8: {=INDEX(B$19:B$1048576,COUNTA(B$19:B$1048576))-B$142} | C8: {=INDEX(C$31:C$1048576,COUNTA(C$31:C$1048576))-C$142} | D8: {=INDEX(D$31:D$1048576,COUNTA(D$31:D$1048576))-D$142} | E8: {=INDEX(E$19:E$1048576,COUNTA(E$19:E$1048576))-E$142} | F8: {=INDEX(F$31:F$1048576,COUNTA(F$31:F$1048576))-F$142} | G8: {=INDEX(G$31:G$1048576,COUNTA(G$31:G$1048576))-G$142} | H8: {=INDEX(H$19:H$1048576,COUNTA(H$19:H$1048576))-H$142} | I8: {=INDEX(I$31:I$1048576,COUNTA(I$31:I$1048576))-I$142} | J8: {=INDEX(J$31:J$1048576,COUNTA(J$31:J$1048576))-J$142} | K8: {=INDEX(K$19:K$1048576,COUNTA(K$19:K$1048576))-K$142} | L8: {=INDEX(L$31:L$1048576,COUNTA(L$31:L$1048576))-L$142} | M8: {=INDEX(M$31:M$1048576,COUNTA(M$31:M$1048576))-M$142} | N8: {=INDEX(N$19:N$1048576,COUNTA(N$19:N$1048576))-N$142} | O8: {=INDEX(O$31:O$1048576,COUNTA(O$31:O$1048576))-O$142} | P8: {=INDEX(P$31:P$1048576,COUNTA(P$31:P$1048576))-P$142} | Q8: {=INDEX(Q$19:Q$1048576,COUNTA(Q$19:Q$1048576))-Q$142} | R8: {=INDEX(R$31:R$1048576,COUNTA(R$31:R$1048576))-R$142} | S8: {=INDEX(S$31:S$1048576,COUNTA(S$31:S$1048576))-S$142} | T8: {=INDEX(T$19:T$1048576,COUNTA(T$19:T$1048576))-T$142} | U8: {=INDEX(U$31:U$1048576,COUNTA(U$31:U$1048576))-U$142} | V8: {=INDEX(V$31:V$1048576,COUNTA(V$31:V$1048576))-V$142} | W8: {=INDEX(W$19:W$1048576,COUNTA(W$19:W$1048576))-W$142} | X8: {=INDEX(X$31:X$1048576,COUNTA(X$31:X$1048576))-X$142} | Y8: {=INDEX(Y$31:Y$1048576,COUNTA(Y$31:Y$1048576))-Y$142} | Z8: {=INDEX(Z$19:Z$1048576,COUNTA(Z$19:Z$1048576))-Z$142} | AA8: {=INDEX(AA$31:AA$1048576,COUNTA(AA$31:AA$1048576))-AA$142} | AB8: {=INDEX(AB$31:AB$1048576,COUNTA(AB$31:AB$1048576))-AB$142}
A10: Table 15: Average Weekly Earnings (nominal) - Regular Pay (Great Britain, seasonally adjusted)1 | M10: Source: Monthly Wages & Salaries Survey
A11: Date of publication: | E11: 45643 | H11: Date of next publication: | L11: 45678
A12: Inquiries: Email: | C12: labour.market@ons.gov.uk | J12: Tel: 01633 455400
A13: Standard Industrial Classification (2007)
B14: Whole Economy | E14: Private sector 3 4 5 | H14: Public sector 3 4 5 | K14: Services, SIC 2007 sections G-S | N14: Finance and business services, SIC 2007 sections K-N | Q14: Public sector excluding financial services 4 5 | T14: Manufacturing, SIC 2007 section C | W14: Construction, SIC 2007 section F | Z14: Wholesaling, retailing, hotels & restaurants, SIC 2007 sections G & I
B15: Weekly Earnings (£) | C15: % changes year on year | E15: Weekly Earnings (£) | F15: % changes year on year | H15: Weekly Earnings (£) | I15: % changes year on year | K15: Weekly Earnings (£) | L15: % changes year on year | N15: Weekly Earnings (£) | O15: % changes year on year | Q15: Weekly Earnings (£) | R15: % changes year on year | T15: Weekly Earnings (£) | U15: % changes year on year | W15: Weekly Earnings (£) | X15: % changes year on year | Z15: Weekly Earnings (£) | AA15: % changes year on year
C16: Single month | D16: 3 month average 2 | F16: Single month | G16: 3 month average 2 | I16: Single month | J16: 3 month average 2 | L16: Single month | M16: 3 month average 2 | O16: Single month | P16: 3 month average 2 | R16: Single month | S16: 3 month average 2 | U16: Single month | V16: 3 month average 2 | X16: Single month | Y16: 3 month average 2 | AA16: Single month | AB16: 3 month average 2
B17: KAI7 | C17: KAI8 | D17: KAI9 | E17: KAJ2 | F17: KAJ3 | G17: KAJ4 | H17: KAJ5 | I17: KAJ6 | J17: KAJ7 | K17: K5DL | L17: K5DM | M17: K5DN | N17: K5DO | O17: K5DP | P17: K5DQ | Q17: KAK6 | R17: KAK7 | S17: KAK8 | T17: K5DU | U17: K5DV | V17: K5DW | W17: K5DX | X17: K5DY | Y17: K5DZ | Z17: K5E2 | AA17: K5E3 | AB17: K5E4

Sheet 18
B1: Working days lost (thousands) | C1: Number of stoppages 1,2 | D1: Workers involved (thousands) 3
A2: Current (singular month) | B2: {=INDEX(B$16:B$1048576,COUNTA(B$16:B$1048576))} | C2: {=INDEX(C$16:C$1048576,COUNTA(C$16:C$1048576))} | D2: {=INDEX(D$16:D$1048576,COUNTA(D$16:D$1048576))}
A3: Change on quarter (3mo avg) | B3: =(AVERAGE(OFFSET(INDEX(B$16:B$1048576,COUNTA(B$16:B$1048576)),-2,0,3,1))-AVERAGE(OFFSET(INDEX(B$16:B$1048576,COUNTA(B$16:B$1048576)),-5,0,3,1)))*52 | C3: =AVERAGE(OFFSET(INDEX(C$16:C$1048576,COUNTA(C$16:C$1048576)),-2,0,3,1))-AVERAGE(OFFSET(INDEX(C$16:C$1048576,COUNTA(C$16:C$1048576)),-5,0,3,1)) | D3: =AVERAGE(OFFSET(INDEX(D$16:D$1048576,COUNTA(D$16:D$1048576)),-2,0,3,1))-AVERAGE(OFFSET(INDEX(D$16:D$1048576,COUNTA(D$16:D$1048576)),-5,0,3,1))
A4: Change since Covid-19 (2019 average) | B4: =(AVERAGE(OFFSET(INDEX(B$16:B$1048576,COUNTA(B$16:B$1048576)),-2,0,3,1))-AVERAGE(B$1072:B$1083))*52 | C4: =AVERAGE(OFFSET(INDEX(C$16:C$1048576,COUNTA(C$16:C$1048576)),-2,0,3,1))-AVERAGE(C$1072:C$1083) | D4: =AVERAGE(OFFSET(INDEX(D$16:D$1048576,COUNTA(D$16:D$1048576)),-2,0,3,1))-AVERAGE(D$1072:D$1083)
A5: Change since 2024 election (3mo avg) | B5: =(AVERAGE(OFFSET(INDEX(B$16:B$1048576,COUNTA(B$16:B$1048576)),-2,0,3,1))-AVERAGE(B$1135:B$1137))*52 | C5: =AVERAGE(OFFSET(INDEX(C$16:C$1048576,COUNTA(C$16:C$1048576)),-2,0,3,1))-AVERAGE(C$1135:C$1137) | D5: =AVERAGE(OFFSET(INDEX(D$16:D$1048576,COUNTA(D$16:D$1048576)),-2,0,3,1))-AVERAGE(D$1135:D$1137)
A6: 2019 average | B6: =AVERAGE(B$1072:B$1083) | C6: =AVERAGE(C$1072:C$1083) | D6: =AVERAGE(D$1072:D$1083)
A7: 2023 average | B7: =AVERAGE(B$1120:B$1131) | C7: =AVERAGE(C$1120:C$1131) | D7: =AVERAGE(D$1120:D$1131)
A9: Table 18: Labour Disputes summary, UK (not seasonally adjusted)

Sheet 20
B1: All Vacancies1 (thousands) | C1: Unemployment2 (thousands) | D1: Number of unemployed people per vacancy | G1: All Vacancies1 (thousands) | H1: Unemployment2 (thousands) | I1: Number of unemployed people per vacancy
A2: Current | B2: {=INDEX(C$17:C$1048576,COUNTA(C$17:C$1048576))} | C2: {=INDEX(D$17:D$1048576,COUNTA(D$17:D$1048576)-1)} | D2: {=INDEX(E$17:E$1048576,COUNTA(E$17:E$1048576)-1)} | F2: Current | G2: =B2 | H2: =C2 | I2: =D2
A3: Quarterly change | B3: {=INDEX(C$17:C$1048576,COUNTA(C$17:C$1048576))-INDEX(C$17:C$1048576,COUNTA(C$17:C$1048576)-3)} | C3: {=INDEX(D$17:D$1048576,COUNTA(D$17:D$1048576)-1)-INDEX(D$17:D$1048576,COUNTA(D$17:D$1048576)-4)} | D3: {=INDEX(E$17:E$1048576,COUNTA(E$17:E$1048576)-1)-INDEX(E$17:E$1048576,COUNTA(E$17:E$1048576)-4)} | F3: Quarterly change | G3: {=B3/INDEX(C$17:C$1048576,COUNTA(C$17:C$1048576)-1)} | H3: {=C3/INDEX(D$17:D$1048576,COUNTA(D$17:D$1048576)-2)} | I3: {=D3/INDEX(E$17:E$1048576,COUNTA(E$17:E$1048576)-2)}
A4: Year on year change | B4: {=INDEX(C$17:C$1048576,COUNTA(C$17:C$1048576))-INDEX(C$17:C$1048576,COUNTA(C$17:C$1048576)-12)} | C4: {=INDEX(D$17:D$1048576,COUNTA(D$17:D$1048576)-1)-INDEX(D$17:D$1048576,COUNTA(D$17:D$1048576)-13)} | D4: {=INDEX(E$17:E$1048576,COUNTA(E$17:E$1048576)-1)-INDEX(E$17:E$1048576,COUNTA(E$17:E$1048576)-13)} | F4: Year on year change | G4: {=B4/INDEX(C$17:C$1048576,COUNTA(C$17:C$1048576)-12)} | H4: {=C4/INDEX(D$17:D$1048576,COUNTA(D$17:D$1048576)-13)} | I4: {=D4/INDEX(E$17:E$1048576,COUNTA(E$17:E$1048576)-13)}
A5: Pre-pandemic trend (Jan-Mar) | B5: {=INDEX(C$17:C$1048576,COUNTA(C$17:C$1048576))-C$242} | C5: {=INDEX(D$17:D$1048576,COUNTA(D$17:D$1048576)-1)-D$242} | D5: {=INDEX(E$17:E$1048576,COUNTA(E$17:E$1048576)-1)-E$242} | F5: Pre-pandemic trend (Jan-Mar) | G5: =B5/C242 | H5: =C5/D242 | I5: =D5/E242
A6: Since 2024 election | B6: {=INDEX(C$17:C$1048576,COUNTA(C$17:C$1048576))-C$293} | C6: {=INDEX(D$17:D$1048576,COUNTA(D$17:D$1048576)-1)-D$293} | D6: {=INDEX(E$17:E$1048576,COUNTA(E$17:E$1048576)-1)-E$293} | F6: Since 2010 election | G6: =B6/C123 | H6: =C6/D123 | I6: =D6/E123
A7: *note: 1. Stats for unemployment are from the period before as data unavailable - check this is still the case.
A8: 2. Covid period is different (Jan-Mar) due to reporting periods
A9: Table 20: Vacancies1 and Unemployment (seasonally adjusted)

Sheet 21
C1: All vacancies1 | D1: Mining & quarrying | E1: Manu- facturing | F1: Electricity, gas, steam & air conditioning supply2 | G1: Water supply, sewerage, waste & remediation activities | H1: Construc-tion | I1: Wholesale & retail trade; repair of motor vehicles and motor cycles | J1: Transport & storage | K1: Accomoda-tion & food service activities | L1: Information & communica-tion | M1: Financial & insurance activities | N1: Real estate activities2 | O1: Professional scientific & technical activities | P1: Administra-tive & support service activities | Q1: Public admin & defence; compulsory social security | R1: Education | S1: Human health & social work activities | T1: Arts, entertainment & recreation | U1: Other service activities | V1: Total services | W1: Motor Trades | X1: Wholesale | Y1: Retail
B2: Current | C2: {=INDEX(C$19:C$1048576,COUNTA(C$19:C$1048576))} | D2: {=INDEX(D$19:D$1048576,COUNTA(D$19:D$1048576))} | E2: {=INDEX(E$19:E$1048576,COUNTA(E$19:E$1048576))} | F2: {=INDEX(F$19:F$1048576,COUNTA(F$19:F$1048576))} | G2: {=INDEX(G$19:G$1048576,COUNTA(G$19:G$1048576))} | H2: {=INDEX(H$19:H$1048576,COUNTA(H$19:H$1048576))} | I2: {=INDEX(I$19:I$1048576,COUNTA(I$19:I$1048576))} | J2: {=INDEX(J$19:J$1048576,COUNTA(J$19:J$1048576))} | ... Y2: {=INDEX(Y$19:Y$1048576,COUNTA(Y$19:Y$1048576))}
B3: Quarterly change | C3: {=INDEX(C$19:C$1048576,COUNTA(C$19:C$1048576))-INDEX(C$19:C$1048576,COUNTA(C$19:C$1048576)-3)} | D3: {=INDEX(D$19:D$1048576,COUNTA(D$19:D$1048576))/INDEX(D$19:D$1048576,COUNTA(D$19:D$1048576)-3)-1} | E3: {=INDEX(E$19:E$1048576,COUNTA(E$19:E$1048576))/INDEX(E$19:E$1048576,COUNTA(E$19:E$1048576)-3)-1} | F3: {=INDEX(F$19:F$1048576,COUNTA(F$19:F$1048576))/INDEX(F$19:F$1048576,COUNTA(F$19:F$1048576)-3)-1} | G3: {=INDEX(G$19:G$1048576,COUNTA(G$19:G$1048576))/INDEX(G$19:G$1048576,COUNTA(G$19:G$1048576)-3)-1} | H3: {=INDEX(H$19:H$1048576,COUNTA(H$19:H$1048576))/INDEX(H$19:H$1048576,COUNTA(H$19:H$1048576)-3)-1} | I3: {=INDEX(I$19:I$1048576,COUNTA(I$19:I$1048576))/INDEX(I$19:I$1048576,COUNTA(I$19:I$1048576)-3)-1} | J3: {=INDEX(J$19:J$1048576,COUNTA(J$19:J$1048576))/INDEX(J$19:J$1048576,COUNTA(J$19:J$1048576)-3)-1} | K3: {=INDEX(K$19:K$1048576,COUNTA(K$19:K$1048576))/INDEX(K$19:K$1048576,COUNTA(K$19:K$1048576)-3)-1} | ... Y3: {=INDEX(Y$19:Y$1048576,COUNTA(Y$19:Y$1048576))/INDEX(Y$19:Y$1048576,COUNTA(Y$19:Y$1048576)-3)-1}
B4: year on year change | C4: {=INDEX(C$19:C$1048576,COUNTA(C$19:C$1048576))-INDEX(C$19:C$1048576,COUNTA(C$19:C$1048576)-12)} | D4: {=INDEX(D$19:D$1048576,COUNTA(D$19:D$1048576))/INDEX(D$19:D$1048576,COUNTA(D$19:D$1048576)-12)-1} | E4: {=INDEX(E$19:E$1048576,COUNTA(E$19:E$1048576))/INDEX(E$19:E$1048576,COUNTA(E$19:E$1048576)-12)-1} | F4: {=INDEX(F$19:F$1048576,COUNTA(F$19:F$1048576))/INDEX(F$19:F$1048576,COUNTA(F$19:F$1048576)-12)-1} | G4: {=INDEX(G$19:G$1048576,COUNTA(G$19:G$1048576))/INDEX(G$19:G$1048576,COUNTA(G$19:G$1048576)-12)-1} | H4: {=INDEX(H$19:H$1048576,COUNTA(H$19:H$1048576))/INDEX(H$19:H$1048576,COUNTA(H$19:H$1048576)-12)-1} | I4: {=INDEX(I$19:I$1048576,COUNTA(I$19:I$1048576))/INDEX(I$19:I$1048576,COUNTA(I$19:I$1048576)-12)-1} | J4: {=INDEX(J$19:J$1048576,COUNTA(J$19:J$1048576))/INDEX(J$19:J$1048576,COUNTA(J$19:J$1048576)-12)-1} | K4: {=INDEX(K$19:K$1048576,COUNTA(K$19:K$1048576))/INDEX(K$19:K$1048576,COUNTA(K$19:K$1048576)-12)-1} | ... Y4: {=INDEX(Y$19:Y$1048576,COUNTA(Y$19:Y$1048576))/INDEX(Y$19:Y$1048576,COUNTA(Y$19:Y$1048576)-12)-1}
B5: pre-pandemic trend (Dec-Feb) | C5: {=INDEX(C$19:C$1048576,COUNTA(C$19:C$1048576))-C$243} | D5: {=INDEX(D$19:D$1048576,COUNTA(D$19:D$1048576))/D$243-1} | E5: {=INDEX(E$19:E$1048576,COUNTA(E$19:E$1048576))/E$243-1} | F5: {=INDEX(F$19:F$1048576,COUNTA(F$19:F$1048576))/F$243-1} | G5: {=INDEX(G$19:G$1048576,COUNTA(G$19:G$1048576))/G$243-1} | H5: {=INDEX(H$19:H$1048576,COUNTA(H$19:H$1048576))/H$243-1} | I5: {=INDEX(I$19:I$1048576,COUNTA(I$19:I$1048576))/I$243-1} | J5: {=INDEX(J$19:J$1048576,COUNTA(J$19:J$1048576))/J$243-1} | K5: {=INDEX(K$19:K$1048576,COUNTA(K$19:K$1048576))/K$243-1} | ... Y5: {=INDEX(Y$19:Y$1048576,COUNTA(Y$19:Y$1048576))/Y$243-1}
B6: Since 2010 election | C6: {=INDEX(C$19:C$1048576,COUNTA(C$19:C$1048576))-C$125} | D6: {=INDEX(D$19:D$1048576,COUNTA(D$19:D$1048576))/D$125-1} | E6: {=INDEX(E$19:E$1048576,COUNTA(E$19:E$1048576))/E$125-1} | F6: {=INDEX(F$19:F$1048576,COUNTA(F$19:F$1048576))/F$125-1} | G6: {=INDEX(G$19:G$1048576,COUNTA(G$19:G$1048576))/G$125-1} | H6: {=INDEX(H$19:H$1048576,COUNTA(H$19:H$1048576))/H$125-1} | I6: {=INDEX(I$19:I$1048576,COUNTA(I$19:I$1048576))/I$125-1} | J6: {=INDEX(J$19:J$1048576,COUNTA(J$19:J$1048576))/J$125-1} | K6: {=INDEX(K$19:K$1048576,COUNTA(K$19:K$1048576))/K$125-1} | ... Y6: {=INDEX(Y$19:Y$1048576,COUNTA(Y$19:Y$1048576))/Y$125-1}
A8: Table 21: Vacancies 1 by industry (seasonally adjusted)
A9: Date of publication: | C9: 45881 | I9: Date of next publication: | J9: 45916

Sheet 1 UK
A1: Worksheet 1: CLA01: Claimant Count, United Kingdom (not designated as an Accredited Official Statistic) [note 1, 2, 5]
A2: This worksheet contains one table. Some cells may refer to notes which can be found on the notes worksheet tab.
A3: Some shorthand may have been used in the spreadsheet, [w] - none recorded in survey, [c] - confidential, [z] - not applicable, [p] - provisional, [r] - revised
A4: Source: Claimant Count, Office for National Statistics
A5: Time period and dataset code row | B5: People: level seasonally adjusted (thousands) | C5: People: rate seasonally adjusted (%) [note 2] | D5: People: level not seasonally adjusted (thousands) | E5: People: rate not seasonally adjusted (%) [note 2] | F5: Men: level seasonally adjusted (thousands) | G5: Men: rate seasonally adjusted (%) [note 2] | H5: Men: level not seasonally adjusted (thousands) | I5: Men: rate not seasonally adjusted (%) [note 2] | J5: Women: level seasonally adjusted (thousands) | K5: Women: rate seasonally adjusted (%) [note 2] | L5: Women: level not seasonally adjusted (thousands) | M5: Women: rate not seasonally adjusted (%) [note 2] | N5: Notes
A6: Dataset identifier code | B6: BCJD | C6: BCJE | D6: BCJA | E6: BCJB | F6: DPAE | G6: DPAH | H6: DPAA | I6: DPAC | J6: DPAF | K6: DPAI | L6: DPAB | M6: DPAD
A7: January 1971 | B7: 533.6 | C7: 2 | D7: 682.8 | E7: 2.6 | F7: 462.2 | G7: 2.7 | H7: 591.5 | I7: 3.4 | J7: 71.4 | K7: 0.8 | L7: 91.3 | M7: 1 | N7: 5 week month
A8: February 1971 | B8: 552.3 | C8: 2.1 | D8: 690.9 | E8: 2.6 | F8: 477.1 | G8: 2.8 | H8: 596.5 | I8: 3.5 | J8: 75.2 | K8: 0.8 | L8: 94.4 | M8: 1
A9: March 1971 | B9: 573.5 | C9: 2.2 | D9: 705.3 | E9: 2.6 | F9: 494.2 | G9: 2.9 | H9: 607.4 | I9: 3.5 | J9: 79.3 | K9: 0.8 | L9: 97.9 | M9: 1
A10: April 1971 | B10: 599.1 | C10: 2.2 | D10: 714.7 | E10: 2.7 | F10: 519.3 | G10: 3 | H10: 618.9 | I10: 3.6 | J10: 79.8 | K10: 0.8 | L10: 95.8 | M10: 1
A11: May 1971 | B11: 641.7 | C11: 2.4 | D11: 720 | E11: 2.7 | F11: 554.9 | G11: 3.2 | H11: 623.8 | I11: 3.6 | J11: 86.8 | K11: 0.9 | L11: 96.2 | M11: 1 | N11: 5 week month
A12: June 1971 | B12: 655.2 | C12: 2.5 | D12: 696 | E12: 2.6 | F12: 567.1 | G12: 3.3 | H12: 606.4 | I12: 3.5 | J12: 88.1 | K12: 0.9 | L12: 89.6 | M12: 0.9
A13: July 1971 | B13: 662.9 | C13: 2.5 | D13: 711.7 | E13: 2.7 | F13: 574.8 | G13: 3.3 | H13: 618.9 | I13: 3.6 | J13: 88.1 | K13: 0.9 | L13: 92.7 | M13: 1
A14: August 1971 | B14: 664.1 | C14: 2.5 | D14: 759 | E14: 2.8 | F14: 578.3 | G14: 3.4 | H14: 653.8 | I14: 3.8 | J14: 85.8 | K14: 0.9 | L14: 105.2 | M14: 1.1 | N14: 5 week month
A15: September 1971 | B15: 684 | C15: 2.6 | D15: 783.6 | E15: 2.9 | F15: 591.6 | G15: 3.4 | H15: 670.7 | I15: 3.9 | J15: 92.4 | K15: 1 | L15: 112.9 | M15: 1.2
A16: October 1971 | B16: 715.8 | C16: 2.7 | D16: 815.6 | E16: 3.1 | F16: 616.9 | G16: 3.6 | H16: 694.9 | I16: 4 | J16: 98.9 | K16: 1 | L16: 120.7 | M16: 1.3 | N16: 5 week month
A17: November 1971 | B17: 747.6 | C17: 2.8 | D17: 857.4 | E17: 3.2 | F17: 644.3 | G17: 3.7 | H17: 730.7 | I17: 4.2 | J17: 103.3 | K17: 1.1 | L17: 126.7 | M17: 1.3
A18: December 1971 | B18: 757.7 | C18: 2.8 | D18: 878.5 | E18: 3.3 | F18: 652.2 | G18: 3.8 | H18: 752.8 | I18: 4.4 | J18: 105.5 | K18: 1.1 | L18: 125.8 | M18: 1.3
A19: January 1972 | B19: 754.1 | C19: 2.8 | D19: 936.1 | E19: 3.5 | F19: 651 | G19: 3.8 | H19: 802.5 | I19: 4.7 | J19: 103.1 | K19: 1.1 | L19: 133.6 | M19: 1.4 | N19: 5 week month
A20: February 1972 | B20: 768.5 | C20: 2.9 | D20: 936.6 | E20: 3.5 | F20: 663.3 | G20: 3.9 | H20: 802.8 | I20: 4.7 | J20: 105.2 | K20: 1.1 | L20: 133.8 | M20: 1.4
A21: March 1972 | B21: 779.6 | C21: 2.9 | D21: 938 | E21: 3.5 | F21: 671.3 | G21: 3.9 | H21: 802.5 | I21: 4.7 | J21: 108.3 | K21: 1.1 | L21: 135.5 | M21: 1.4
A22: April 1972 | B22: 775.9 | C22: 2.9 | D22: 918.4 | E22: 3.4 | F22: 666.2 | G22: 3.9 | H22: 784.1 | I22: 4.6 | J22: 109.7 | K22: 1.1 | L22: 134.3 | M22: 1.4 | N22: 5 week month
A23: May 1972 | B23: 745.8 | C23: 2.8 | D23: 840.9 | E23: 3.1 | F23: 637.8 | G23: 3.7 | H23: 718.3 | I23: 4.2 | J23: 108 | K23: 1.1 | L23: 122.6 | M23: 1.3
A24: June 1972 | B24: 722.4 | C24: 2.7 | D24: 777.6 | E24: 2.9 | F24: 617 | G24: 3.6 | H24: 666.3 | I24: 3.9 | J24: 105.4 | K24: 1.1 | L24: 111.4 | M24: 1.2
A25: July 1972 | B25: 709.8 | C25: 2.7 | D25: 776.2 | E25: 2.9 | F25: 607 | G25: 3.5 | H25: 662.3 | I25: 3.9 | J25: 102.8 | K25: 1.1 | L25: 113.9 | M25: 1.2 | N25: 5 week month
A26: August 1972 | B26: 692.7 | C26: 2.6 | D26: 808.5 | E26: 3 | F26: 593.6 | G26: 3.5 | H26: 681.8 | I26: 4 | J26: 99.1 | K26: 1 | L26: 126.7 | M26: 1.3
A27: September 1972 | B27: 696.7 | C27: 2.6 | D27: 809.5 | E27: 3 | F27: 596.8 | G27: 3.5 | H27: 683.9 | I27: 4 | J27: 99.9 | K27: 1 | L27: 125.6 | M27: 1.3 | N27: 5 week month
A28: October 1972 | B28: 680.7 | C28: 2.5 | D28: 783.5 | E28: 2.9 | F28: 580.2 | G28: 3.4 | H28: 659.7 | I28: 3.9 | J28: 100.5 | K28: 1 | L28: 123.7 | M28: 1.3
A29: November 1972 | B29: 666.2 | C29: 2.5 | D29: 771.4 | E29: 2.9 | F29: 565.6 | G29: 3.3 | H29: 648.1 | I29: 3.8 | J29: 100.6 | K29: 1 | L29: 123.3 | M29: 1.3
A30: December 1972 | B30: 639.4 | C30: 2.4 | D30: 751.6 | E30: 2.8 | F30: 540.6 | G30: 3.2 | H30: 634.4 | I30: 3.7 | J30: 98.8 | K30: 1 | L30: 117.2 | M30: 1.2 | N30: 5 week month
A31: January 1973 | B31: 603.7 | C31: 2.2 | D31: 776.6 | E31: 2.9 | F31: 510.7 | G31: 3 | H31: 654.9 | I31: 3.8 | J31: 93 | K31: 0.9 | L31: 121.7 | M31: 1.2
A32: February 1973 | B32: 574.3 | C32: 2.1 | D32: 725.4 | E32: 2.7 | F32: 484.7 | G32: 2.8 | H32: 611.9 | I32: 3.6 | J32: 89.6 | K32: 0.9 | L32: 113.5 | M32: 1.1
A33: March 1973 | B33: 560.3 | C33: 2.1 | D33: 693 | E33: 2.6 | F33: 471.7 | G33: 2.8 | H33: 585.2 | I33: 3.4 | J33: 88.6 | K33: 0.9 | L33: 107.8 | M33: 1.1
A34: April 1973 | B34: 547.2 | C34: 2 | D34: 656.8 | E34: 2.4 | F34: 459.1 | G34: 2.7 | H34: 554.5 | I34: 3.2 | J34: 88.1 | K34: 0.9 | L34: 102.3 | M34: 1 | N34: 5 week month
A35: May 1973 | B35: 537.6 | C35: 2 | D35: 601.8 | E35: 2.2 | F35: 452.3 | G35: 2.6 | H35: 512.2 | I35: 3 | J35: 85.3 | K35: 0.9 | L35: 89.7 | M35: 0.9
A36: June 1973 | B36: 530.2 | C36: 2 | D36: 556.8 | E36: 2.1 | F36: 445.5 | G36: 2.6 | H36: 476.1 | I36: 2.8 | J36: 84.7 | K36: 0.9 | L36: 80.7 | M36: 0.8 | N36: 5 week month
A37: July 1973 | B37: 506.3 | C37: 1.9 | D37: 541.5 | E37: 2 | F37: 426.5 | G37: 2.5 | H37: 461.1 | I37: 2.7 | J37: 79.8 | K37: 0.8 | L37: 80.5 | M37: 0.8
A38: August 1973 | B38: 486.8 | C38: 1.8 | D38: 552.9 | E38: 2 | F38: 412 | G38: 2.4 | H38: 467.5 | I38: 2.7 | J38: 74.8 | K38: 0.8 | L38: 85.4 | M38: 0.9
A39: September 1973 | B39: 469.4 | C39: 1.7 | D39: 530.9 | E39: 2 | F39: 397.4 | G39: 2.3 | H39: 449.7 | I39: 2.6 | J39: 72 | K39: 0.7 | L39: 81.2 | M39: 0.8 | N39: 5 week month
A40: October 1973 | B40: 456.5 | C40: 1.7 | D40: 513.1 | E40: 1.9 | F40: 387.2 | G40: 2.3 | H40: 435.6 | I40: 2.5 | J40: 69.3 | K40: 0.7 | L40: 77.5 | M40: 0.8
A41: November 1973 | B41: 441.2 | C41: 1.6 | D41: 503 | E41: 1.9 | F41: 375.3 | G41: 2.2 | H41: 428.4 | I41: 2.5 | J41: 65.9 | K41: 0.7 | L41: 74.6 | M41: 0.7
A42: December 1973 | B42: 422.6 | C42: 1.6 | D42: 495.5 | E42: 1.8 | F42: 358.4 | G42: 2.1 | H42: 425 | I42: 2.5 | J42: 64.2 | K42: 0.6 | L42: 70.5 | M42: 0.7 | N42: 5 week month
A43: January 1974 | B43: 468.7 | C43: 1.7 | D43: 611.5 | E43: 2.3 | F43: 399 | G43: 2.4 | H43: 521.7 | I43: 3.1 | J43: 69.7 | K43: 0.7 | L43: 89.9 | M43: 0.9
A44: February 1974 | B44: 486.6 | C44: 1.8 | D44: 612.5 | E44: 2.3 | F44: 414.6 | G44: 2.4 | H44: 523.6 | I44: 3.1 | J44: 72 | K44: 0.7 | L44: 88.9 | M44: 0.9 | N44: 5 week month
A45: March 1974 | B45: 494.8 | C45: 1.8 | D45: 601.5 | E45: 2.2 | F45: 422.1 | G45: 2.5 | H45: 517.1 | I45: 3 | J45: 72.7 | K45: 0.7 | L45: 84.4 | M45: 0.8
A46: April 1974 | B46: 497.4 | C46: 1.8 | D46: 588 | E46: 2.2 | F46: 420.8 | G46: 2.5 | H46: 502.6 | I46: 3 | J46: 76.6 | K46: 0.8 | L46: 85.4 | M46: 0.8
A47: May 1974 | B47: 494.3 | C47: 1.8 | D47: 545.8 | E47: 2 | F47: 418.7 | G47: 2.5 | H47: 469.9 | I47: 2.8 | J47: 75.6 | K47: 0.7 | L47: 75.9 | M47: 0.7
A48: June 1974 | B48: 508.9 | C48: 1.9 | D48: 527.5 | E48: 1.9 | F48: 429.5 | G48: 2.5 | H48: 455.6 | I48: 2.7 | J48: 79.4 | K48: 0.8 | L48: 71.9 | M48: 0.7 | N48: 5 week month
A49: July 1974 | B49: 510.8 | C49: 1.9 | D49: 552.1 | E49: 2 | F49: 434.5 | G49: 2.6 | H49: 472.3 | I49: 2.8 | J49: 76.3 | K49: 0.7 | L49: 79.8 | M49: 0.8
A50: August 1974 | B50: 530.2 | C50: 2 | D50: 626.8 | E50: 2.3 | F50: 451.1 | G50: 2.7 | H50: 524.7 | I50: 3.1 | J50: 79.1 | K50: 0.8 | L50: 102.1 | M50: 1
A51: September 1974 | B51: 534.3 | C51: 2 | D51: 621.7 | E51: 2.3 | F51: 453.9 | G51: 2.7 | H51: 520 | I51: 3.1 | J51: 80.4 | K51: 0.8 | L51: 101.6 | M51: 1 | N51: 5 week month
A52: October 1974 | B52: 539.7 | C52: 2 | D52: 615.4 | E52: 2.3 | F52: 461.7 | G52: 2.7 | H52: 520.2 | I52: 3.1 | J52: 78 | K52: 0.8 | L52: 95.3 | M52: 0.9
A53: November 1974 | B53: 544.9 | C53: 2 | D53: 629.8 | E53: 2.3 | F53: 465.7 | G53: 2.7 | H53: 531.3 | I53: 3.1 | J53: 79.2 | K53: 0.8 | L53: 98.4 | M53: 1 | N53: 5 week month
A54: December 1974 | B54: 558.5 | C54: 2.1 | D54: 661.1 | E54: 2.4 | F54: 476.3 | G54: 2.8 | H54: 559.1 | I54: 3.3 | J54: 82.2 | K54: 0.8 | L54: 101.9 | M54: 1
A55: January 1975 | B55: 587.8 | C55: 2.1 | D55: 771.8 | E55: 2.8 | F55: 499.8 | G55: 2.9 | H55: 635.1 | I55: 3.7 | J55: 88 | K55: 0.9 | L55: 136.7 | M55: 1.3
A56: February 1975 | B56: 609.1 | C56: 2.2 | D56: 791.8 | E56: 2.9 | F56: 515.1 | G56: 3 | H56: 650.2 | I56: 3.8 | J56: 94 | K56: 0.9 | L56: 141.6 | M56: 1.4 | N56: 5 week month
A57: March 1975 | B57: 641.7 | C57: 2.3 | D57: 802.6 | E57: 2.9 | F57: 539 | G57: 3.2 | H57: 657.7 | I57: 3.9 | J57: 102.7 | K57: 1 | L57: 144.9 | M57: 1.4
A58: April 1975 | B58: 683.4 | C58: 2.5 | D58: 845 | E58: 3.1 | F58: 573.5 | G58: 3.4 | H58: 690.2 | I58: 4 | J58: 109.9 | K58: 1.1 | L58: 154.9 | M58: 1.5
A59: May 1975 | B59: 734.4 | C59: 2.7 | D59: 850.3 | E59: 3.1 | F59: 612.2 | G59: 3.6 | H59: 693.9 | I59: 4.1 | J59: 122.2 | K59: 1.2 | L59: 156.4 | M59: 1.5
A60: June 1975 | B60: 774.2 | C60: 2.8 | D60: 866.1 | E60: 3.2 | F60: 644.5 | G60: 3.8 | H60: 706.6 | I60: 4.1 | J60: 129.7 | K60: 1.3 | L60: 159.4 | M60: 1.5 | N60: 5 week month
A61: July 1975 | B61: 818.7 | C61: 3 | D61: 990.1 | E61: 3.6 | F61: 681.3 | G61: 4 | H61: 784.5 | I61: 4.6 | J61: 137.4 | K61: 1.3 | L61: 205.6 | M61: 2
A62: August 1975 | B62: 845.8 | C62: 3.1 | D62: 1151 | E62: 4.2 | F62: 703.6 | G62: 4.1 | H62: 885.2 | I62: 5.2 | J62: 142.2 | K62: 1.4 | L62: 265.8 | M62: 2.6 | N62: 5 week month
A63: September 1975 | B63: 877 | C63: 3.2 | D63: 1145.5 | E63: 4.2 | F63: 727.2 | G63: 4.3 | H63: 883.3 | I63: 5.2 | J63: 149.8 | K63: 1.5 | L63: 262.2 | M63: 2.5
A64: October 1975 | B64: 934.4 | C64: 3.4 | D64: 1147.3 | E64: 4.2 | F64: 767.3 | G64: 4.5 | H64: 888.8 | I64: 5.2 | J64: 167.1 | K64: 1.6 | L64: 258.5 | M64: 2.5
A65: November 1975 | B65: 970.1 | C65: 3.5 | D65: 1168.9 | E65: 4.3 | F65: 794.7 | G65: 4.7 | H65: 909 | I65: 5.3 | J65: 175.4 | K65: 1.7 | L65: 259.9 | M65: 2.5 | N65: 5 week month
A66: December 1975 | B66: 997.1 | C66: 3.6 | D66: 1200.8 | E66: 4.4 | F66: 814.4 | G66: 4.8 | H66: 940.5 | I66: 5.5 | J66: 182.7 | K66: 1.8 | L66: 260.3 | M66: 2.5
A67: January 1976 | B67: 1022 | C67: 3.7 | D67: 1303.2 | E67: 4.7 | F67: 831.4 | G67: 4.9 | H67: 1017.4 | I67: 5.9 | J67: 190.6 | K67: 1.8 | L67: 285.8 | M67: 2.7
A68: February 1976 | B68: 1042.3 | C68: 3.8 | D68: 1304.4 | E68: 4.7 | F68: 843.3 | G68: 4.9 | H68: 1014.6 | I68: 5.9 | J68: 199 | K68: 1.9 | L68: 289.8 | M68: 2.8 | N68: 5 week month
A69: March 1976 | B69: 1055.6 | C69: 3.8 | D69: 1284.9 | E69: 4.7 | F69: 849.9 | G69: 5 | H69: 997.7 | I69: 5.8 | J69: 205.7 | K69: 2 | L69: 287.2 | M69: 2.8
A70: April 1976 | B70: 1070.1 | C70: 3.9 | D70: 1281.1 | E70: 4.6 | F70: 860.3 | G70: 5 | H70: 994.2 | I70: 5.8 | J70: 209.8 | K70: 2 | L70: 287 | M70: 2.8
A71: May 1976 | B71: 1088.2 | C71: 3.9 | D71: 1271.8 | E71: 4.6 | F71: 872.4 | G71: 5.1 | H71: 982.9 | I71: 5.7 | J71: 215.8 | K71: 2.1 | L71: 288.9 | M71: 2.8 | N71: 5 week month
A72: June 1976 | B72: 1085.5 | C72: 3.9 | D72: 1331.8 | E72: 4.8 | F72: 868.1 | G72: 5.1 | H72: 1009.4 | I72: 5.9 | J72: 217.4 | K72: 2.1 | L72: 322.4 | M72: 3.1
A73: July 1976 | B73: 1093 | C73: 4 | D73: 1463.5 | E73: 5.3 | F73: 869.6 | G73: 5.1 | H73: 1071.2 | I73: 6.3 | J73: 223.4 | K73: 2.1 | L73: 392.2 | M73: 3.8
A74: August 1976 | B74: 1107.6 | C74: 4 | D74: 1502 | E74: 5.5 | F74: 874.2 | G74: 5.1 | H74: 1092.2 | I74: 6.4 | J74: 233.4 | K74: 2.2 | L74: 408.8 | M74: 3.9 | N74: 5 week month
A75: September 1976 | B75: 1107 | C75: 4 | D75: 1455.7 | E75: 5.3 | F75: 871.5 | G75: 5.1 | H75: 1059.8 | I75: 6.2 | J75: 235.5 | K75: 2.3 | L75: 395.9 | M75: 3.8
A76: October 1976 | B76: 1097.8 | C76: 4 | D76: 1377.1 | E76: 5 | F76: 862.2 | G76: 5 | H76: 1010 | I76: 5.9 | J76: 235.6 | K76: 2.3 | L76: 367.1 | M76: 3.5 | N76: 5 week month
A77: November 1976 | B77: 1105.1 | C77: 4 | D77: 1366.5 | E77: 5 | F77: 864.7 | G77: 5 | H77: 1011.6 | I77: 5.9 | J77: 240.4 | K77: 2.3 | L77: 354.9 | M77: 3.4
A78: December 1976 | B78: 1108.8 | C78: 4 | D78: 1371 | E78: 5 | F78: 865.4 | G78: 5.1 | H78: 1019.5 | I78: 5.9 | J78: 243.4 | K78: 2.3 | L78: 351.5 | M78: 3.4
A79: January 1977 | B79: 1111.1 | C79: 4 | D79: 1448.2 | E79: 5.2 | F79: 863.6 | G79: 5.1 | H79: 1074.1 | I79: 6.3 | J79: 247.5 | K79: 2.3 | L79: 374.1 | M79: 3.5 | N79: 5 week month
A80: February 1977 | B80: 1107.4 | C80: 4 | D80: 1421.8 | E80: 5.1 | F80: 859.7 | G80: 5 | H80: 1055.5 | I80: 6.2 | J80: 247.7 | K80: 2.3 | L80: 366.3 | M80: 3.5
A81: March 1977 | B81: 1107.9 | C81: 4 | D81: 1383.5 | E81: 5 | F81: 858.9 | G81: 5 | H81: 1028.5 | I81: 6 | J81: 249 | K81: 2.4 | L81: 355 | M81: 3.4
A82: April 1977 | B82: 1117.6 | C82: 4 | D82: 1392.3 | E82: 5 | F82: 865.7 | G82: 5.1 | H82: 1032.4 | I82: 6 | J82: 251.9 | K82: 2.4 | L82: 359.9 | M82: 3.4 | N82: 5 week month
A83: May 1977 | B83: 1119.7 | C83: 4 | D83: 1341.7 | E83: 4.8 | F83: 866 | G83: 5.1 | H83: 994.3 | I83: 5.8 | J83: 253.7 | K83: 2.4 | L83: 347.4 | M83: 3.3
A84: June 1977 | B84: 1149.3 | C84: 4.2 | D84: 1450.1 | E84: 5.2 | F84: 886.7 | G84: 5.2 | H84: 1050.8 | I84: 6.2 | J84: 262.6 | K84: 2.5 | L84: 399.3 | M84: 3.8
A85: July 1977 | B85: 1169.8 | C85: 4.2 | D85: 1622.4 | E85: 5.9 | F85: 896 | G85: 5.2 | H85: 1132.7 | I85: 6.6 | J85: 273.8 | K85: 2.6 | L85: 489.6 | M85: 4.6 | N85: 5 week month
A86: August 1977 | B86: 1172.7 | C86: 4.2 | D86: 1635.8 | E86: 5.9 | F86: 898.3 | G86: 5.3 | H86: 1143.5 | I86: 6.7 | J86: 274.4 | K86: 2.6 | L86: 492.3 | M86: 4.7
A87: September 1977 | B87: 1193.6 | C87: 4.3 | D87: 1609.1 | E87: 5.8 | F87: 910.3 | G87: 5.3 | H87: 1124.3 | I87: 6.6 | J87: 283.3 | K87: 2.7 | L87: 484.8 | M87: 4.6
A88: October 1977 | B88: 1188.1 | C88: 4.3 | D88: 1518.3 | E88: 5.5 | F88: 905.1 | G88: 5.3 | H88: 1070.8 | I88: 6.3 | J88: 283 | K88: 2.7 | L88: 447.6 | M88: 4.2 | N88: 5 week month
A89: November 1977 | B89: 1186.1 | C89: 4.3 | D89: 1499.1 | E89: 5.4 | F89: 900.4 | G89: 5.3 | H89: 1063.2 | I89: 6.2 | J89: 285.7 | K89: 2.7 | L89: 435.9 | M89: 4.1
A90: December 1977 | B90: 1181.5 | C90: 4.3 | D90: 1480.8 | E90: 5.4 | F90: 894.9 | G90: 5.2 | H90: 1060.7 | I90: 6.2 | J90: 286.6 | K90: 2.7 | L90: 420.1 | M90: 4
A91: January 1978 | B91: 1167.5 | C91: 4.2 | D91: 1548.5 | E91: 5.6 | F91: 885.3 | G91: 5.2 | H91: 1114.8 | I91: 6.6 | J91: 282.2 | K91: 2.6 | L91: 433.7 | M91: 4 | N91: 5 week month
A92: February 1978 | B92: 1150.9 | C92: 4.1 | D92: 1508.7 | E92: 5.4 | F92: 871.1 | G92: 5.1 | H92: 1089.6 | I92: 6.4 | J92: 279.8 | K92: 2.6 | L92: 419.1 | M92: 3.9
A93: March 1978 | B93: 1148.1 | C93: 4.1 | D93: 1461 | E93: 5.3 | F93: 868 | G93: 5.1 | H93: 1058.4 | I93: 6.2 | J93: 280.1 | K93: 2.6 | L93: 402.6 | M93: 3.7
A94: April 1978 | B94: 1147.3 | C94: 4.1 | D94: 1451.8 | E94: 5.2 | F94: 862.3 | G94: 5.1 | H94: 1045.4 | I94: 6.2 | J94: 285 | K94: 2.6 | L94: 406.4 | M94: 3.8 | N94: 5 week month
A95: May 1978 | B95: 1140.6 | C95: 4.1 | D95: 1386.8 | E95: 5 | F95: 856.5 | G95: 5 | H95: 1001.1 | I95: 5.9 | J95: 284.1 | K95: 2.6 | L95: 385.7 | M95: 3.6
A96: June 1978 | B96: 1140.3 | C96: 4.1 | D96: 1446.1 | E96: 5.2 | F96: 852.5 | G96: 5 | H96: 1022.9 | I96: 6 | J96: 287.8 | K96: 2.7 | L96: 423.1 | M96: 3.9
A97: July 1978 | B97: 1134.6 | C97: 4.1 | D97: 1585.8 | E97: 5.7 | F97: 846.6 | G97: 5 | H97: 1087.3 | I97: 6.4 | J97: 288 | K97: 2.7 | L97: 498.5 | M97: 4.6 | N97: 5 week month
A98: August 1978 | B98: 1144.6 | C98: 4.1 | D98: 1499.6 | E98: 5.4 | F98: 849.2 | G98: 5 | H98: 1059.6 | I98: 6.2 | J98: 295.4 | K98: 2.7 | L98: 440 | M98: 4.1
A99: September 1978 | B99: 1130.2 | C99: 4.1 | D99: 1418.4 | E99: 5.1 | F99: 838.7 | G99: 4.9 | H99: 1007.2 | I99: 5.9 | J99: 291.5 | K99: 2.7 | L99: 411.2 | M99: 3.8 | N99: 5 week month
A100: October 1978 | B100: 1115.4 | C100: 4 | D100: 1335.8 | E100: 4.8 | F100: 825.6 | G100: 4.9 | H100: 958.7 | I100: 5.6 | J100: 289.8 | K100: 2.7 | L100: 377.1 | M100: 3.5
...

Sheet AWE Real_CPI
B1: Total Pay Real AWE (2015 £) | C1: Total Pay Real AWE (%) | D1: Regular Pay Real AWE (2015 £) | E1: Regular Pay Real AWE (%)
A2: Current (3mo avg) | B2: =AVERAGE(OFFSET(INDEX(B$17:B$1048576,COUNTA(B$17:B$1048576)),-2,0,3,1)) | D2: =AVERAGE(OFFSET(INDEX(F$17:F$1048576,COUNTA(F$17:F$1048576)),-2,0,3,1))
A3: Change on quarter (3mo avg) | B3: =(AVERAGE(OFFSET(INDEX(B$17:B$1048576,COUNTA(B$17:B$1048576)),-2,0,3,1))-AVERAGE(OFFSET(INDEX(B$17:B$1048576,COUNTA(B$17:B$1048576)),-5,0,3,1)))*52 | D3: =(AVERAGE(OFFSET(INDEX(F$17:F$1048576,COUNTA(F$17:F$1048576)),-2,0,3,1))-AVERAGE(OFFSET(INDEX(F$17:F$1048576,COUNTA(F$17:F$1048576)),-5,0,3,1)))*52
A4: Change year on year (3mo avg) | B4: =(AVERAGE(OFFSET(INDEX(B$17:B$1048576,COUNTA(B$17:B$1048576)),-2,0,3,1))-AVERAGE(OFFSET(INDEX(B$17:B$1048576,COUNTA(B$17:B$1048576)),-14,0,3,1)))*52 | C4: {=INDEX(E$31:E$1048576,COUNTA(E$31:E$1048576))} | D4: =(AVERAGE(OFFSET(INDEX(F$17:F$1048576,COUNTA(F$17:F$1048576)),-2,0,3,1))-AVERAGE(OFFSET(INDEX(F$17:F$1048576,COUNTA(F$17:F$1048576)),-14,0,3,1)))*52 | E4: {=INDEX(I$31:I$1048576,COUNTA(I$31:I$1048576))}
A5: Change since Covid-19 (2019 average) | B5: =(AVERAGE(OFFSET(INDEX($B$17:$B$1048576,COUNTA($B$17:$B$1048576)),-2,0,3,1))-AVERAGE($B$256:$B$258))*52 | C5: =(AVERAGE(OFFSET(INDEX($B$17:$B$1048576,COUNTA($B$17:$B$1048576)),-2,0,3,1))/AVERAGE($B$256:$B$258))-1 | D5: =(AVERAGE(OFFSET(INDEX(F$17:F$1048576,COUNTA(F$17:F$1048576)),-2,0,3,1))-AVERAGE($F$256:$F$258))*52 | E5: =(AVERAGE(OFFSET(INDEX(F$17:F$1048576,COUNTA(F$17:F$1048576)),-2,0,3,1))/AVERAGE($F$256:$F$258))-1
A6: Change since 2010 | B6: =(AVERAGE(OFFSET(INDEX($B$17:$B$1048576,COUNTA($B$17:$B$1048576)),-2,0,3,1))-AVERAGE($B$138:$B$140))*52 | C6: =(AVERAGE(OFFSET(INDEX($B$17:$B$1048576,COUNTA($B$17:$B$1048576)),-2,0,3,1))/AVERAGE($B$138:$B$140))-1 | D6: =(AVERAGE(OFFSET(INDEX(F$17:F$1048576,COUNTA(F$17:F$1048576)),-2,0,3,1))-AVERAGE($F$138:$F$140))*52 | E6: =(AVERAGE(OFFSET(INDEX(F$17:F$1048576,COUNTA(F$17:F$1048576)),-2,0,3,1))/AVERAGE($F$138:$F$140))-1
A7: Change since financial crisis | B7: =(AVERAGE(OFFSET(INDEX($B$17:$B$1048576,COUNTA($B$17:$B$1048576)),-2,0,3,1))-AVERAGE($B$110:$B$112))*52 | C7: =(AVERAGE(OFFSET(INDEX($B$17:$B$1048576,COUNTA($B$17:$B$1048576)),-2,0,3,1))/AVERAGE($B$110:$B$112))-1 | D7: =(AVERAGE(OFFSET(INDEX(F$17:F$1048576,COUNTA(F$17:F$1048576)),-2,0,3,1))-AVERAGE($F$110:$F$112))*52 | E7: =(AVERAGE(OFFSET(INDEX(F$17:F$1048576,COUNTA(F$17:F$1048576)),-2,0,3,1))/AVERAGE($F$110:$F$112))-1
A9: Real Average Weekly Earnings using CPI (seasonally adjusted) | K9: Source: Monthly Wages and Salaries Survey
A10: Date of this publication: 12 August 2025 | G10: Date of next publication: 16 September 2025
A11: Inquiries: Email: | C11: earnings@ons.gov.uk | G11: Tel: 01633 456120
B13: Total pay, seasonally adjusted | F13: Regular Pay, seasonally adjusted
B14: Real AWE (2015 £) | C14: Real AWE (Index numbers 2015=100) | D14: % changes year on year | F14: Real AWE (2015 £) | G14: Real AWE (Index numbers 2015=100) | H14: % changes year on year
D15: Single month | E15: 3 month average | H15: Single month | I15: 3 month average

Sheet Redundancies >>>

Sheet 1a
B1: North East | C1: North West | D1: Yorkshire and The Humber | E1: East Midlands | F1: West Midlands | G1: East of England | H1: London | I1: South East | J1: South West | K1: Wales | L1: Scotland | M1: GB
A2: Current | B2: =AVERAGE(OFFSET(INDEX(B$13:B$1048576,COUNTA(B$13:B$1048576)),-2,0,3,1)) | C2: =AVERAGE(OFFSET(INDEX(C$13:C$1048576,COUNTA(C$13:C$1048576)),-2,0,3,1)) | D2: =AVERAGE(OFFSET(INDEX(D$13:D$1048576,COUNTA(D$13:D$1048576)),-2,0,3,1)) | E2: =AVERAGE(OFFSET(INDEX(E$13:E$1048576,COUNTA(E$13:E$1048576)),-2,0,3,1)) | F2: =AVERAGE(OFFSET(INDEX(F$13:F$1048576,COUNTA(F$13:F$1048576)),-2,0,3,1)) | G2: =AVERAGE(OFFSET(INDEX(G$13:G$1048576,COUNTA(G$13:G$1048576)),-2,0,3,1)) | H2: =AVERAGE(OFFSET(INDEX(H$13:H$1048576,COUNTA(H$13:H$1048576)),-2,0,3,1)) | I2: =AVERAGE(OFFSET(INDEX(I$13:I$1048576,COUNTA(I$13:I$1048576)),-2,0,3,1)) | ... M2: =AVERAGE(OFFSET(INDEX(M$13:M$1048576,COUNTA(M$13:M$1048576)),-2,0,3,1))
A3: Average since start of 2023 | B3: =AVERAGE(INDEX(B$13:B$1048576,MATCH(44927,$A$13:$A$1048576,0)): INDEX(B$13:B$1048576,COUNTA(B$13:B$1048576))) | C3: =AVERAGE(INDEX(C$13:C$1048576,MATCH(44927,$A$13:$A$1048576,0)): INDEX(C$13:C$1048576,COUNTA(C$13:C$1048576))) | D3: =AVERAGE(INDEX(D$13:D$1048576,MATCH(44927,$A$13:$A$1048576,0)): INDEX(D$13:D$1048576,COUNTA(D$13:D$1048576))) | E3: =AVERAGE(INDEX(E$13:E$1048576,MATCH(44927,$A$13:$A$1048576,0)): INDEX(E$13:E$1048576,COUNTA(E$13:E$1048576))) | F3: =AVERAGE(INDEX(F$13:F$1048576,MATCH(44927,$A$13:$A$1048576,0)): INDEX(F$13:F$1048576,COUNTA(F$13:F$1048576))) | G3: =AVERAGE(INDEX(G$13:G$1048576,MATCH(44927,$A$13:$A$1048576,0)): INDEX(G$13:G$1048576,COUNTA(G$13:G$1048576))) | H3: =AVERAGE(INDEX(H$13:H$1048576,MATCH(44927,$A$13:$A$1048576,0)): INDEX(H$13:H$1048576,COUNTA(H$13:H$1048576))) | I3: =AVERAGE(INDEX(I$13:I$1048576,MATCH(44927,$A$13:$A$1048576,0)): INDEX(I$13:I$1048576,COUNTA(I$13:I$1048576))) | ... M3: =AVERAGE(INDEX(M$13:M$1048576,MATCH(44927,$A$13:$A$1048576,0)): INDEX(M$13:M$1048576,COUNTA(M$13:M$1048576)))
A4: Average pre-covid (April 2019-February 2020) | B4: =AVERAGE(B$13:B$23) | C4: =AVERAGE(C$13:C$23) | D4: =AVERAGE(D$13:D$23) | E4: =AVERAGE(E$13:E$23) | F4: =AVERAGE(F$13:F$23) | G4: =AVERAGE(G$13:G$23) | H4: =AVERAGE(H$13:H$23) | I4: =AVERAGE(I$13:I$23) | ... M4: =AVERAGE(M$13:M$23)
A5: Change on month | B5: =(AVERAGE(OFFSET(INDEX(B$13:B$1048576,COUNTA(B$13:B$1048576)),-2,0,3,1))/AVERAGE(OFFSET(INDEX(B$13:B$1048576,COUNTA(B$13:B$1048576)),-3,0,3,1)))-1 | C5: =(AVERAGE(OFFSET(INDEX(C$13:C$1048576,COUNTA(C$13:C$1048576)),-2,0,3,1))/AVERAGE(OFFSET(INDEX(C$13:C$1048576,COUNTA(C$13:C$1048576)),-3,0,3,1)))-1 | D5: =(AVERAGE(OFFSET(INDEX(D$13:D$1048576,COUNTA(D$13:D$1048576)),-2,0,3,1))/AVERAGE(OFFSET(INDEX(D$13:D$1048576,COUNTA(D$13:D$1048576)),-3,0,3,1)))-1 | E5: =(AVERAGE(OFFSET(INDEX(E$13:E$1048576,COUNTA(E$13:E$1048576)),-2,0,3,1))/AVERAGE(OFFSET(INDEX(E$13:E$1048576,COUNTA(E$13:E$1048576)),-3,0,3,1)))-1 | F5: =(AVERAGE(OFFSET(INDEX(F$13:F$1048576,COUNTA(F$13:F$1048576)),-2,0,3,1))/AVERAGE(OFFSET(INDEX(F$13:F$1048576,COUNTA(F$13:F$1048576)),-3,0,3,1)))-1 | G5: =(AVERAGE(OFFSET(INDEX(G$13:G$1048576,COUNTA(G$13:G$1048576)),-2,0,3,1))/AVERAGE(OFFSET(INDEX(G$13:G$1048576,COUNTA(G$13:G$1048576)),-3,0,3,1)))-1 | H5: =(AVERAGE(OFFSET(INDEX(H$13:H$1048576,COUNTA(H$13:H$1048576)),-2,0,3,1))/AVERAGE(OFFSET(INDEX(H$13:H$1048576,COUNTA(H$13:H$1048576)),-3,0,3,1)))-1 | I5: =(AVERAGE(OFFSET(INDEX(I$13:I$1048576,COUNTA(I$13:I$1048576)),-2,0,3,1))/AVERAGE(OFFSET(INDEX(I$13:I$1048576,COUNTA(I$13:I$1048576)),-3,0,3,1)))-1 | ... M5: =(AVERAGE(OFFSET(INDEX(M$13:M$1048576,COUNTA(M$13:M$1048576)),-2,0,3,1))/AVERAGE(OFFSET(INDEX(M$13:M$1048576,COUNTA(M$13:M$1048576)),-3,0,3,1)))-1
A6: Change on quarter | B6: =(AVERAGE(OFFSET(INDEX(B$13:B$1048576,COUNTA(B$13:B$1048576)),-2,0,3,1))/AVERAGE(OFFSET(INDEX(B$13:B$1048576,COUNTA(B$13:B$1048576)),-5,0,3,1)))-1 | C6: =(AVERAGE(OFFSET(INDEX(C$13:C$1048576,COUNTA(C$13:C$1048576)),-2,0,3,1))/AVERAGE(OFFSET(INDEX(C$13:C$1048576,COUNTA(C$13:C$1048576)),-5,0,3,1)))-1 | D6: =(AVERAGE(OFFSET(INDEX(D$13:D$1048576,COUNTA(D$13:D$1048576)),-2,0,3,1))/AVERAGE(OFFSET(INDEX(D$13:D$1048576,COUNTA(D$13:D$1048576)),-5,0,3,1)))-1 | E6: =(AVERAGE(OFFSET(INDEX(E$13:E$1048576,COUNTA(E$13:E$1048576)),-2,0,3,1))/AVERAGE(OFFSET(INDEX(E$13:E$1048576,COUNTA(E$13:E$1048576)),-5,0,3,1)))-1 | F6: =(AVERAGE(OFFSET(INDEX(F$13:F$1048576,COUNTA(F$13:F$1048576)),-2,0,3,1))/AVERAGE(OFFSET(INDEX(F$13:F$1048576,COUNTA(F$13:F$1048576)),-5,0,3,1)))-1 | G6: =(AVERAGE(OFFSET(INDEX(G$13:G$1048576,COUNTA(G$13:G$1048576)),-2,0,3,1))/AVERAGE(OFFSET(INDEX(G$13:G$1048576,COUNTA(G$13:G$1048576)),-5,0,3,1)))-1 | H6: =(AVERAGE(OFFSET(INDEX(H$13:H$1048576,COUNTA(H$13:H$1048576)),-2,0,3,1))/AVERAGE(OFFSET(INDEX(H$13:H$1048576,COUNTA(H$13:H$1048576)),-5,0,3,1)))-1 | I6: =(AVERAGE(OFFSET(INDEX(I$13:I$1048576,COUNTA(I$13:I$1048576)),-2,0,3,1))/AVERAGE(OFFSET(INDEX(I$13:I$1048576,COUNTA(I$13:I$1048576)),-5,0,3,1)))-1 | ... M6: =(AVERAGE(OFFSET(INDEX(M$13:M$1048576,COUNTA(M$13:M$1048576)),-2,0,3,1))/AVERAGE(OFFSET(INDEX(M$13:M$1048576,COUNTA(M$13:M$1048576)),-5,0,3,1)))-1
A7: Change on year | B7: =(AVERAGE(OFFSET(INDEX(B$13:B$1048576,COUNTA(B$13:B$1048576)),-2,0,3,1))/AVERAGE(OFFSET(INDEX(B$13:B$1048576,COUNTA(B$13:B$1048576)),-14,0,3,1)))-1 | C7: =(AVERAGE(OFFSET(INDEX(C$13:C$1048576,COUNTA(C$13:C$1048576)),-2,0,3,1))/AVERAGE(OFFSET(INDEX(C$13:C$1048576,COUNTA(C$13:C$1048576)),-14,0,3,1)))-1 | D7: =(AVERAGE(OFFSET(INDEX(D$13:D$1048576,COUNTA(D$13:D$1048576)),-2,0,3,1))/AVERAGE(OFFSET(INDEX(D$13:D$1048576,COUNTA(D$13:D$1048576)),-14,0,3,1)))-1 | E7: =(AVERAGE(OFFSET(INDEX(E$13:E$1048576,COUNTA(E$13:E$1048576)),-2,0,3,1))/AVERAGE(OFFSET(INDEX(E$13:E$1048576,COUNTA(E$13:E$1048576)),-14,0,3,1)))-1 | F7: =(AVERAGE(OFFSET(INDEX(F$13:F$1048576,COUNTA(F$13:F$1048576)),-2,0,3,1))/AVERAGE(OFFSET(INDEX(F$13:F$1048576,COUNTA(F$13:F$1048576)),-14,0,3,1)))-1 | G7: =(AVERAGE(OFFSET(INDEX(G$13:G$1048576,COUNTA(G$13:G$1048576)),-2,0,3,1))/AVERAGE(OFFSET(INDEX(G$13:G$1048576,COUNTA(G$13:G$1048576)),-14,0,3,1)))-1 | H7: =(AVERAGE(OFFSET(INDEX(H$13:H$1048576,COUNTA(H$13:H$1048576)),-2,0,3,1))/AVERAGE(OFFSET(INDEX(H$13:H$1048576,COUNTA(H$13:H$1048576)),-14,0,3,1)))-1 | I7: =(AVERAGE(OFFSET(INDEX(I$13:I$1048576,COUNTA(I$13:I$1048576)),-2,0,3,1))/AVERAGE(OFFSET(INDEX(I$13:I$1048576,COUNTA(I$13:I$1048576)),-14,0,3,1)))-1 | ... M7: =(AVERAGE(OFFSET(INDEX(M$13:M$1048576,COUNTA(M$13:M$1048576)),-2,0,3,1))/AVERAGE(OFFSET(INDEX(M$13:M$1048576,COUNTA(M$13:M$1048576)),-14,0,3,1)))-1
A9: Worksheet 1a: Number of potential redundancies from HR1 forms by region, GB [note 6]

Sheet 1b
A1: Worksheet 1b: Number of employers submitting HR1 forms by region, GB [note 6]
A2: This worksheet contains one table.
A3: Some shorthand is used in this table, [c] = confidential
A4: Month | B4: North East | C4: North West | D4: Yorkshire and The Humber | E4: East Midlands | F4: West Midlands | G4: East of England | H4: London | I4: South East | J4: South West | K4: Wales | L4: Scotland | M4: GB
A5: 43556 | B5: 8 | C5: 29 | D5: [c] | E5: 12 | F5: 14 | G5: 29 | H5: 52 | I5: 38 | J5: 24 | K5: [c] | L5: 22 | M5: 256
A6: 43586 | B6: 10 | C6: 34 | D6: 30 | E6: 12 | F6: 27 | G6: 29 | H6: 65 | I6: 47 | J6: 30 | K6: 10 | L6: 21 | M6: 315
A7: 43617 | B7: 15 | C7: 29 | D7: 40 | E7: 20 | F7: 30 | G7: 17 | H7: 57 | I7: 33 | J7: 18 | K7: 13 | L7: 13 | M7: 285
A8: 43647 | B8: 10 | C8: 28 | D8: 21 | E8: 16 | F8: 25 | G8: 19 | H8: 48 | I8: 30 | J8: 16 | K8: 13 | L8: 16 | M8: 242
A9: 43678 | B9: [c] | C9: 21 | D9: 15 | E9: 9 | F9: 24 | G9: [c] | H9: 40 | I9: 17 | J9: 14 | K9: 13 | L9: 16 | M9: 186

Sheet 2a
A1: Worksheet 2a: Number of potential redundancies from HR1 forms by combined industries, GB [note 6] [note 7]
A2: This worksheet contains one table.
A3: Some shorthand is used in this table, [c] = confidential
A4: Month | B4: Manufacturing | C4: Energy and Water | D4: Construction | E4: Transport and Communication | F4: Distribution, Hotels and Restaurants | G4: Banking and Finance | H4: Public Admin, Education and Health | I4: Other Services | J4: GB
A5: 43556 | B5: 2067 | C5: [c] | D5: 659 | E5: 1666 | F5: [c] | G5: 3517 | H5: 3100 | I5: 401 | J5: 82454
A6: 43586 | B6: 8362 | C6: 1177 | D6: 1107 | E6: 3570 | F6: 3998 | G6: 5877 | H6: 3286 | I6: 519 | J6: 27896
A7: 43617 | B7: 4594 | C7: 440 | D7: 903 | E7: 1642 | F7: 2322 | G7: 6505 | H7: 3629 | I7: 282 | J7: 20317
A8: 43647 | B8: 4441 | C8: 1011 | D8: 1330 | E8: 1827 | F8: 2045 | G8: 3807 | H8: 2374 | I8: 661 | J8: 17496
A9: 43678 | B9: 3151 | C9: 610 | D9: 591 | E9: 1282 | F9: 9468 | G9: 4015 | H9: 2400 | I9: 562 | J9: 22079
A10: 43709 | B10: 2894 | C10: 778 | D10: 1422 | E10: 4493 | F10: 2373 | G10: 7686 | H10: 4904 | I10: 418 | J10: 24968
A11: 43739 | B11: 4376 | C11: 995 | D11: 1433 | E11: 2260 | F11: 3949 | G11: 4254 | H11: 1882 | I11: 1795 | J11: 20944
A12: 43770 | B12: 3000 | C12: 150 | D12: 407 | E12: 2515 | F12: 4308 | G12: 5579 | H12: 1771 | I12: 516 | J12: 18246
A13: 43800 | B13: 2195 | C13: [c] | D13: 843 | E13: 915 | F13: 1762 | G13: 3721 | H13: 2079 | I13: [c] | J13: 16619
A14: 43831 | B14: 5611 | C14: 166 | D14: 1057 | E14: 1990 | F14: 7967 | G14: 4106 | H14: 4572 | I14: 1590 | J14: 27059
A15: 43862 | B15: 4256 | C15: [c] | D15: 1384 | E15: 2586 | F15: 8021 | G15: 5964 | H15: 2455 | I15: [c] | J15: 25140
A16: 43891 | B16: 4649 | C16: 369 | D16: 1711 | E16: 7707 | F16: 12436 | G16: 8504 | H16: 2661 | I16: 1250 | J16: 39287
A17: 43922 | B17: 3350 | C17: 2200 | D17: 2802 | E17: 16872 | F17: 20143 | G17: 7473 | H17: 1956 | I17: 1079 | J17: 55875
A18: 43952 | B18: 19792 | C18: 1739 | D18: 2290 | E18: 14801 | F18: 14523 | G18: 9962 | H18: 2702 | I18: 3481 | J18: 69290
A19: 43983 | B19: 23082 | C19: 4628 | D19: 4237 | E19: 33324 | F19: 40307 | G19: 26034 | H19: 5203 | I19: 8123 | J19: 144938
A20: 44013 | B20: 15452 | C20: 928 | D20: 2547 | E20: 11622 | F20: 38576 | G20: 22569 | H20: 5584 | I20: 11597 | J20: 108875
A21: 44044 | B21: 6569 | C21: 419 | D21: 1616 | E21: 5223 | F21: 13169 | G21: 12419 | H21: 3325 | I21: 7316 | J21: 50056
A22: 44075 | B22: 6560 | C22: 302 | D22: 762 | E22: 7626 | F22: 33858 | G22: 11565 | H22: 4370 | I22: 3147 | J22: 68190
A23: 44105 | B23: 5188 | C23: 857 | D23: 1407 | E23: 10573 | F23: 10636 | G23: 11319 | H23: 2907 | I23: 3215 | J23: 46102
A24: 44136 | B24: 6155 | C24: 371 | D24: 867 | E24: 3410 | F24: 12011 | G24: 5805 | H24: 3558 | I24: 751 | J24: 32928
A25: 44166 | B25: 1298 | C25: 295 | D25: 724 | E25: 2392 | F25: 10913 | G25: 2924 | H25: 1361 | I25: 380 | J25: 20287
A26: 44197 | B26: 2001 | C26: 4160 | D26: 375 | E26: 1866 | F26: 2741 | G26: 12593 | H26: 2647 | I26: 480 | J26: 26863
A27: 44228 | B27: 5459 | C27: 1196 | D27: 469 | E27: 3654 | F27: 5244 | G27: 4203 | H27: 1942 | I27: 517 | J27: 22684
... A30: 44317 | B30: 4265 | C30: 1749 | D30: 520 | E30: 739 | F30: 1712 | G30: 5072 | H30: 2882 | I30: 461 | J30: 17400
A31: 44348 | B31: 4083 | C31: [c] | D31: 462 | E31: 1122 | F31: 933 | G31: 1214 | H31: 4689 | I31: [c] | J31: 12922
A32: 44378 | B32: 1881 | C32: 189 | D32: 272 | E32: 3837 | F32: 1177 | G32: 2677 | H32: 2328 | I32: 101 | J32: 12462
A33: 44409 | B33: 1820 | C33: 489 | D33: 224 | E33: 800 | F33: 2365 | G33: 1788 | H33: 2641 | I33: 319 | J33: 10446
A34: 44440 | B34: 1458 | C34: 579 | D34: 392 | E34: 534 | F34: 2540 | G34: 2006 | H34: 3232 | I34: 260 | J34: 11001
A35: 44470 | B35: 2234 | C35: 583 | D35: 566 | E35: 2231 | F35: 1766 | G35: 2908 | H35: 1622 | I35: 261 | J35: 12171
A36: 44501 | B36: 899 | C36: [c] | D36: 386 | E36: 452 | F36: 1089 | G36: 5928 | H36: 2852 | I36: [c] | J36: 12124
A37: 44531 | B37: 772 | C37: [c] | D37: 417 | E37: 355 | F37: 318 | G37: 1678 | H37: 2518 | I37: [c] | J37: 6209
A38: 44562 | B38: 1149 | C38: [c] | D38: [c] | E38: 1923 | F38: 1632 | G38: 1346 | H38: 1885 | I38: 508 | J38: 8869
A39: 44593 | B39: 1696 | C39: [c] | D39: 853 | E39: 3279 | F39: 2177 | G39: 5466 | H39: 4168 | I39: [c] | J39: 18103
A40: 44621 | B40: 2922 | C40: 1669 | D40: 608 | E40: 1026 | F40: 2904 | G40: 8998 | H40: 4604 | I40: 679 | J40: 23410
A41: 44652 | B41: 2161 | C41: 114 | D41: 732 | E41: 955 | F41: 5417 | G41: 2934 | H41: 1866 | I41: 472 | J41: 14651
A42: 44682 | B42: 1904 | C42: 83 | D42: 1268 | E42: 1870 | F42: 3525 | G42: 2268 | H42: 3398 | I42: 702 | J42: 15018
A43: 44713 | B43: 1661 | C43: [c] | D43: 239 | E43: 1222 | F43: 1839 | G43: 1863 | H43: 2613 | I43: [c] | J43: 10000
A44: 44743 | B44: 2343 | C44: [c] | D44: 735 | E44: 2248 | F44: 1789 | G44: 2206 | H44: 1708 | I44: [c] | J44: 11633
A45: 44774 | B45: 2938 | C45: [c] | D45: 2362 | E45: 1504 | F45: 2007 | G45: 2941 | H45: 2329 | I45: [c] | J45: 14706
A46: 44805 | B46: 3666 | C46: [c] | D46: [c] | E46: 1880 | F46: 2327 | G46: 2667 | H46: 2193 | I46: 424 | J46: 13694
A47: 44835 | B47: 3094 | C47: 157 | D47: 434 | E47: 1998 | F47: 1624 | G47: 3641 | H47: 1868 | I47: 754 | J47: 13570
A48: 44866 | B48: 4376 | C48: 268 | D48: 599 | E48: 5571 | F48: 1573 | G48: 3280 | H48: 4089 | I48: 507 | J48: 20263
A49: 44896 | B49: 937 | C49: [c] | D49: 238 | E49: 1435 | F49: 2782 | G49: 3017 | H49: 3619 | I49: [c] | J49: 12232
A50: 44927 | B50: 5432 | C50: [c] | D50: 608 | E50: 2768 | F50: 8446 | G50: 5240 | H50: 1635 | I50: [c] | J50: 24482
A51: 44958 | B51: 4389 | C51: [c] | D51: 1973 | E51: 6309 | F51: 5720 | G51: 5152 | H51: 8678 | I51: [c] | J51: 32892
A52: 44986 | B52: 4300 | C52: 302 | D52: 690 | E52: 3729 | F52: 3361 | G52: 5199 | H52: 4255 | I52: 732 | J52: 22568
A53: 45017 | B53: 4060 | C53: 394 | D53: 732 | E53: 2089 | F53: 2419 | G53: 6712 | H53: 1860 | I53: 390 | J53: 18656
A54: 45047 | B54: 3813 | C54: 125 | D54: 544 | E54: 2435 | F54: 2417 | G54: 4258 | H54: 3635 | I54: 227 | J54: 17454
A55: 45078 | B55: 4431 | C55: 189 | D55: 735 | E55: 6988 | F55: 1660 | G55: 4730 | H55: 3009 | I55: 783 | J55: 22525
A56: 45108 | B56: 3399 | C56: [c] | D56: 1365 | E56: 3734 | F56: 3617 | G56: 6902 | H56: 4066 | I56: [c] | J56: 23975
A57: 45139 | B57: 2519 | C57: [c] | D57: 639 | E57: 3154 | F57: 13652 | G57: 4075 | H57: 3220 | I57: [c] | J57: 27942
A58: 45170 | B58: 2854 | C58: [c] | D58: 393 | E58: 2501 | F58: 2208 | G58: 6668 | H58: 2080 | I58: [c] | J58: 17150
A59: 45200 | B59: 4555 | C59: 269 | D59: 1278 | E59: 3768 | F59: 1862 | G59: 5721 | H59: 3350 | I59: 803 | J59: 21606
A60: 45231 | B60: 5203 | C60: [c] | D60: 801 | E60: 3632 | F60: 3802 | G60: 15502 | H60: 3046 | I60: [c] | J60: 32694
A61: 45261 | B61: 2404 | C61: [c] | D61: 797 | E61: 2118 | F61: 2108 | G61: 3583 | H61: 4553 | I61: [c] | J61: 16233
A62: 45292 | B62: 4088 | C62: [c] | D62: 1348 | E62: 3629 | F62: 4243 | G62: 5246 | H62: 3577 | I62: [c] | J62: 23591
A63: 45323 | B63: 5261 | C63: 338 | D63: 788 | E63: 5477 | F63: 3376 | G63: 7365 | H63: 4962 | I63: 178 | J63: 27745
A64: 45352 | B64: 3338 | C64: [c] | D64: 614 | E64: 4435 | F64: 7044 | G64: 5134 | H64: 2812 | I64: [c] | J64: 23845
A65: 45383 | B65: 2489 | C65: 257 | D65: 562 | E65: 3215 | F65: 3100 | G65: 4590 | H65: 3014 | I65: 745 | J65: 17972
A66: 45413 | B66: 3103 | C66: 247 | D66: 1351 | E66: 2692 | F66: 5750 | G66: 4976 | H66: 5187 | I66: 450 | J66: 23756
A67: 45444 | B67: 2631 | C67: 234 | D67: 987 | E67: 4070 | F67: 2255 | G67: 3557 | H67: 1441 | I67: 524 | J67: 15699
A68: 45474 | B68: 4276 | C68: 1093 | D68: 1181 | E68: 4141 | F68: 2924 | G68: 3386 | H68: 2327 | I68: 872 | J68: 20200
A69: 45505 | B69: 2713 | C69: [c] | D69: 437 | E69: 1831 | F69: 2342 | G69: 3608 | H69: 2314 | I69: [c] | J69: 13700
A70: Sep-24 | B70: 3865 | C70: 211 | D70: 2694 | E70: 2333 | F70: 2840 | G70: 5259 | H70: 2693 | I70: 336 | J70: 20231
A71: 45566 | B71: 3270 | C71: 741 | D71: 719 | E71: 2202 | F71: 2547 | G71: 6138 | H71: 2930 | I71: 137 | J71: 18684
A72: 45597 | B72: 4456 | C72: 535 | D72: 459 | E72: 1794 | F72: 5884 | G72: 5820 | H72: 3197 | I72: 623 | J72: 22768
A73: 45627 | B73: 2497 | C73: 354 | D73: 435 | E73: 2127 | F73: 1091 | G73: 10104 | H73: 2207 | I73: 484 | J73: 19299
A74: 45658 | B74: 3594 | C74: 206 | D74: 1401 | E74: 3492 | F74: 4902 | G74: 4935 | H74: 3261 | I74: 573 | J74: 22364
A75: 45689 | B75: 3588 | C75: 275 | D75: 1759 | E75: 4400 | F75: 2456 | G75: 6062 | H75: 5867 | I75: 2331 | J75: 26738
A76: 45717 | B76: 5556 | C76: 1190 | D76: 900 | E76: 3646 | F76: 5353 | G76: 4811 | H76: 7053 | I76: 534 | J76: 29043
A77: 45748 | B77: 4096 | C77: 684 | D77: 565 | E77: 2171 | F77: 2690 | G77: 5259 | H77: 4395 | I77: 2907 | J77: 22767
A78: 45778 | B78: 2626 | C78: 508 | D78: 789 | E78: 2704 | F78: 2892 | G78: 6289 | H78: 6345 | I78: 542 | J78: 22695
A79: 45809 | B79: 3779 | C79: 597 | D79: 1200 | E79: 2835 | F79: 4238 | G79: 8713 | H79: 4173 | I79: 916 | J79: 26451
A80: 45839 | B80: 4274 | C80: 392 | D80: 1633 | E80: 3309 | F80: 4011 | G80: 5303 | H80: 2842 | I80: 1397 | J80: 23161
A81: 45870 | B81: 4110 | C81: 447 | D81: 240 | E81: 1747 | F81: 2382 | G81: 5472 | H81: 4752 | I81: 279 | J81: 19429
A82: 45901 | B82: 3260 | C82: 392 | D82: 759 | E82: 2606 | F82: 3342 | G82: 7177 | H82: 5902 | I82: 412 | J82: 23850
... A84: 45962 | B84: 4195 | C84: 1578 | D84: 1025 | E84: 2871 | F84: 2462 | G84: 5350 | H84: 11442 | I84: 810 | J84: 29733

Sheet 2b
A1: Worksheet 2b: Number of employers submitting HR1 forms by combined industries, GB [note 6] [note 7]
A2: This worksheet contains one table.
A3: Some shorthand is used in this table, [c] = confidential
A4: Month | B4: Manufacturing | C4: Energy and Water | D4: Construction | E4: Transport and Communication | F4: Distribution, Hotels and Restaurants | G4: Banking and Finance | H4: Public Admin, Education and Health | I4: Other Services | J4: GB
A5: 43556 | B5: 37 | C5: [c] | D5: 14 | E5: 32 | F5: [c] | G5: 63 | H5: 50 | I5: 9 | J5: 256
A6: 43586 | B6: 55 | C6: 8 | D6: 14 | E6: 31 | F6: 60 | G6: 86 | H6: 53 | I6: 8 | J6: 315
A7: 43617 | B7: 54 | C7: 3 | D7: 17 | E7: 24 | F7: 48 | G7: 89 | H7: 41 | I7: 9 | J7: 285
A8: 43647 | B8: 41 | C8: 4 | D8: 23 | E8: 32 | F8: 41 | G8: 57 | H8: 34 | I8: 10 | J8: 242
A9: 43678 | B9: 37 | C9: 5 | D9: 12 | E9: 16 | F9: 36 | G9: 48 | H9: 28 | I9: 4 | J9: 186
A10: 43709 | B10: 51 | C10: 7 | D10: 14 | E10: 32 | F10: 46 | G10: 46 | H10: 38 | I10: 10 | J10: 244
A11: 43739 | B11: 62 | C11: 16 | D11: 22 | E11: 30 | F11: 55 | G11: 58 | H11: 30 | I11: 14 | J11: 287
A12: 43770 | B12: 47 | C12: 4 | D12: 12 | E12: 35 | F12: 37 | G12: 79 | H12: 31 | I12: 9 | J12: 254
A13: 43800 | B13: 34 | C13: [c] | D13: 12 | E13: 14 | F13: 34 | G13: 44 | H13: 19 | I13: [c] | J13: 164
A14: 43831 | B14: 66 | C14: 3 | D14: 12 | E14: 36 | F14: 68 | G14: 72 | H14: 42 | I14: 11 | J14: 310
A15: 43862 | B15: 63 | C15: [c] | D15: 18 | E15: 45 | F15: 40 | G15: 72 | H15: 42 | I15: [c] | J15: 288
A16: 43891 | B16: 56 | C16: 6 | D16: 29 | E16: 54 | F16: 90 | G16: 92 | H16: 37 | I16: 18 | J16: 382
A17: 43922 | B17: 47 | C17: 19 | D17: 21 | E17: 49 | F17: 57 | G17: 89 | H17: 18 | I17: 16 | J17: 316
A18: 43952 | B18: 182 | C18: 16 | D18: 39 | E18: 99 | F18: 136 | G18: 147 | H18: 31 | I18: 50 | J18: 700
A19: 43983 | B19: 280 | C19: 22 | D19: 67 | E19: 124 | F19: 495 | G19: 299 | H19: 85 | I19: 102 | J19: 1474
A20: 44013 | B20: 214 | C20: 13 | D20: 53 | E20: 131 | F20: 366 | G20: 304 | H20: 63 | I20: 106 | J20: 1250
A21: 44044 | B21: 97 | C21: 11 | D21: 31 | E21: 67 | F21: 212 | G21: 184 | H21: 49 | I21: 79 | J21: 730
A22: 44075 | B22: 110 | C22: 6 | D22: 18 | E22: 58 | F22: 214 | G22: 167 | H22: 54 | I22: 55 | J22: 682
A23: 44105 | B23: 86 | C23: 13 | D23: 18 | E23: 86 | F23: 164 | G23: 184 | H23: 39 | I23: 65 | J23: 655
A24: 44136 | B24: 51 | C24: 7 | D24: 16 | E24: 41 | F24: 89 | G24: 92 | H24: 40 | I24: 14 | J24: 350
A25: 44166 | B25: 24 | C25: 5 | D25: 8 | E25: 22 | F25: 71 | G25: 43 | H25: 24 | I25: 6 | J25: 203
A26: 44197 | B26: 35 | C26: 6 | D26: 8 | E26: 28 | F26: 50 | G26: 70 | H26: 37 | I26: 8 | J26: 242
A27: 44228 | B27: 47 | C27: 9 | D27: 10 | E27: 37 | F27: 41 | G27: 76 | H27: 35 | I27: 7 | J27: 262
... A30: 44317 | B30: 41 | C30: 6 | D30: 8 | E30: 16 | F30: 33 | G30: 57 | H30: 40 | I30: 6 | J30: 207
A31: 44348 | B31: 21 | C31: [c] | D31: 9 | E31: 23 | F31: 21 | G31: 26 | H31: 40 | I31: [c] | J31: 150
A32: 44378 | B32: 22 | C32: 4 | D32: 6 | E32: 15 | F32: 22 | G32: 49 | H32: 28 | I32: 4 | J32: 150
A33: 44409 | B33: 22 | C33: 7 | D33: 6 | E33: 14 | F33: 33 | G33: 37 | H33: 35 | I33: 7 | J33: 161
A34: 44440 | B34: 25 | C34: 10 | D34: 9 | E34: 12 | F34: 38 | G34: 38 | H34: 23 | I34: 4 | J34: 159
A35: 44470 | B35: 30 | C35: 7 | D35: 5 | E35: 28 | F35: 24 | G35: 29 | H35: 23 | I35: 6 | J35: 152
A36: 44501 | B36: 15 | C36: [c] | D36: 6 | E36: 11 | F36: 23 | G36: 54 | H36: 20 | I36: [c] | J36: 136
A37: 44531 | B37: 13 | C37: [c] | D37: 9 | E37: 6 | F37: 8 | G37: 24 | H37: 16 | I37: [c] | J37: 80
A38: 44562 | B38: 21 | C38: [c] | D38: [c] | E38: 17 | F38: 35 | G38: 31 | H38: 21 | I38: 7 | J38: 140
A39: 44593 | B39: 27 | C39: [c] | D39: 13 | E39: 27 | F39: 27 | G39: 57 | H39: 40 | I39: [c] | J39: 201
A40: 44621 | B40: 39 | C40: 4 | D40: 10 | E40: 22 | F40: 44 | G40: 66 | H40: 29 | I40: 9 | J40: 223
A41: 44652 | B41: 32 | C41: 3 | D41: 12 | E41: 15 | F41: 35 | G41: 46 | H41: 19 | I41: 9 | J41: 171
A42: 44682 | B42: 37 | C42: 3 | D42: 14 | E42: 25 | F42: 51 | G42: 42 | H42: 28 | I42: 5 | J42: 205
A43: 44713 | B43: 28 | C43: [c] | D43: 5 | E43: 14 | F43: 33 | G43: 42 | H43: 40 | I43: [c] | J43: 167
A44: 44743 | B44: 34 | C44: [c] | D44: 17 | E44: 27 | F44: 28 | G44: 38 | H44: 27 | I44: [c] | J44: 178
A45: 44774 | B45: 42 | C45: [c] | D45: 19 | E45: 26 | F45: 35 | G45: 52 | H45: 21 | I45: [c] | J45: 205
A46: 44805 | B46: 45 | C46: [c] | D46: [c] | E46: 33 | F46: 32 | G46: 46 | H46: 30 | I46: 10 | J46: 207
A47: 44835 | B47: 45 | C47: 4 | D47: 10 | E47: 31 | F47: 39 | G47: 65 | H47: 22 | I47: 13 | J47: 229
A48: 44866 | B48: 57 | C48: 7 | D48: 16 | E48: 48 | F48: 31 | G48: 45 | H48: 37 | I48: 9 | J48: 250
A49: 44896 | B49: 19 | C49: [c] | D49: 6 | E49: 33 | F49: 37 | G49: 46 | H49: 26 | I49: [c] | J49: 173
A50: 44927 | B50: 60 | C50: [c] | D50: 16 | E50: 42 | F50: 68 | G50: 70 | H50: 35 | I50: [c] | J50: 302
A51: 44958 | B51: 54 | C51: 3 | D51: 23 | E51: 59 | F51: 49 | G51: 70 | H51: 43 | I51: 9 | J51: 310
A52: 44986 | B52: 56 | C52: 5 | D52: 16 | E52: 53 | F52: 69 | G52: 92 | H52: 39 | I52: 10 | J52: 340
A53: 45017 | B53: 51 | C53: 6 | D53: 17 | E53: 42 | F53: 49 | G53: 71 | H53: 35 | I53: 7 | J53: 278
A54: 45047 | B54: 53 | C54: 3 | D54: 11 | E54: 39 | F54: 49 | G54: 73 | H54: 36 | I54: 5 | J54: 269
A55: 45078 | B55: 49 | C55: 4 | D55: 15 | E55: 54 | F55: 31 | G55: 74 | H55: 50 | I55: 12 | J55: 289
A56: 45108 | B56: 42 | C56: [c] | D56: 20 | E56: 47 | F56: 48 | G56: 50 | H56: 42 | I56: [c] | J56: 260
A57: 45139 | B57: 39 | C57: 4 | D57: 12 | E57: 46 | F57: 32 | G57: 64 | H57: 38 | I57: 8 | J57: 243
A58: 45170 | B58: 43 | C58: [c] | D58: 7 | E58: 36 | F58: 52 | G58: 105 | H58: 38 | I58: [c] | J58: 288
A59: 45200 | B59: 48 | C59: 3 | D59: 21 | E59: 63 | F59: 36 | G59: 94 | H59: 29 | I59: 10 | J59: 304
A60: 45231 | B60: 65 | C60: [c] | D60: 16 | E60: 57 | F60: 52 | G60: 98 | H60: 39 | I60: [c] | J60: 340
A61: 45261 | B61: 39 | C61: [c] | D61: 9 | E61: 23 | F61: 33 | G61: 50 | H61: 28 | I61: [c] | J61: 190
A62: 45292 | B62: 51 | C62: 5 | D62: 20 | E62: 52 | F62: 85 | G62: 74 | H62: 49 | I62: 12 | J62: 348
A63: 45323 | B63: 50 | C63: 6 | D63: 18 | E63: 71 | F63: 56 | G63: 105 | H63: 54 | I63: 5 | J63: 365
A64: 45352 | B64: 53 | C64: [c] | D64: 13 | E64: 55 | F64: 85 | G64: 75 | H64: 50 | I64: [c] | J64: 344
A65: 45383 | B65: 48 | C65: 5 | D65: 12 | E65: 44 | F65: 45 | G65: 76 | H65: 42 | I65: 6 | J65: 278
A66: 45413 | B66: 49 | C66: 4 | D66: 17 | E66: 41 | F66: 71 | G66: 98 | H66: 59 | I66: 10 | J66: 349
A67: 45444 | B67: 36 | C67: 4 | D67: 17 | E67: 53 | F67: 36 | G67: 62 | H67: 24 | I67: 5 | J67: 237
A68: 45474 | B68: 52 | C68: 11 | D68: 19 | E68: 62 | F68: 51 | G68: 67 | H68: 42 | I68: 11 | J68: 315
A69: 45505 | B69: 42 | C69: [c] | D69: 12 | E69: 29 | F69: 45 | G69: 64 | H69: 38 | I69: [c] | J69: 240
A70: Sep-24 | B70: 43 | C70: 3 | D70: 15 | E70: 42 | F70: 43 | G70: 85 | H70: 34 | I70: 8 | J70: 273
A71: 45566 | B71: 60 | C71: 7 | D71: 18 | E71: 43 | F71: 46 | G71: 97 | H71: 39 | I71: 4 | J71: 314
A72: 45597 | B72: 51 | C72: 5 | D72: 9 | E72: 38 | F72: 37 | G72: 68 | H72: 39 | I72: 14 | J72: 261
A73: 45627 | B73: 44 | C73: 6 | D73: 7 | E73: 29 | F73: 28 | G73: 57 | H73: 33 | I73: 11 | J73: 215
A74: 45658 | B74: 56 | C74: 4 | D74: 15 | E74: 55 | F74: 69 | G74: 79 | H74: 57 | I74: 13 | J74: 348
A75: 45689 | B75: 58 | C75: 6 | D75: 25 | E75: 69 | F75: 49 | G75: 91 | H75: 52 | I75: 15 | J75: 365
A76: 45717 | B76: 59 | C76: 16 | D76: 21 | E76: 51 | F76: 69 | G76: 99 | H76: 68 | I76: 12 | J76: 395
A77: 45748 | B77: 56 | C77: 11 | D77: 11 | E77: 41 | F77: 48 | G77: 75 | H77: 59 | I77: 19 | J77: 320
A78: 45778 | B78: 49 | C78: 8 | D78: 12 | E78: 48 | F78: 45 | G78: 95 | H78: 65 | I78: 10 | J78: 332
A79: 45809 | B79: 60 | C79: 9 | D79: 14 | E79: 43 | F79: 50 | G79: 91 | H79: 58 | I79: 12 | J79: 337
A80: 45839 | B80: 44 | C80: 6 | D80: 13 | E80: 54 | F80: 67 | G80: 91 | H80: 45 | I80: 24 | J80: 344
A81: 45870 | B81: 42 | C81: 5 | D81: 6 | E81: 32 | F81: 37 | G81: 73 | H81: 39 | I81: 8 | J81: 242
A82: 45901 | B82: 45 | C82: 4 | D82: 17 | E82: 47 | F82: 47 | G82: 112 | H82: 33 | I82: 7 | J82: 312
... A84: 45962 | B84: 54 | C84: 5 | D84: 17 | E84: 44 | F84: 52 | G84: 82 | H84: 81 | I84: 15 | J84: 350

Sheet Labour market flows >>>

Sheet Labour market flows SA
B1: X02: Labour Market Flows (designated as official statistics in development)
B3: Seasonally adjusted, people aged 16-64, UK (thousands)
C5: Employment | K5: Job to Job1 (aged 16 to 69) | N5: Unemployment | V5: Economic Inactivity
C7: Still in Employment | D7: Employment to Unemployment | E7: Employment to Economic Inactivity | F7: Employment Gross Inflow | G7: Employment Gross Outflow | H7: Employment Net Flow | I7: Employment Quarterly Change in Stock | K7: Levels | L7: Rates | N7: Still in Unemployment | O7: Unemployment to Employment | P7: Unemployment to Economic Inactivity | Q7: Unemployment Gross Inflow | R7: Unemployment Gross Outflow | S7: Unemployment Net Flow | T7: Unemployment Quarterly Change in Stock | V7: Still in Economic Inactivity | W7: Economic Inactivity to Employment | X7: Economic Inactivity to Unemployment | Y7: Economic Inactivity Gross Inflow | Z7: Economic Inactivity Gross Outflow | AA7: Economic Inactivity Net Flow | AB7: Economic Inactivity Quarterly Change in Stock | AE7: % of people moving from inactivity to employment | AF7: % of people moving from inactivity to unemployment | AH7: % of people moving from inactivity to unemployment | AI7: % of people moving from employment to unemployment
A8: =DATE(2001,10,1) | B8: Oct-Dec 2001 | C8: 26375755 | D8: 363624.03 | E8: 543004.63 | F8: 915392.66 | G8: 906628.65 | H8: 8764.008 | I8: 66356.919 | K8: 821003.28 | L8: 3.0807616 | N8: 792239.97 | O8: 417425.19 | P8: 261623.46 | Q8: 688747.69 | R8: 679048.64 | S8: 9699.0424 | T8: 31472.995 | V8: 7873641.5 | W8: 497967.47 | X8: 325123.66 | Y8: 804628.08 | Z8: 823091.13 | AA8: -18463.05 | AB8: -33477.914 | AE8: =W8/Z8 | AF8: =X8/Z8 | AH8: =X8/$Q8 | AI8: =D8/$Q8 | AV8: Using July-September to April-June quarters
A9: =EDATE(A8, 3) | B9: Jan-Mar 2002 | C9: 26375458 | D9: 354867.77 | E9: 570290.4 | F9: 904665.62 | G9: 925158.17 | H9: -20492.556 | I9: -1086.4927 | K9: 813983.07 | L9: 3.054621 | N9: 799291.66 | O9: 441693.36 | P9: 265444.09 | Q9: 680606 | R9: 707137.45 | S9: -26531.455 | T9: -7313.2113 | V9: 7911050.8 | W9: 462972.26 | X9: 325738.22 | Y9: 835734.49 | Z9: 788710.48 | AA9: 47024.011 | AB9: 71725.704 | AE9: =W9/Z9 | AF9: =X9/Z9 | AH9: =X9/$Q9 | AI9: =D9/$Q9 | AW9: =D7 | AX9: =E7 | AY9: =O7 | AZ9: =P7 | BA9: =W7 | BB9: =X7 | BC9: Job to job changes
A10: =EDATE(A9, 3) | B10: Apr-Jun 2002 | C10: 26423873 | D10: 353757.51 | E10: 521247.65 | F10: 1019781.3 | G10: 875005.15 | H10: 144776.13 | I10: 133016.53 | K10: 781956.6 | L10: 2.9290347 | N10: 773623.44 | O10: 479712.07 | P10: 258239.09 | Q10: 720654.43 | R10: 737951.17 | S10: -17296.735 | T10: 2939.1994 | V10: 7879987 | W10: 540069.21 | X10: 366896.92 | Y10: 779486.74 | Z10: 906966.13 | AA10: -127479.4 | AB10: -71244.725 | AE10: =W10/Z10 | AF10: =X10/Z10 | AH10: =X10/$Q10 | AI10: =D10/$Q10 | AV10: Avg Jul-Sep 2015 to Apr-Jun 2020 | AW10: =AVERAGE(D63:D82) | AX10: =AVERAGE(E63:E82) | AY10: =AVERAGE(O63:O82) | AZ10: =AVERAGE(P63:P82) | BA10: =AVERAGE(W63:W82) | BB10: =AVERAGE(X63:X82) | BC10: =AVERAGE(K63:K82)
A11: =EDATE(A10, 3) | B11: Jul-Sep 2002 | C11: 26525576 | D11: 374961.33 | E11: 533018.42 | F11: 943941.84 | G11: 907979.75 | H11: 35962.085 | I11: 1869.6704 | K11: 763238.37 | L11: 2.8476304 | N11: 789597.99 | O11: 454993.21 | P11: 254818.51 | Q11: 721720.55 | R11: 709811.73 | S11: 11908.825 | T11: 47036.111 | V11: 7873632 | W11: 488948.62 | X11: 346759.22 | Y11: 787836.93 | Z11: 835707.84 | AA11: -47870.909 | AB11: 12561.218 | AE11: =W11/Z11 | AF11: =X11/Z11 | AH11: =X11/$Q11 | AI11: =D11/$Q11 | AV11: 2020/21 | AW11: =AVERAGE(D83:D86) | AX11: =AVERAGE(E83:E86) | AY11: =AVERAGE(O83:O86) | AZ11: =AVERAGE(P83:P86) | BA11: =AVERAGE(W83:W86) | BB11: =AVERAGE(X83:X86) | BC11: =AVERAGE(K83:K86)
A12: =EDATE(A11, 3) | B12: Oct-Dec 2002 | C12: 26617721 | D12: 342048.2 | E12: 517078.5 | F12: 960046.94 | G12: 859126.71 | H12: 100920.23 | I12: 159113.08 | K12: 760258.71 | L12: 2.8251458 | N12: 774123.9 | O12: 471555.14 | P12: 293335.42 | Q12: 715880.52 | R12: 764890.56 | S12: -49010.041 | T12: -45899.484 | V12: 7831995.7 | W12: 488491.8 | X12: 373832.31 | Y12: 810413.92 | Z12: 862324.11 | AA12: -51910.192 | AB12: -50848.597 | AE12: =W12/Z12 | AF12: =X12/Z12 | AH12: =X12/$Q12 | AI12: =D12/$Q12 | AV12: 2021/22 | AW12: =AVERAGE(D87:D90) | AX12: =AVERAGE(E87:E90) | AY12: =AVERAGE(O87:O90) | AZ12: =AVERAGE(P87:P90) | BA12: =AVERAGE(W87:W90) | BB12: =AVERAGE(X87:X90) | BC12: =AVERAGE(K87:K90)
A13: =EDATE(A12, 3) | B13: Jan-Mar 2003 | C13: 26630949 | D13: 363908.7 | E13: 573074.68 | F13: 908641.12 | G13: 936983.39 | H13: -28342.267 | I13: -27511.411 | K13: 785181.98 | L13: 2.9139556 | N13: 778271.58 | O13: 437895.32 | P13: 288919.53 | Q13: 710818.93 | R13: 726814.85 | S13: -15995.917 | T13: 11927.323 | V13: 7847553.6 | W13: 470745.8 | X13: 346910.23 | Y13: 861994.21 | Z13: 817656.03 | AA13: 44338.184 | AB13: 77279.088 | AE13: =W13/Z13 | AF13: =X13/Z13 | AH13: =X13/$Q13 | AI13: =D13/$Q13 | AV13: 2022/23 | AW13: =AVERAGE(D91:D94) | AX13: =AVERAGE(E91:E94) | AY13: =AVERAGE(O91:O94) | AZ13: =AVERAGE(P91:P94) | BA13: =AVERAGE(W91:W94) | BB13: =AVERAGE(X91:X94) | BC13: =AVERAGE(K91:K94)
A14: =EDATE(A13, 3) | B14: Apr-Jun 2003 | C14: 26708542 | D14: 317973.62 | E14: 529745.58 | F14: 976696.26 | G14: 847719.2 | H14: 128977.07 | I14: 121063.18 | K14: 760447.23 | L14: 2.8144147 | N14: 768852.12 | O14: 473491.96 | P14: 279592.25 | Q14: 666067.95 | R14: 753084.21 | S14: -87016.259 | T14: -65262.093 | V14: 7910519.8 | W14: 503204.3 | X14: 348094.33 | Y14: 809337.83 | Z14: 851298.63 | AA14: -41960.806 | AB14: 6008.9175 | AE14: =W14/Z14 | AF14: =X14/Z14 | AH14: =X14/$Q14 | AI14: =D14/$Q14 | AV14: 2023/24 | AW14: =AVERAGE(D95:D98) | AX14: =AVERAGE(E95:E98) | AY14: =AVERAGE(O95:O98) | AZ14: =AVERAGE(P95:P98) | BA14: =AVERAGE(W95:W98) | BB14: =AVERAGE(X95:X98) | BC14: =AVERAGE(K95:K98)
A15: =EDATE(A14, 3) | B15: Jul-Sep 2003 | C15: 26781004 | D15: 339608.36 | E15: 558200.87 | F15: 930504.65 | G15: 897809.23 | H15: 32695.424 | I15: 12668.805 | K15: 794633.4 | L15: 2.9316924 | N15: 757575.94 | O15: 419668 | P15: 264946.14 | Q15: 689270.46 | R15: 684614.13 | S15: 4656.329 | T15: 36602.714 | V15: 7903008.1 | W15: 510836.66 | X15: 349662.11 | Y15: 823147.01 | Z15: 860498.76 | AA15: -37351.753 | AB15: 21108.481 | AE15: =W15/Z15 | AF15: =X15/Z15 | AH15: =X15/$Q15 | AI15: =D15/$Q15 | AV15: 2024/25 | AW15: =AVERAGE(D99:D102) | AX15: =AVERAGE(E99:E102) | AY15: =AVERAGE(O99:O102) | AZ15: =AVERAGE(P99:P102) | BA15: =AVERAGE(W99:W102) | BB15: =AVERAGE(X99:X102) | BC15: =AVERAGE(K99:K102)
A16: =EDATE(A15, 3) | B16: Oct-Dec 2003 | C16: 26795033 | D16: 315907.75 | E16: 596366.46 | F16: 948238.27 | G16: 912274.21 | H16: 35964.059 | I16: 49559.929 | K16: 765635.88 | L16: 2.8220339 | N16: 762557.43 | O16: 445167.73 | P16: 274492.9 | Q16: 660451.4 | R16: 719660.63 | S16: -59209.229 | T16: -48415.616 | V16: 7939276.8 | W16: 503070.54 | X16: 344543.65 | Y16: 870859.36 | Z16: 847614.19 | AA16: 23245.17 | AB16: 72964.687 | AE16: =W16/Z16 | AF16: =X16/Z16 | AH16: =X16/$Q16 | AI16: =D16/$Q16
A17: =EDATE(A16, 3) | B17: Jan-Mar 2004 | C17: 26910078 | D17: 315237.94 | E17: 533447.69 | F17: 994673.23 | G17: 848685.62 | H17: 145987.6 | I17: 155336.55 | K17: 787934.18 | L17: 2.8947243 | N17: 728141.88 | O17: 453428.15 | P17: 262482.6 | Q17: 672312.56 | R17: 715910.75 | S17: -43598.189 | T17: -20737.839 | V17: 7938074.1 | W17: 541245.07 | X17: 357074.63 | Y17: 795930.29 | Z17: 898319.7 | AA17: -102389.41 | AB17: -60700.711 | AE17: =W17/Z17 | AF17: =X17/Z17 | AH17: =X17/$Q17 | AI17: =D17/$Q17 | AV17: Using calendar years
A18: =EDATE(A17, 3) | B18: Apr-Jun 2004 | C18: 26954424 | D18: 346209.54 | E18: 610590.75 | F18: 943905.47 | G18: 956800.29 | H18: -12894.82 | I18: -5117.1567 | K18: 796685.92 | L18: 2.9214514 | N18: 715122.08 | O18: 437832.94 | P18: 271637.16 | Q18: 694021.86 | R18: 709470.1 | S18: -15448.239 | T18: 4623.6961 | V18: 7928549 | W18: 506072.53 | X18: 347812.32 | Y18: 882227.91 | Z18: 853884.85 | AA18: 28343.059 | AB18: 75182.461 | AE18: =W18/Z18 | AF18: =X18/Z18 | AH18: =X18/$Q18 | AI18: =D18/$Q18 | AW18: =AW9 | AX18: =AX9 | AY18: =AY9 | AZ18: =AZ9 | BA18: =BA9 | BB18: =BB9 | BC18: =BC9
A19: =EDATE(A18, 3) | B19: Jul-Sep 2004 | C19: 27006393 | D19: 293441.88 | E19: 607440.14 | F19: 962462.44 | G19: 900882.02 | H19: 61580.419 | I19: 63542.611 | K19: 813684.53 | L19: 2.9779873 | N19: 696455.21 | O19: 429090.26 | P19: 288105.38 | Q19: 658157.62 | R19: 717195.64 | S19: -59038.016 | T19: -34235.097 | V19: 7986000.6 | W19: 533372.17 | X19: 364715.74 | Y19: 895545.51 | Z19: 898087.92 | AA19: -2542.403 | AB19: 63868.486 | AE19: =W19/Z19 | AF19: =X19/Z19 | AH19: =X19/$Q19 | AI19: =D19/$Q19 | AV19: Avg 2015-2019 | AW19: =AVERAGE(D61:D80) | AX19: =AVERAGE(E61:E80) | AY19: =AVERAGE(O61:O80) | AZ19: =AVERAGE(P61:P80) | BA19: =AVERAGE(W61:W80) | BB19: =AVERAGE(X61:X80) | BC19: =AVERAGE(K61:K80)
A20: =EDATE(A19, 3) | B20: Oct-Dec 2004 | C20: 27107388 | D20: 342022.97 | E20: 550921.48 | F20: 1014126.7 | G20: 892944.45 | H20: 121182.22 | I20: 142010.4 | K20: 794833.68 | L20: 2.8977897 | N20: 698815.47 | O20: 425464.05 | P20: 268342.79 | Q20: 691973.38 | R20: 693806.84 | S20: -1833.4634 | T20: 16617.808 | V20: 8021336.8 | W20: 588662.62 | X20: 349950.41 | Y20: 819264.27 | Z20: 938613.03 | AA20: -119348.76 | AB20: -55634.211 | AE20: =W20/Z20 | AF20: =X20/Z20 | AH20: =X20/$Q20 | AI20: =D20/$Q20 | AV20: 2020 | AW20: =AVERAGE(D81:D84) | AX20: =AVERAGE(E81:E84) | AY20: =AVERAGE(O81:O84) | AZ20: =AVERAGE(P81:P84) | BA20: =AVERAGE(W81:W84) | BB20: =AVERAGE(X81:X84) | BC20: =AVERAGE(K81:K84)
A21: =EDATE(A20, 3) | B21: Jan-Mar 2005 | C21: 27229877 | D21: 334294.46 | E21: 533906.25 | F21: 984873.75 | G21: 868200.72 | H21: 116673.03 | I21: 90606.546 | K21: 722522.73 | L21: 2.6207451 | N21: 673492.07 | O21: 435515.47 | P21: 301008.44 | Q21: 707075.45 | R21: 736523.91 | S21: -29448.459 | T21: -5220.1498 | V21: 7985219.5 | W21: 549358.28 | X21: 372780.99 | Y21: 834914.69 | Z21: 922139.26 | AA21: -87224.575 | AB21: 19550.604 | AE21: =W21/Z21 | AF21: =X21/Z21 | AH21: =X21/$Q21 | AI21: =D21/$Q21 | AV21: 2021 | AW21: =AVERAGE(D85:D88) | AX21: =AVERAGE(E85:E88) | AY21: =AVERAGE(O85:O88) | AZ21: =AVERAGE(P85:P88) | BA21: =AVERAGE(W85:W88) | BB21: =AVERAGE(X85:X88) | BC21: =AVERAGE(K85:K88)
A22: =EDATE(A21, 3) | B22: Apr-Jun 2005 | C22: 27279072 | D22: 340199.4 | E22: 578926.07 | F22: 936266.01 | G22: 919125.47 | H22: 17140.543 | I22: 4757.0813 | K22: 726723.95 | L22: 2.629851 | N22: 722411.1 | O22: 418717.63 | P22: 265190.27 | Q22: 688119.45 | R22: 683907.9 | S22: 4211.5586 | T22: 23271.713 | V22: 8074087.4 | W22: 517548.38 | X22: 347920.06 | Y22: 844116.34 | Z22: 865468.44 | AA22: -21352.102 | AB22: 75181.206 | AE22: =W22/Z22 | AF22: =X22/Z22 | AH22: =X22/$Q22 | AI22: =D22/$Q22 | AV22: 2022 | AW22: =AVERAGE(D89:D92) | AX22: =AVERAGE(E89:E92) | AY22: =AVERAGE(O89:O92) | AZ22: =AVERAGE(P89:P92) | BA22: =AVERAGE(W89:W92) | BB22: =AVERAGE(X89:X92) | BC22: =AVERAGE(K89:K92)
A23: =EDATE(A22, 3) | B23: Jul-Sep 2005 | C23: 27360394 | D23: 314894.3 | E23: 509249.97 | F23: 971556.5 | G23: 824144.27 | H23: 147412.22 | I23: 130671.68 | K23: 695708.58 | L23: 2.5103944 | N23: 677393.32 | O23: 452841.61 | P23: 280237.01 | Q23: 698835.53 | R23: 733078.61 | S23: -34243.083 | T23: -4627.899 | V23: 8088313.8 | W23: 518714.89 | X23: 383941.23 | Y23: 789486.98 | Z23: 902656.12 | AA23: -113169.14 | AB23: -26835.785 | AE23: =W23/Z23 | AF23: =X23/Z23 | AH23: =X23/$Q23 | AI23: =D23/$Q23 | AV23: 2023 | AW23: =AVERAGE(D93:D96) | AX23: =AVERAGE(E93:E96) | AY23: =AVERAGE(O93:O96) | AZ23: =AVERAGE(P93:P96) | BA23: =AVERAGE(W93:W96) | BB23: =AVERAGE(X93:X96) | BC23: =AVERAGE(K93:K96) | BF23: Employment to Unemployment | BG23: Employment to Economic Inactivity | BH23: Unemployment to Employment | BI23: Unemployment to Economic Inactivity | BJ23: Economic Inactivity to Employment | BK23: Economic Inactivity to Unemployment | BL23: Job to job changes
A24: =EDATE(A23, 3) | B24: Oct-Dec 2005 | C24: 27375439 | D24: 380987.91 | E24: 574908.23 | F24: 903253.69 | G24: 955896.15 | H24: -52642.461 | I24: -74267.404 | K24: 685361.45 | L24: 2.4712727 | N24: 777116.33 | O24: 390287.28 | P24: 268934.9 | Q24: 760430.28 | R24: 659222.18 | S24: 101208.1 | T24: 128463.89 | V24: 8090435.7 | W24: 512966.41 | X24: 379442.37 | Y24: 843843.14 | Z24: 892408.78 | AA24: -48565.643 | AB24: 42035.517 | AE24: =W24/Z24 | AF24: =X24/Z24 | AH24: =X24/$Q24 | AI24: =D24/$Q24 | AV24: 2024 | AW24: =AVERAGE(D97:D100) | AX24: =AVERAGE(E97:E100) | AY24: =AVERAGE(O97:O100) | AZ24: =AVERAGE(P97:P100) | BA24: =AVERAGE(W97:W100) | BB24: =AVERAGE(X97:X100) | BC24: =AVERAGE(K97:K100) | BE24: 2015-2024 average | BF24: =AVERAGE(D61:D100) | BG24: =AVERAGE(E61:E100) | BH24: =AVERAGE(O61:O100) | BI24: =AVERAGE(P61:P100) | BJ24: =AVERAGE(W61:W100) | BK24: =AVERAGE(X61:X100) | BL24: =AVERAGE(K61:K100)
A25: =EDATE(A24, 3) | B25: Jan-Mar 2006 | C25: 27460660 | D25: 320567.14 | E25: 475711.8 | F25: 976779.98 | G25: 796278.94 | H25: 180501.04 | I25: 160252.49 | K25: 687873.33 | L25: 2.4730818 | N25: 847489.26 | O25: 418290.66 | P25: 280004.37 | Q25: 713419.33 | R25: 698295.02 | S25: 15124.306 | T25: 39122.936 | V25: 8050564.5 | W25: 558489.32 | X25: 392852.19 | Y25: 755716.16 | Z25: 951341.51 | AA25: -195625.35 | AB25: -102600.42 | AE25: =W25/Z25 | AF25: =X25/Z25 | AH25: =X25/$Q25 | AI25: =D25/$Q25 | AV25: Q1, Q2 and Q3 2025 | AW25: =AVERAGE($D$101:$D$104) | AX25: =AVERAGE($E$101:$E$104) | AY25: =AVERAGE($O$101:$O$104) | AZ25: =AVERAGE($P$101:$P$104) | BA25: =AVERAGE($W$101:$W$104) | BB25: =AVERAGE($X$101:$X$104) | BC25: =AVERAGE($K$101:$K$104) | BE25: Q1/Q2/Q3 2025 average | BF25: =AVERAGE($D$101:$D$104) | BG25: =AVERAGE($E$101:$E$104) | BH25: =AVERAGE($O$101:$O$104) | BI25: =AVERAGE($P$101:$P$104) | BJ25: =AVERAGE($W$101:$W$104) | BK25: =AVERAGE($X$101:$X$104) | BL25: =AVERAGE($K$101:$K$104)
A26: =EDATE(A25, 3) | B26: Apr-Jun 2006 | C26: 27555934 | D26: 350208.39 | E26: 525010.81 | F26: 933416.18 | G26: 875219.2 | H26: 58196.985 | I26: 46238.041 | K26: 730765.85 | L26: 2.618051 | N26: 868285.22 | O26: 421066.62 | P26: 302261.43 | Q26: 801185.93 | R26: 723328.05 | S26: 77857.88 | T26: 80825.43 | V26: 7957874.2 | W26: 512349.56 | X26: 450977.54 | Y26: 827272.24 | Z26: 963327.1 | AA26: -136054.86 | AB26: -31138.471 | AE26: =W26/Z26 | AF26: =X26/Z26 | AH26: =X26/$Q26 | AI26: =D26/$Q26
A27: =EDATE(A26, 3) | B27: Jul-Sep 2006 | C27: 27558239 | D27: 372630.26 | E27: 530756.73 | F27: 994250.57 | G27: 903386.98 | H27: 90863.584 | I27: 60796.04 | K27: 635428.1 | L27: 2.2749029 | N27: 890117.35 | O27: 465132.26 | P27: 301653.18 | Q27: 750420.04 | R27: 766785.43 | S27: -16365.388 | T27: 7073.387 | V27: 7961985.2 | W27: 529118.31 | X27: 377789.79 | Y27: 832409.9 | Z27: 906908.1 | AA27: -74498.196 | AB27: 29876.574 | AE27: =W27/Z27 | AF27: =X27/Z27 | AH27: =X27/$Q27 | AI27: =D27/$Q27
A28: =EDATE(A27, 3) | B28: Oct-Dec 2006 | C28: 27639711 | D28: 345805.42 | E28: 558730.13 | F28: 930381.56 | G28: 904535.55 | H28: 25846.004 | I28: 27996.827 | K28: 711247.34 | L28: 2.5368446 | N28: 934743.97 | O28: 446447.31 | P28: 299127.39 | Q28: 733682.11 | R28: 745574.71 | S28: -11892.598 | T28: 12729.917 | V28: 8024169.5 | W28: 483934.24 | X28: 387876.68 | Y28: 857857.52 | Z28: 871810.93 | AA28: -13953.406 | AB28: 56880.256 | AE28: =W28/Z28 | AF28: =X28/Z28 | AH28: =X28/$Q28 | AI28: =D28/$Q28
A29: =EDATE(A28, 3) | B29: Jan-Mar 2007 | C29: 27586969 | D29: 344451.66 | E29: 616256.48 | F29: 931220.57 | G29: 960708.14 | H29: -29487.567 | I29: -10109.067 | K29: 702361.26 | L29: 2.5105554 | N29: 896813.98 | O29: 441437.15 | P29: 347362.24 | Q29: 762998.06 | R29: 788799.39 | S29: -25801.336 | T29: -883.99845 | V29: 8040103.7 | W29: 489783.42 | X29: 418546.4 | Y29: 963618.72 | Z29: 908329.82 | AA29: 55288.903 | AB29: 108179.07 | AE29: =W29/Z29 | AF29: =X29/Z29 | AH29: =X29/$Q29 | AI29: =D29/$Q29
A30: =EDATE(A29, 3) | B30: Apr-Jun 2007 | C30: 27683314 | D30: 320581.17 | E30: 534555.09 | F30: 1006447.4 | G30: 855136.26 | H30: 151311.1 | I30: 129549.11 | K30: 749595.43 | L30: 2.6726427 | N30: 885889.82 | O30: 463867.75 | P30: 345344.4 | Q30: 742979.77 | R30: 809212.15 | S30: -66232.382 | T30: -49157.468 | V30: 8110919.9 | W30: 542579.61 | X30: 422398.6 | Y30: 879899.49 | Z30: 964978.21 | AA30: -85078.717 | AB30: 17361.358 | AE30: =W30/Z30 | AF30: =X30/Z30 | AH30: =X30/$Q30 | AI30: =D30/$Q30
A31: =EDATE(A30, 3) | B31: Jul-Sep 2007 | C31: 27742424 | D31: 331586.48 | E31: 563019.36 | F31: 1001968.6 | G31: 894605.84 | H31: 107362.72 | I31: 74741.097 | K31: 710882.3 | L31: 2.5277102 | N31: 866409.53 | O31: 451880.13 | P31: 302953.93 | Q31: 742795.7 | R31: 754834.06 | S31: -12038.357 | T31: -1950.767 | V31: 8127670.6 | W31: 550088.43 | X31: 411209.22 | Y31: 865973.29 | Z31: 961297.65 | AA31: -95324.362 | AB31: 12849.67 | AE31: =W31/Z31 | AF31: =X31/Z31 | AH31: =X31/$Q31 | AI31: =D31/$Q31
A32: =EDATE(A31, 3) | B32: Oct-Dec 2007 | C32: 27876285 | D32: 318118.22 | E32: 562923.49 | F32: 1041272.8 | G32: 881041.7 | H32: 160231.13 | I32: 146447.03 | K32: 734951.62 | L32: 2.5996791 | N32: 817640.56 | O32: 497748.48 | P32: 317848.41 | Q32: 755777.96 | R32: 815596.89 | S32: -59818.929 | T32: -38767.112 | V32: 8096525 | W32: 543524.35 | X32: 437659.75 | Y32: 880771.9 | Z32: 981184.09 | AA32: -100412.2 | AB32: -29688.914 | AE32: =W32/Z32 | AF32: =X32/Z32 | AH32: =X32/$Q32 | AI32: =D32/$Q32
A33: =EDATE(A32, 3) | B33: Jan-Mar 2008 | C33: 27965849 | D33: 330631.22 | E33: 590213.28 | F33: 1042197.4 | G33: 920844.5 | H33: 121352.85 | I33: 83899.044 | K33: 792781.74 | L33: 2.7953278 | N33: 852496.73 | O33: 471023.36 | P33: 282930.82 | Q33: 737869.67 | R33: 753954.18 | S33: -16084.514 | T33: 10230.345 | V33: 8080394.4 | W33: 571174 | X33: 407238.45 | Y33: 873144.11 | Z33: 978412.45 | AA33: -105268.34 | AB33: -15430.389 | AE33: =W33/Z33 | AF33: =X33/Z33 | AH33: =X33/$Q33 | AI33: =D33/$Q33
A34: =EDATE(A33, 3) | B34: Apr-Jun 2008 | C34: 28060992 | D34: 342192.98 | E34: 555586.07 | F34: 946190.94 | G34: 897779.05 | H34: 48411.893 | I34: 27298.56 | K34: 706835.26 | L34: 2.4825341 | N34: 862364.73 | O34: 436075.36 | P34: 312722.31 | Q34: 791759.96 | R34: 748797.67 | S34: 42962.29 | T34: 55846.287 | V34: 8111584.1 | W34: 510115.58 | X34: 449566.98 | Y34: 868308.38 | Z34: 959682.56 | AA34: -91374.183 | AB34: -4377.8469 | AE34: =W34/Z34 | AF34: =X34/Z34 | AH34: =X34/$Q34 | AI34: =D34/$Q34
A35: =EDATE(A34, 3) | B35: Jul-Sep 2008 | C35: 27986884 | D35: 421748.6 | E35: 561114.33 | F35: 909037.03 | G35: 982862.94 | H35: -73825.903 | I35: -140690.8 | K35: 651046.92 | L35: 2.2924789 | N35: 892821.52 | O35: 401034.54 | P35: 355696.75 | Q35: 889231.74 | R35: 756731.29 | S35: 132500.45 | T35: 155996.58 | V35: 8058873.3 | W35: 508002.49 | X35: 467483.14 | Y35: 916811.08 | Z35: 975485.63 | AA35: -58674.543 | AB35: 45219.219 | AE35: =W35/Z35 | AF35: =X35/Z35 | AH35: =X35/$Q35 | AI35: =D35/$Q35
A36: =EDATE(A35, 3) | B36: Oct-Dec 2008 | C36: 27820108 | D36: 464872.17 | E36: 580473.83 | F36: 1003944.2 | G36: 1045346 | H36: -41401.75 | I36: -67188.031 | K36: 611098.14 | L36: 2.1625038 | N36: 1005920.6 | O36: 482833.44 | P36: 334563.57 | Q36: 951085.33 | R36: 817397.01 | S36: 133688.32 | T36: 165048.26 | V36: 8016537.8 | W36: 521110.81 | X36: 486213.16 | Y36: 915037.4 | Z36: 1007324 | AA36: -92286.574 | AB36: -46117.224 | AE36: =W36/Z36 | AF36: =X36/Z36 | AH36: =X36/$Q36 | AI36: =D36/$Q36
A37: =EDATE(A36, 3) | B37: Jan-Mar 2009 | C37: 27738572 | D37: 536333.45 | E37: 475731.04 | F37: 895436.81 | G37: 1012064.5 | H37: -116627.67 | I37: -162915.65 | K37: 527847.69 | L37: 1.8723512 | N37: 1191275.8 | O37: 438653.07 | P37: 350836.76 | Q37: 989369.54 | R37: 789489.83 | S37: 199879.71 | T37: 228787.7 | V37: 8113362.1 | W37: 456783.75 | X37: 453036.09 | Y37: 826567.8 | Z37: 909819.84 | AA37: -83252.038 | AB37: -14171.052 | AE37: =W37/Z37 | AF37: =X37/Z37 | AH37: =X37/$Q37 | AI37: =D37/$Q37
... A103: =EDATE(A102, 3) | B103: Jul-Sep 2025 | C103: 31589422 | D103: 367040.93 | E103: 571988.27 | F103: 1022842.2 | G103: 939029.2 | H103: 83812.989 | I103: -41466.414 | K103: 708308.18 | L103: 2.1787355 | N103: 877561.84 | O103: 422027.89 | P103: 337544.63 | Q103: 838478.19 | R103: 759572.52 | S103: 78905.666 | T103: 110202 | V103: 7889148.8 | W103: 600814.3 | X103: 471437.26 | Y103: 909532.9 | Z103: 1072251.6 | AA103: -162718.66 | AB103: 6808.4126 | AE103: =W103/Z103 | AF103: =X103/Z103 | AH103: =X103/$Q103 | AI103: =D103/$Q103
B104: 1 Job to job flows refer to those who were employed in both quarters, but who in the latter quarter reported being with their current employer for less than three months, indicating a change of job between the quarters | AG104: 2014-2019 average: | AH104: =AVERAGE(AH61:AH80) | AI104: =AVERAGE(AI61:AI80)
B105: 2 These series were revised from Apr-Jun 2012 to reflect changes to the weighting methodology, resulting in a discontinuity. Further information is available here.
B106: 3 Data from Jan-Mar 2019 are weighted to the same population totals as the quarterly Labour Force Survey estimates, resulting in a discontinuity in these series.
AH107: =SUM(D101:D103)/(SUM($D$101:$D$103)+SUM($X$101:$X$103)) | AI107: =SUM(X101:X103)/(SUM($D$101:$D$103)+SUM($X$101:$X$103))
B108: Quality indicator | AH108: =X103/SUM(X103,D103)
B109: Shaded estimates are based on a small sample size. This may result in less precise estimates, which should be used with caution.
B110: Unshaded estimates are based on a larger sample size. This is likely to result in estimates of higher precision, although they will still be subject to some sampling variability.
B111: .. Estimate has been suppressed on disclosure grounds.

Sheet International Comparisons >>>

Sheet Final Table
A1: OECD Data Explorer • Infra-annual labour statistics
C3: Time period | D3: Unemployment rate (15+1, %) | E3: Employment rate (15-641, %) | F3: Inactivity Rate (15-641, %)
B4: UK | C4: Q3 2025 | D4: 0.05 | E4: 0.75 | F4: 0.21
B5: US | C5: Q3 2025 | D5: 0.043 | E5: 0.716 | F5: 0.251
B6: France | C6: Q2 2025 | D6: 0.075 | E6: 0.696 | F6: 0.247
B7: Germany | C7: Q2 2025 | D7: 0.037 | E7: 0.774 | F7: 0.196
B8: Italy | C8: Q2 2025 | D8: 0.066 | E8: 0.625 | F8: 0.329
B9: Spain | C9: Q2 2025 | D9: 0.105 | E9: 0.669 | F9: 0.252
B10: Canada | C10: Q3 2025 | D10: 0.07 | E10: 0.74 | F10: 0.204
B11: Japan | C11: Q3 2026 | D11: 0.025 | E11: 0.801 | F11: 0.178
B12: Euro Area | C12: Q2 2025 | D12: 0.064 | E12: 0.709 | F12: 0.242

Sheet Unemployment
B1: Infra-annual labour statistics
B2: Age: 15 years or over
B3: Frequency of observation: Quarterly
B4: Measure: Unemployment rate
B5: Unit of measure: Percentage of labour force in the same subgroup, Calendar and seasonally adjusted
B7: Time period | D7: 2024-Q1 | E7: 2024-Q2 | F7: 2024-Q3 | G7: 2024-Q4 | H7: 2025-Q1 | I7: 2025-Q2 | J7: 2025-Q3
B8: Reference area
B9: Canada | D9: 5.9 | E9: 6.3 | F9: 6.566667 | G9: 6.733333 | H9: 6.633333 | I9: 6.933333 | J9: 7.033333
B10: France | D10: 7.460117 | E10: 7.337601 | F10: 7.433329 | G10: 7.319407 | H10: 7.431423 | I10: 7.533759
B11: Germany | D11: 3.262658 | E11: 3.380795 | F11: 3.472289 | G11: 3.370946 | H11: 3.570873 | I11: 3.691198
B12: Italy | D12: 7.210085 | E12: 6.735523 | F12: 6.085654 | G12: 5.963633 | H12: 6.333858 | I12: 6.631587
B13: Japan | D13: 2.566667 | E13: 2.566667 | F13: 2.5 | G13: 2.5 | H13: 2.466667 | I13: 2.5 | J13: 2.5
B14: Spain | D14: 11.68634 | E14: 11.50025 | F14: 11.29459 | G14: 10.89764 | H14: 10.78951 | I14: 10.49921
B15: United Kingdom | D15: 4.341712 | E15: 4.196704 | F15: 4.2713 | G15: 4.382324 | H15: 4.535109 | I15: 4.659199 | J15: 4.972069
B16: United States | D16: 3.833333 | E16: 4 | F16: 4.166667 | G16: 4.133333 | H16: 4.1 | I16: 4.166667 | J16: 4.3
B17: Euro area (20 countries) | D17: 6.531428 | E17: 6.380807 | F17: 6.374712 | G17: 6.125721 | H17: 6.347013 | I17: 6.369351
B19: © Terms & conditions | K19: Infra-annual labour statistics

Sheet Employment
B1: Infra-annual labour statistics
B2: Age: From 15 to 64 years
B3: Frequency of observation: Quarterly
B4: Measure: Employment rate
B5: Unit of measure: Percentage of working age population in the same subgroup, Calendar and seasonally adjusted
B7: Time period | D7: 2024-Q1 | E7: 2024-Q2 | F7: 2024-Q3 | G7: 2024-Q4 | H7: 2025-Q1 | I7: 2025-Q2 | J7: 2025-Q3
B8: Reference area
B9: Canada | D9: 75.2 | E9: 74.86667 | F9: 74.33334 | G9: 74.2 | H9: 74.33334 | I9: 74.13333 | J9: 73.96667
B10: France | D10: 68.68109 | E10: 68.95626 | F10: 69.26001 | G10: 68.96091 | H10: 69.34494 | I10: 69.59042
B11: Germany | D11: 77.2682 | E11: 77.48019 | F11: 77.36938 | G11: 77.6973 | H11: 77.55413 | I11: 77.37474
B12: Italy | D12: 61.99093 | E12: 62.06493 | F12: 62.48814 | G12: 62.17719 | H12: 62.85172 | I12: 62.5015
B13: Japan | D13: 79.15117 | E13: 79.27747 | F13: 79.55813 | G13: 79.76027 | H13: 79.8768 | I13: 80.09341 | J13: 80.09509
B14: Spain | D14: 65.91387 | E14: 65.96774 | F14: 66.10919 | G14: 66.39844 | H14: 66.58608 | I14: 66.91159
B15: United Kingdom | D15: 74.5 | E15: 74.6 | F15: 74.9 | G15: 75 | H15: 75 | I15: 75.3 | J15: 75
B16: United States | D16: 71.94076 | E16: 71.88129 | F16: 71.83945 | G16: 71.7635 | H16: 71.86433 | I16: 71.75611 | J16: 71.6202
B17: Euro area (20 countries) | D17: 70.27025 | E17: 70.48885 | F17: 70.47901 | G17: 70.63184 | H17: 70.78915 | I17: 70.8757
B19: © Terms & conditions | K19: Infra-annual labour statistics

Sheet Inactivity
B1: Infra-annual labour statistics
B2: Age: From 15 to 64 years
B3: Frequency of observation: Quarterly
B4: Measure: Inactivity rate
B5: Unit of measure: Percentage of working age population in the same subgroup, Calendar and seasonally adjusted
B7: Time period | D7: 2024-Q1 | E7: 2024-Q2 | F7: 2024-Q3 | G7: 2024-Q4 | H7: 2025-Q1 | I7: 2025-Q2 | J7: 2025-Q3
B8: Reference area
B9: Canada | D9: 19.99503 | E9: 20.05516 | F9: 20.38306 | G9: 20.41497 | H9: 20.20076 | I9: 20.2871 | J9: 20.36548
B10: France | D10: 25.71629 | E10: 25.51469 | F10: 25.097 | G10: 25.54247 | H10: 25.04611 | I10: 24.67437
B11: Germany | D11: 20.05347 | E11: 19.73733 | F11: 19.77225 | G11: 19.50614 | H11: 19.50209 | I11: 19.57276
B12: Italy | D12: 33.08072 | E12: 33.349 | F12: 33.36731 | G12: 33.77273 | H12: 32.80219 | I12: 32.94898
B13: Japan | D13: 18.6463 | E13: 18.51271 | F13: 18.27169 | G13: 18.11496 | H13: 17.98372 | I13: 17.78764 | J13: 17.77443
B14: Spain | D14: 25.32893 | E14: 25.3481 | F14: 25.39102 | G14: 25.4638 | H14: 25.30016 | I14: 25.16554
B15: United Kingdom | D15: 22.06724 | E15: 22.08912 | F15: 21.64368 | G15: 21.54378 | H15: 21.37431 | I15: 20.97028 | J15: 20.95014
B16: United States | D16: 25.15181 | E16: 25.09198 | F16: 25.00768 | G16: 25.06466 | H16: 24.98564 | I16: 25.03471 | J16: 25.08722
B17: Euro area (20 countries) | D17: 24.71453 | E17: 24.60444 | F17: 24.62069 | G17: 24.67089 | H17: 24.31433 | I17: 24.19838
B19: © Terms & conditions | K19: Infra-annual labour statistics

Sheet Charts >>>

Sheet Real Wages Chart
A1: Date | C1: Total Pay | D1: Regular Pay
A2: 36526 | C2: ='AWE Real_CPI'!B17 | D2: ='AWE Real_CPI'!F17
A3: 36557 | C3: ='AWE Real_CPI'!B18 | D3: ='AWE Real_CPI'!F18
A4: 36586 | C4: ='AWE Real_CPI'!B19 | D4: ='AWE Real_CPI'!F19
A5: 36617 | C5: ='AWE Real_CPI'!B20 | D5: ='AWE Real_CPI'!F20
A6: 36647 | C6: ='AWE Real_CPI'!B21 | D6: ='AWE Real_CPI'!F21
A7: 36678 | C7: ='AWE Real_CPI'!B22 | D7: ='AWE Real_CPI'!F22
A8: 36708 | C8: ='AWE Real_CPI'!B23 | D8: ='AWE Real_CPI'!F23
A9: 36739 | C9: ='AWE Real_CPI'!B24 | D9: ='AWE Real_CPI'!F24
A10: 36770 | C10: ='AWE Real_CPI'!B25 | D10: ='AWE Real_CPI'!F25
A11: 36800 | C11: ='AWE Real_CPI'!B26 | D11: ='AWE Real_CPI'!F26
A12: 36831 | C12: ='AWE Real_CPI'!B27 | D12: ='AWE Real_CPI'!F27
A13: 36861 | C13: ='AWE Real_CPI'!B28 | D13: ='AWE Real_CPI'!F28
... A307: 45809 | C307: ='AWE Real_CPI'!B322 | D307: ='AWE Real_CPI'!F322

Sheet Emp, Unemp & Inac Chart
A1: Quarter | B1: Year | C1: Employment Rate | D1: Unemployment Rate | E1: Inactivity Rate | F1: Employment Level | I1: 16-64 Employment rate - check | L1: 16+ Unemployment rate - check
A2: Jan-Mar 2010 | B2: =RIGHT(A2, LEN(A2) - 8) | C2: ='2'!K232 | D2: ='2'!E232 | E2: ='2'!Q232 | F2: 29012557 | G2: =F2/1000000 | I2: 70.195062 | J2: =I2-C2 | L2: 8.0095867 | M2: =L2-D2
A3: Feb-Apr 2010 | B3: =RIGHT(A3, LEN(A3) - 8) | C3: ='2'!K233 | D3: ='2'!E233 | E3: ='2'!Q233 | F3: 29047598 | G3: =F3/1000000 | I3: 70.213583 | J3: =I3-C3 | L3: 7.9523754 | M3: =L3-D3
A4: Mar-May 2010 | B4: =RIGHT(A4, LEN(A4) - 8) | C4: ='2'!K234 | D4: ='2'!E234 | E4: ='2'!Q234 | F4: 29143687 | G4: =F4/1000000 | I4: 70.397616 | J4: =I4-C4 | L4: 7.922887 | M4: =L4-D4
A5: Apr-Jun 2010 | B5: =RIGHT(A5, LEN(A5) - 8) | C5: ='2'!K235 | D5: ='2'!E235 | E5: ='2'!Q235 | F5: 29191923 | G5: =F5/1000000 | I5: 70.422667 | J5: =I5-C5 | L5: 7.8523516 | M5: =L5-D5
A6: May-Jul 2010 | B6: =RIGHT(A6, LEN(A6) - 8) | C6: ='2'!K236 | D6: ='2'!E236 | E6: ='2'!Q236 | F6: 29325226 | G6: =F6/1000000 | I6: 70.621486 | J6: =I6-C6 | L6: 7.8203224 | M6: =L6-D6
A7: Jun-Aug 2010 | B7: =RIGHT(A7, LEN(A7) - 8) | C7: ='2'!K237 | D7: ='2'!E237 | E7: ='2'!Q237 | F7: 29339443 | G7: =F7/1000000 | I7: 70.638594 | J7: =I7-C7 | L7: 7.7820184 | M7: =L7-D7
A8: Jul-Sep 2010 | B8: =RIGHT(A8, LEN(A8) - 8) | C8: ='2'!K238 | D8: ='2'!E238 | E8: ='2'!Q238 | F8: 29385322 | G8: =F8/1000000 | I8: 70.7054 | J8: =I8-C8 | L8: 7.7546458 | M8: =L8-D8
A9: Aug-Oct 2010 | B9: =RIGHT(A9, LEN(A9) - 8) | C9: ='2'!K239 | D9: ='2'!E239 | E9: ='2'!Q239 | F9: 29307906 | G9: =F9/1000000 | I9: 70.490409 | J9: =I9-C9 | L9: 7.8971509 | M9: =L9-D9
A10: Sep-Nov 2010 | B10: =RIGHT(A10, LEN(A10) - 8) | C10: ='2'!K240 | D10: ='2'!E240 | E10: ='2'!Q240 | F10: 29283658 | G10: =F10/1000000 | I10: 70.338702 | J10: =I10-C10 | L10: 7.8710967 | M10: =L10-D10
A11: Oct-Dec 2010 | B11: =RIGHT(A11, LEN(A11) - 8) | C11: ='2'!K241 | D11: ='2'!E241 | E11: ='2'!Q241 | F11: 29324411 | G11: =F11/1000000 | I11: 70.389849 | J11: =I11-C11 | L11: 7.8632686 | M11: =L11-D11
A12: Nov-Jan 2011 | B12: =RIGHT(A12, LEN(A12) - 8) | C12: ='2'!K242 | D12: ='2'!E242 | E12: ='2'!Q242 | F12: 29391159 | G12: =F12/1000000 | I12: 70.468865 | J12: =I12-C12 | L12: 7.9086112 | M12: =L12-D12
A13: Dec-Feb 2011 | B13: =RIGHT(A13, LEN(A13) - 8) | C13: ='2'!K243 | D13: ='2'!E243 | E13: ='2'!Q243 | F13: 29441982 | G13: =F13/1000000 | I13: 70.586397 | J13: =I13-C13 | L13: 7.8026593 | M13: =L13-D13
... A128: Jul-Sep 2020 | B128: =RIGHT(A128, LEN(A128) - 8) | C128: ='2'!K358 | D128: ='2'!E358 | E128: ='2'!Q358 | F128: 32353994 | G128: =F128/1000000 | I128: 74.529709 | J128: =I128-C128 | L128: 4.9864893 | M128: =L128-D128
A129: Aug-Oct 2020 | B129: =RIGHT(A129, LEN(A129) - 8) | C129: ='2'!K359 | D129: ='2'!E359 | E129: ='2'!Q359 | F129: 32335267 | G129: =F129/1000000 | I129: 74.446638 | J129: =I129-C129 | L129: 5.1657493 | M129: =L129-D129 | O129: Employment Rate (16-64, Seasonally Adjusted (%))
A130: Sep-Nov 2020 | B130: =RIGHT(A130, LEN(A130) - 8) | C130: ='2'!K360 | D130: ='2'!E360 | E130: ='2'!Q360 | F130: 32338613 | G130: =F130/1000000 | I130: 74.460382 | J130: =I130-C130 | L130: 5.2380391 | M130: =L130-D130
A131: Oct-Dec 2020 | B131: =RIGHT(A131, LEN(A131) - 8) | C131: ='2'!K361 | D131: ='2'!E361 | E131: ='2'!Q361 | F131: 32197966 | G131: =F131/1000000 | I131: 74.171573 | J131: =I131-C131 | L131: 5.3356019 | M131: =L131-D131
A132: Nov-Jan 2021 | B132: =RIGHT(A132, LEN(A132) - 8) | C132: ='2'!K362 | D132: ='2'!E362 | E132: ='2'!Q362 | F132: 32170466 | G132: =F132/1000000 | I132: 74.149655 | J132: =I132-C132 | L132: 5.2560059 | M132: =L132-D132
A133: Dec-Feb 2021 | B133: =RIGHT(A133, LEN(A133) - 8) | C133: ='2'!K363 | D133: ='2'!E363 | E133: ='2'!Q363 | F133: 32218137 | G133: =F133/1000000 | I133: 74.275536 | J133: =I133-C133 | L133: 5.1766201 | M133: =L133-D133
A134: Jan-Mar 2021 | B134: =RIGHT(A134, LEN(A134) - 8) | C134: ='2'!K364 | D134: ='2'!E364 | E134: ='2'!Q364 | F134: 32220977 | G134: =F134/1000000 | I134: 74.248377 | J134: =I134-C134 | L134: 5.0611394 | M134: =L134-D134
A135: Feb-Apr 2021 | B135: =RIGHT(A135, LEN(A135) - 8) | C135: ='2'!K365 | D135: ='2'!E365 | E135: ='2'!Q365 | F135: 32236308 | G135: =F135/1000000 | I135: 74.268201 | J135: =I135-C135 | L135: 5.0108705 | M135: =L135-D135
A136: Mar-May 2021 | B136: =RIGHT(A136, LEN(A136) - 8) | C136: ='2'!K366 | D136: ='2'!E366 | E136: ='2'!Q366 | F136: 32259597 | G136: =F136/1000000 | I136: 74.322069 | J136: =I136-C136 | L136: 4.9811901 | M136: =L136-D136
A137: Apr-Jun 2021 | B137: =RIGHT(A137, LEN(A137) - 8) | C137: ='2'!K367 | D137: ='2'!E367 | E137: ='2'!Q367 | F137: 32376949 | G137: =F137/1000000 | I137: 74.584293 | J137: =I137-C137 | L137: 4.8395853 | M137: =L137-D137
A138: May-Jul 2021 | B138: =RIGHT(A138, LEN(A138) - 8) | C138: ='2'!K368 | D138: ='2'!E368 | E138: ='2'!Q368 | F138: 32489468 | G138: =F138/1000000 | I138: 74.701663 | J138: =I138-C138 | L138: 4.7044345 | M138: =L138-D138
A139: Jun-Aug 2021 | B139: =RIGHT(A139, LEN(A139) - 8) | C139: ='2'!K369 | D139: ='2'!E369 | E139: ='2'!Q369 | F139: 32577076 | G139: =F139/1000000 | I139: 74.795856 | J139: =I139-C139 | L139: 4.5680071 | M139: =L139-D139
A140: Jul-Sep 2021 | B140: =RIGHT(A140, LEN(A140) - 8) | C140: ='2'!K370 | D140: ='2'!E370 | E140: ='2'!Q370 | F140: 32687486 | G140: =F140/1000000 | I140: 74.884968 | J140: =I140-C140 | L140: 4.3900589 | M140: =L140-D140
A141: Aug-Oct 2021 | B141: =RIGHT(A141, LEN(A141) - 8) | C141: ='2'!K371 | D141: ='2'!E371 | E141: ='2'!Q371 | F141: 32686197 | G141: =F141/1000000 | I141: 74.928227 | J141: =I141-C141 | L141: 4.3133335 | M141: =L141-D141
... A152: Jul-Sep 2022 | B152: =RIGHT(A152, LEN(A152) - 8) | C152: ='2'!K382 | D152: ='2'!E382 | E152: ='2'!Q382 | F152: 32915868 | G152: =F152/1000000 | I152: 74.969451 | J152: =I152-C152 | L152: 3.7521614 | M152: =L152-D152
A153: Aug-Oct 2022 | B153: =RIGHT(A153, LEN(A153) - 8) | C153: ='2'!K383 | D153: ='2'!E383 | E153: ='2'!Q383 | F153: 32951175 | G153: =F153/1000000 | I153: 75.043155 | J153: =I153-C153 | L153: 3.8567966 | M153: =L153-D153 | O153: Unemployment rate (16+, seasonally adjusted)
A154: Sep-Nov 2022 | B154: =RIGHT(A154, LEN(A154) - 8) | C154: ='2'!K384 | D154: ='2'!E384 | E154: ='2'!Q384 | F154: 33076042 | G154: =F154/1000000 | I154: 75.236534 | J154: =I154-C154 | L154: 3.8031557 | M154: =L154-D154
A155: Oct-Dec 2022 | B155: =RIGHT(A155, LEN(A155) - 8) | C155: ='2'!K385 | D155: ='2'!E385 | E155: ='2'!Q385 | F155: 33066998 | G155: =F155/1000000 | I155: 75.18609 | J155: =I155-C155 | L155: 3.8738682 | M155: =L155-D155
A156: Nov-Jan 2023 | B156: =RIGHT(A156, LEN(A156) - 8) | C156: ='2'!K386 | D156: ='2'!E386 | E156: ='2'!Q386 | F156: 33099435 | G156: =F156/1000000 | I156: 75.243637 | J156: =I156-C156 | L156: 3.819651 | M156: =L156-D156
A157: Dec-Feb 2023 | B157: =RIGHT(A157, LEN(A157) - 8) | C157: ='2'!K387 | D157: ='2'!E387 | E157: ='2'!Q387 | F157: 33175551 | G157: =F157/1000000 | I157: 75.238481 | J157: =I157-C157 | L157: 3.899553 | M157: =L157-D157
A158: Jan-Mar 2023 | B158: =RIGHT(A158, LEN(A158) - 8) | C158: ='2'!K388 | D158: ='2'!E388 | E158: ='2'!Q388 | F158: 33200617 | G158: =F158/1000000 | I158: 75.278703 | J158: =I158-C158 | L158: 3.9991662 | M158: =L158-D158
A159: Feb-Apr 2023 | B159: =RIGHT(A159, LEN(A159) - 8) | C159: ='2'!K389 | D159: ='2'!E389 | E159: ='2'!Q389 | F159: 33325668 | G159: =F159/1000000 | I159: 75.43069 | J159: =I159-C159 | L159: 3.9016814 | M159: =L159-D159
A160: Mar-May 2023 | B160: =RIGHT(A160, LEN(A160) - 8) | C160: ='2'!K390 | D160: ='2'!E390 | E160: ='2'!Q390 | F160: 33310557 | G160: =F160/1000000 | I160: 75.460293 | J160: =I160-C160 | L160: 4.0197231 | M160: =L160-D160
A161: Apr-Jun 2023 | B161: =RIGHT(A161, LEN(A161) - 8) | C161: ='2'!K391 | D161: ='2'!E391 | E161: ='2'!Q391 | F161: 33162821 | G161: =F161/1000000 | I161: 75.169188 | J161: =I161-C161 | L161: 4.2180538 | M161: =L161-D161
A162: May-Jul 2023 | B162: =RIGHT(A162, LEN(A162) - 8) | C162: ='2'!K392 | D162: ='2'!E392 | E162: ='2'!Q392 | F162: 33082007 | G162: =F162/1000000 | I162: 74.911923 | J162: =I162-C162 | L162: 4.3275575 | M162: =L162-D162
A163: Jun-Aug 2023 | B163: =RIGHT(A163, LEN(A163) - 8) | C163: ='2'!K393 | D163: ='2'!E393 | E163: ='2'!Q393 | F163: 33027893 | G163: =F163/1000000 | I163: 74.744985 | J163: =I163-C163 | L163: 4.212086 | M163: =L163-D163
A164: Jul-Sep 2023 | B164: =RIGHT(A164, LEN(A164) - 8) | C164: ='2'!K394 | D164: ='2'!E394 | E164: ='2'!Q394 | F164: 33102186 | G164: =F164/1000000 | I164: 74.846469 | J164: =I164-C164 | L164: 4.0762415 | M164: =L164-D164
A165: Aug-Oct 2023 | B165: =RIGHT(A165, LEN(A165) - 8) | C165: ='2'!K395 | D165: ='2'!E395 | E165: ='2'!Q395 | F165: 33195699 | G165: =F165/1000000 | I165: 75.062677 | J165: =I165-C165 | L165: 3.9545749 | M165: =L165-D165
... A168: Nov-Jan 2024 | B168: =RIGHT(A168, LEN(A168) - 8) | C168: ='2'!K398 | D168: ='2'!E398 | E168: ='2'!Q398 | F168: 33174976 | G168: =F168/1000000 | I168: 74.845424 | J168: =I168-C168 | L168: 3.9813393 | M168: =L168-D168
A169: Dec-Feb 2024 | B169: =RIGHT(A169, LEN(A169) - 8) | C169: ='2'!K399 | D169: ='2'!E399 | E169: ='2'!Q399 | I169: 74.487887 | J169: =I169-C169 | L169: 4.1839209 | M169: =L169-D169
A170: Jan-Mar 2024 | B170: =RIGHT(A170, LEN(A170) - 8) | C170: ='2'!K400 | D170: ='2'!E400 | E170: ='2'!Q400
A171: Feb-Apr 2024 | B171: =RIGHT(A171, LEN(A171) - 8) | C171: ='2'!K401 | D171: ='2'!E401 | E171: ='2'!Q401
A172: Mar-May 2024 | B172: =RIGHT(A172, LEN(A172) - 8) | C172: ='2'!K402 | D172: ='2'!E402 | E172: ='2'!Q402
A173: Apr-Jun 2024 | B173: =RIGHT(A173, LEN(A173) - 8) | C173: ='2'!K403 | D173: ='2'!E403 | E173: ='2'!Q403
A174: May-Jul 2024 | B174: =RIGHT(A174, LEN(A174) - 8) | C174: ='2'!K404 | D174: ='2'!E404 | E174: ='2'!Q404 | O174: Inactivity Rate (16-64, Seasonally Adjusted (%))
A175: Jun-Aug 2024 | B175: =RIGHT(A175, LEN(A175) - 8) | C175: ='2'!K405 | D175: ='2'!E405 | E175: ='2'!Q405
A176: Jul-Sep 2024 | B176: =RIGHT(A176, LEN(A176) - 8) | C176: ='2'!K406 | D176: ='2'!E406 | E176: ='2'!Q406
A177: Aug-Oct 2024 | B177: =RIGHT(A177, LEN(A177) - 8) | C177: ='2'!K407 | D177: ='2'!E407 | E177: ='2'!Q407
A178: Sep-Nov 2024 | B178: =RIGHT(A178, LEN(A178) - 8) | C178: ='2'!K408 | D178: ='2'!E408 | E178: ='2'!Q408
A179: Oct-Dec 2024 | B179: =RIGHT(A179, LEN(A179) - 8) | C179: ='2'!K409 | D179: ='2'!E409 | E179: ='2'!Q409
A180: Nov-Jan 2025 | B180: =RIGHT(A180, LEN(A180) - 8) | C180: ='2'!K410 | D180: ='2'!E410 | E180: ='2'!Q410
A181: Dec-Feb 2025 | B181: =RIGHT(A181, LEN(A181) - 8) | C181: ='2'!K411 | D181: ='2'!E411 | E181: ='2'!Q411
A182: Jan-Mar 2025 | B182: =RIGHT(A182, LEN(A182) - 8) | C182: ='2'!K412 | D182: ='2'!E412 | E182: ='2'!Q412
A183: Feb-Apr 2025 | B183: =RIGHT(A183, LEN(A183) - 8) | C183: ='2'!K413 | D183: ='2'!E413 | E183: ='2'!Q413
A184: Mar-May 2025 | B184: =RIGHT(A184, LEN(A184) - 8) | C184: ='2'!K414 | D184: ='2'!E414 | E184: ='2'!Q414
A185: Apr-Jun 2025 | B185: =RIGHT(A185, LEN(A185) - 8) | C185: ='2'!K415 | D185: ='2'!E415 | E185: ='2'!Q415
A186: May-Jul 2025 | B186: =RIGHT(A186, LEN(A186) - 8) | C186: ='2'!K416 | D186: ='2'!E416 | E186: ='2'!Q416
... A189: Aug-Oct 2025 | B189: =RIGHT(A189, LEN(A189) - 8) | C189: ='2'!K419 | D189: ='2'!E419 | E189: ='2'!Q419

Sheet Vacancies Chart
C1: ='20'!C16
A2: =RIGHT(B2,4) | B2: ='20'!A17 | C2: ='20'!C17
A3: =RIGHT(B3,4) | B3: ='20'!A18 | C3: ='20'!C18
A4: =RIGHT(B4,4) | B4: ='20'!A19 | C4: ='20'!C19
A5: =RIGHT(B5,4) | B5: ='20'!A20 | C5: ='20'!C20
A6: =RIGHT(B6,4) | B6: ='20'!A21 | C6: ='20'!C21
A7: =RIGHT(B7,4) | B7: ='20'!A22 | C7: ='20'!C22
A8: =RIGHT(B8,4) | B8: ='20'!A23 | C8: ='20'!C23
A9: =RIGHT(B9,4) | B9: ='20'!A24 | C9: ='20'!C24
A10: =RIGHT(B10,4) | B10: ='20'!A25 | C10: ='20'!C25
A11: =RIGHT(B11,4) | B11: ='20'!A26 | C11: ='20'!C26
A12: =RIGHT(B12,4) | B12: ='20'!A27 | C12: ='20'!C27
A13: =RIGHT(B13,4) | B13: ='20'!A28 | C13: ='20'!C28
... A294: =RIGHT(B294,4) | B294: ='20'!A309 | C294: ='20'!C309

Sheet Payrolled Employees Chart
A2: ='1. Payrolled employees (UK)'!A10 | B2: ='1. Payrolled employees (UK)'!B10
A3: =DATEVALUE('1. Payrolled employees (UK)'!A11) | B3: ='1. Payrolled employees (UK)'!B11 | C3: Max | D3: =MAX($B$3:$B$139)
A4: =DATEVALUE('1. Payrolled employees (UK)'!A12) | B4: ='1. Payrolled employees (UK)'!B12
A5: =DATEVALUE('1. Payrolled employees (UK)'!A13) | B5: ='1. Payrolled employees (UK)'!B13 | D5: Number of Payrolled Employees
A6: =DATEVALUE('1. Payrolled employees (UK)'!A14) | B6: ='1. Payrolled employees (UK)'!B14
A7: =DATEVALUE('1. Payrolled employees (UK)'!A15) | B7: ='1. Payrolled employees (UK)'!B15
A8: =DATEVALUE('1. Payrolled employees (UK)'!A16) | B8: ='1. Payrolled employees (UK)'!B16
A9: =DATEVALUE('1. Payrolled employees (UK)'!A17) | B9: ='1. Payrolled employees (UK)'!B17
A10: =DATEVALUE('1. Payrolled employees (UK)'!A18) | B10: ='1. Payrolled employees (UK)'!B18
A11: =DATEVALUE('1. Payrolled employees (UK)'!A19) | B11: ='1. Payrolled employees (UK)'!B19
A12: =DATEVALUE('1. Payrolled employees (UK)'!A20) | B12: ='1. Payrolled employees (UK)'!B20
A13: =DATEVALUE('1. Payrolled employees (UK)'!A21) | B13: ='1. Payrolled employees (UK)'!B21
A14: =DATEVALUE('1. Payrolled employees (UK)'!A22) | B14: ='1. Payrolled employees (UK)'!B22
A15: =DATEVALUE('1. Payrolled employees (UK)'!A23) | B15: ='1. Payrolled employees (UK)'!B23
A16: =DATEVALUE('1. Payrolled employees (UK)'!A24) | B16: ='1. Payrolled employees (UK)'!B24
A17: =DATEVALUE('1. Payrolled employees (UK)'!A25) | B17: ='1. Payrolled employees (UK)'!B25
... A139: =DATEVALUE('1. Payrolled employees (UK)'!A147) | B139: ='1. Payrolled employees (UK)'!B147
